Workbook

Sheet Global IP Scan Kanban Board
C24: In Progress (WIP Limits)
B25: Local Coordinator | C25: Preperation | D25: Baseline ID | E25: Incremental ID | F25: Communication | G25: Total
A26: GTLC China | B26: Amy | C26: 1 | D26: 1 | E26: 5 | F26: 1 | G26: =SUM(C26:F26) -> 8
A27: GTLC India | B27: Komal | C27: 5 | D27: 2 | E27: 8 | F27: 4 | G27: =SUM(C27:F27) -> 19
A28: GTLC Germany | B28: Klaus | C28: 1 | D28: 1 | E28: 2 | F28: 2 | G28: =SUM(C28:F28) -> 6
A29: GTLC Canada | B29: Raj | C29: 5 | D29: 5 | E29: 10 | F29: 5 | G29: =SUM(C29:F29) -> 25
A31: **The above table shows the WIP Limits ONLY. To find out the WIP for a site, refer to the Local Kanban Board**

Sheet Data
B1: In Progress | C1: Done
A2: China | B2: =COUNTIFS(#REF!,"GTLC China",#REF!,"In Progress") -> #REF! | C2: =COUNTIFS(#REF!,"GTLC China",#REF!,"Done") -> #REF!
A3: India | B3: =COUNTIFS(#REF!,"GTLC India",#REF!,"In Progress") -> #REF! | C3: =COUNTIFS(#REF!,"GTLC India",#REF!,"Done") -> #REF!
A4: Germany | B4: =COUNTIFS(#REF!,"GTLC Germany",#REF!,"In Progress") -> #REF! | C4: =COUNTIFS(#REF!,"GTLC Germany",#REF!,"Done") -> #REF!
A5: Canada | B5: =COUNTIFS(#REF!,"GTLC Canada",#REF!,"In Progress") -> #REF! | C5: =COUNTIFS(#REF!,"GTLC Canada",#REF!,"Done") -> #REF!
A6: Global | B6: =SUM(B2:B5) -> #REF! | C6: =SUM(C2:C5) -> #REF!
A9: Backlog
A10: P1 | B10: =COUNTIFS(#REF!,"GLOBAL",#REF!,"P1",#REF!,"backlog") -> #REF!
A11: P2 | B11: =COUNTIFS(#REF!,"GLOBAL",#REF!,"P2",#REF!,"backlog") -> #REF!
A12: P3 | B12: =COUNTIFS(#REF!,"GLOBAL",#REF!,"P3",#REF!,"backlog") -> #REF!
A13: Total | B13: =SUM(B10:B12) -> #REF!
A15: RTC Passed
A16: P1 | B16: =COUNTIFS(#REF!,"RTC Passed",#REF!,"P1") -> #REF!
A17: P2 | B17: =COUNTIFS(#REF!,"RTC Passed",#REF!,"P2") -> #REF!
A18: Total | B18: =SUM(B16:B17) -> #REF!

Sheet Data Validation
A1: Values for Data Validation (do not edit) | B1: Program Category | C1: Delivery Mode | D1: Priority | E1: Severity | F1: Previously Scanned | G1: Scan Category | H1: Location | I1: FOSS Analyst | J1: Owner I-Number mapping | K1: FOSS Scan State | L1: Black Duck Scan | M1: Ticket Tracking Status | N1: Commercial Analyst | O1: Commercial Scan State | P1: Web Service Analyst | Q1: Web Service Scan State | R1: Continuous Scan | S1: L1 Manager | T1: L1 Development Unit | U1: Board Area Member | V1: Board Area
B2: Docker Container | C2: On-Demand (SaaS) | D2: P1 | E2: S1 | F2: Y | G2: Incremental ONLY | H2: GLOBAL | I2: Global | J2: Global | K2: Backlog | L2: Y | M2: Open | N2: Komal | O2: Backlog | P2: Yi Zhang | Q2: Backlog | R2: Y | S2: Fei Yu Xu | T2: Artificial Intelligence | U2: Juergen Mueller | V2: Technology and Innovation
B3: Source Code | C3: On-Premise | D3: P2 | E3: S2 | F3: N | G3: OneTime Scan | H3: GTLC China | I3: Prashant | J3: I536654 | K3: Cancelled | M3: Closed | N3: Yi Zhang | O3: In Progress | P3: Raksha | Q3: In Progress | R3: N | S3: Manoj Swaminathan | T3: ISBN CloudOps Cross COPS
B4: On-Premise | C4: On-Mobile Device | D4: P3 | E4: S3 | H4: GTLC India | I4: RTC Passed | J4: RTC Passed | K4: In Progress | N4: Raksha | O4: Done | P4: Yash | Q4: Done | S4: Muhammad Alam | T4: ISBN Executive
B5: On-Mobile Device | E5: S4 | H5: GTLC Germany | I5: Amy | J5: I076757 | K5: Done | N5: ChangFei | O5: N/A | P5: Komal | Q5: N/A | S5: Florian Heretsch | T5: PE MXE Mgmt
B6: ATS | H6: GTLC Canada | I6: Arshia | J6: I557608 | K6: RTC Passed | L6: N | N6: Yi Zhang | S6: Gary Slater | T6: Global Cloud Services
B7: Custom Code | H7: GTLC Vietnam | I7: Jessie | J7: I300127 | N7: Yash | S7: Michael Paul Weingartner | T7: SAP BTP Core
B8: On-Demand (SaaS) | H8: RTC Passed | I8: Sarah | J8: I076758 | N8: Raksha | S8: Juergen Kreuziger | T8: SAP HANA Database & Analytics
B9: Outbound OSS | I9: Tina | J9: I076782 | N9: Sarah Li | S9: Sonja Lienard | T9: BTP ABAP Platform Mgmt (SE)
B10: Outbound OEM | I10: Deb | J10: I077275 | N10: Tina Liao | S10: Andrea Fluegel | T10: BTP Core AP Mgmt & COO SE
I11: Alekh | J11: I556028 | N11: N/A | S11: Sina Doebbelin | T11: T&I Board Office
I12: Komal | J12: I321911 | S12: Bhagat Nainani | T12: BTP Core AP Mgmt & COO (US)
I13: Gunter | J13: D038475 | S13: Michael Ameling | T13: Cross Architecture
I14: Klaus | J14: D061043 | S14: Harald Kuck | T14: TI ABAP Platform Mgmt (SE)
I15: Shweta | J15: D059874 | S15: Martin Heinig | T15: New Ventures & Technologies
I16: Brian | J16: I844758 | S16: Irfan Khan | T16: SAP HANA Database & Analytics
I17: Devan | J17: I819681 | S17: Anja Schneider | T17: T&I COO
I18: Erika | J18: I828891 | S18: Meg bear | T18: People | U18: Thomas Saueressig | V18: SAP Product Engineering
I19: Hamad | J19: I831094 | S19: Andreas Heckman | T19: Customer Solution Support and Innovation
I20: Jimmy | J20: I819510 | S20: Peter Pluim | T20: Enterprise Cloud Services
I21: Justine | J21: I822712 | S21: Jan Gilg | T21: SAP S/4 HANA
I22: Matthew | J22: I844765 | S22: Julia Lakatos | T22: SAP Product Engineering Office
I23: Mitch | J23: I830949 | S23: John Wookey | T23: Intelling Spend and Business Network
I24: Siva | J24: I537790 | S24: Bob Stutz | T24: Customer Experience E&O
I25: Sabrina | J25: I822781 | S25: Eva Zauke | T25: SAP Enterprise Adoption
I26: Tes | J26: I830866 | S26: Stefan Stainle | T26: COO & Strategy, SAP Product Engineering
I27: Rajat | J27: I501689 | S27: Philipp Herzig | T27: Product Engineering Intelligent Enterprise and Cross Architecture
I28: Assmitra | J28: I342117 | S28: Jurgen Sattler | T28: One Strike
I29: Ravi | J29: D072009 | S29: Benedikt Lehnert | T29: SAP Design
I30: Gaurisha | J30: I748895 | S30: Dragana Bjelonic | T30: Chief Controlling Ofiicer
... I33: Madhusudanan | J33: I503416 | S33: Christiane Kubach | T33: Executive Comms & Events
I34: Giang | J34: I540507 | S34: Mira Wohlhueter | T34: Executive Comms & Events | U34: Scott Russell | V34: Customer Success
I35: Domenik | J35: I500407 | S35: Eric Stine | T35: Chief of Staff, Customer Success
I36: Raksha | J36: I353860 | S36: Greg Tomb | T36: Solution Area Sales
I37: Yash | J37: I537966 | S37: Steve Shute | T37: Chief Operation Officers, Customer Success
I38: Shivani | J38: I537015 | S38: Thomas Pfiester | T38: CS&D Regions Mgmt MENA
I39: Alekh | J39: I556028 | S39: Thomas Bamberger | T39: Customer Engagement & Experience
I40: Mariem | J40: I556456 | S40: Ken Hamel | T40: Business Operations, Customer Success
I41: Harshal | J41: I557311 | S41: Holger Lemanczyk | T41: Strategy & Transformation, Customer Success
I42: Liye | J42: I853975 | S42: John Graham | T42: Strategy & Transformation, Customer Success
I43: Frazia | J43: I588032 | S43: Uma Rani T M | T43: Strategy & Transformation, Customer Success
I44: Kun | J44: I746175 | S44: Daniel Mueller | T44: Strategy & Transformation, Customer Success
I45: Wilko | J45: I541859 | S45: Sindhu Gangadharan | T45: SAP User Enabl Mgmt SE
I46: Yi Zhang | J46: I559269 | S46: Traci Hughes | T46: HRBP - SAP Americas
... I50: Apoorva | J50: C5367590 | S50: Dominik Metzger | T50: People Growth Management Office UK
I51: Viswa | J51: C5366020
I52: Sandhya | J52: I538189
I53: Alan | J53: I541886 | S53: Mark Gibbs | T53: Greater China, Customer Success
I54: Sabrina | J54: I822781 | S54: Gero Decker | T54: SAP Signavio Product & Engineering
I55: Duane | J55: C5380108 | S55: Brian Duffy | T55: EMEA North, Customer Success
I56: Devanshi | J56: C5380104 | S56: Claudio Muruzabal | T56: EMEA South, Customer Success
I57: Kanika | J57: C5380106 | S57: Hartmut Thomson | T57: MEE, Customer Success
I58: Anh | J58: C5385497 | S58: Augusta Spinelli | T58: Services Head, Southern Europe,MEA
I59: Mengjie | J59: C5390744 | S59: DJ Paoni | T59: North America, Customer Success
I60: Phu | J60: I760461 | S60: Scott Russell | T60: APJ, Customer Success
I61: Ngoc | J61: I758014 | S61: Cristina Palmaka | T61: Latin America, Customer Success
I62: Thao | J62: I758015 | S62: NN | T62: COO People & Operations | U62: Sabine Bendiek | V62: People & Operations
I63: Huu | J63: I758016 | S63: Florian Roth | T63: Intelligent Enterprise Solutions
I64: Dong | J64: I758010 | S64: Benjamin Blau | T64: Transformation Office
I65: Khoi | J65: I758929 | S65: Craig McMahon | T65: Global Performance Organization
I66: Luyen | J66: I516362 | S66: Thorsten Thee | T66: Global Performance Organization
I67: Khoa | J67: I758929 | S67: Matt Angell | T67: Global Strategic Pricing & Commercialization
I68: Hoan | J68: I758150 | S68: Max Wesssel | T68: SAP Learning
I69: Nguyen | J69: I762314 | S69: Carsten Poeschl | T69: Ombudsperson
I70: Yashwant | J70: C5403671 | S70: Fausto Brembilla | T70: Global HR Service Delivery
I71: Arun | J71: C5381614 | S71: NN | T71: People Sustainability
I72: Gayathri | J72: C5385241 | S72: Elke Manjet | T72: Global Talent Attraction
I73: Shreyas | J73: C5385254 | S73: Chetna Singh | T73: Total Rewards
I74: Soumya Pawar | J74: C5385243 | S74: Christian Schmeichel | T74: HR BP for OCEO, T&I & HR
... I77: Sharath | J77: C5385258 | S77: Wolfgang Fassnacht | T77: HR BP for Finance & Administration
I78: Sushma | J78: I773708 | S78: Miriam Kraus | T78: GFA COO | U78: Luka Mucic | V78: Global Finance & Administration
I79: Akash | J79: C5385256 | S79: Jochen Scholten | T79: Global Legal
I80: Iliyan | J80: I757367 | S80: Kirsten Birnbaum | T80: Global Tax
I81: Domenik | J81: I500407 | S81: Steffen Diel | T81: Global Treasury
I82: Arpitha | J82: C5396309 | S82: Stefan Gruber | T82: Investor Relations
I83: Varshitha | J83: C5385242 | S83: Rico Modess | T83: Global Risk & Assurance Services
S84: Daniel Schmid | T84: Sustainability
S85: Joel Bernstein | T85: CFO Customer Success
S86: Christopher Sessar | T86: Corporate Financial Reporting
S87: Mathias Cellarius | T87: Data Protection & Export Controls
S88: Sebastian Behrendt | T88: Global Controlling
S89: Peter David | T89: Global Finance Infrastructure
S90: Rob Bachmann | T90: Qualtrics Finance
S91: Carmen Krueger | T91: Office of the COO, M&S | U91: Julia White | V91: Marketing & Solutions
S92: Heike Neumann | T92: HRBP, M&S
S93: Peter Selfridge | T93: Government Affairs
S94: Oliver Roll | T94: Global Corporate Affairs
S95: Michelle Cooper | T95: Field Marketing & Sponsorships
S96: Jill Popelka | T96: Human Experience Management (HXM) Global Risk & Assurance Services
S97: Tom Lavin | T97: Chief Controlling Officer
S98: Peter Maier | T98: Industries & Customer Advisory
S99: Alison Biggan | T99: Corporate Marketing
S100: Eric van Rossum | T100: SAP S/4HANA, Finance, & Digital Supply Chain (DSC)
S101: Sameer Patel | T101: Customer Experience (CX)
S102: Karina Edmonds | T102: Academies & Univ. Alliances - US | U102: Christian KLEIN | V102: CEO
S103: Sebastian Steinhaeuser | T103: Corporate Portfolio and Strategy to Exec
S104: Stefan Baeuerle | T104: BTP HANA Mgmt Office
S105: Balaji Balasubramanian | T105: BTP HANA Mgmt Office

Sheet Sheet1
A3: TripIt Mobile iOS | B3: Don
A4: TripIt Mobile Android | B4: done
A5: Complete android
A6: complete ios
A7: SAP Concur Mobile iOS | B7: done
A8: SAP Concur Mobile Android | B8: done
A9: SAP Concur Mobile Tencent H1 2026
A13: Philipp Herzig | B13: =VLOOKUP(A13,'Data Validation'!S:T,2,FALSE) -> Product Engineering Intelligent Enterprise and Cross Architecture | C13: Venkatesan, Divya<divya.venkatesan@sap.com | D13: On-Premise | E13: On-Premise | F13: P2 | G13: S2 | H13: Y | I13: Incremental ONLY | J13: FS on K8s Delivery 2609a | K13: 46244 | L13: 46255 | M13: 46268 | AA13: 500000 | AB13: Open | AC13: No | AD13: =IF((AND((AS13-TODAY())<=30,(L13-TODAY())<=0,(F27="P1")))=TRUE,"Yes",IF(AND((AS13-TODAY())<=30,(L13-TODAY())<=0,(F27="P2"))=TRUE,"Yes","No")) -> No | AE13: I758929 | AF13: 21.449057 | AG13: 1.509434 | AH13: =SUM($AG$2:AG13) -> 1.509434 | AI13: 17.449057 | AJ13: 21.449057 | AK13: 46253 | AL13: N | AM13: Y | AN13: =AS13-S13 -> 46267 | AR13: -1 | AS13: 46267

Sheet Active Scans
A1: L1 Manager | B1: L1 Development Unit | C1: Dev Contact | D1: Program Category | E1: Delivery Mode | F1: Priority | G1: Severity | H1: Previously Scanned | I1: Scan Category | J1: Program (Delivery) | K1: Start of Development | L1: End of Development | M1: RTC | N1: Location | O1: FOSS Analyst | P1: FOSS Scan State | Q1: Black Duck Scan | R1: FOSS Scan Assigned | S1: FOSS Scan Closed | T1: Commercial Scan Status | U1: Comm Analyst | V1: CTP Scan Ticket JIRA link | W1: Web Service Scan Status | X1: Web Service Analyst | Y1: WS Scan Ticket JIRA link | Z1: Comments | AA1: SLOC Count | AB1: Tracking System Ticket Status | AC1: RTC Passed | AD1: Recommended to Request Exemption | AE1: Owner # | AF1: Estimated Calendar Week (CW) for the scan to be "In Progress" | AG1: Estimated # of days to complete the first round of scan | AH1: Cumulative Days | AI1: CW to be added to the current CW | AJ1: Estimated CW for scan to be in progress | AK1: Scan Submission Date | AL1: Continuous scan | AM1: Crown Jewel | AN1: Closed within SLA | AO1: Unreviewed components | AP1: Unmatched | AQ1: Snippets | AS1: RDM | AT1: Maintenance
A2: Uma Rani T M | B2: Strategy & Transformation, Customer Success | C2: MEGEVAND,Emmanuel<emmanuel.megevand@sap.com> | D2: Outbound OEM | E2: On-Premise | F2: P1 | G2: S2 | H2: Y | I2: Incremental ONLY | J2: SAP Information Steward 4.3 SP03 | K2: N/A | L2: 46364 | M2: 46387 | N2: GLOBAL | O2: Global | P2: Backlog | Q2: Y | AA2: 500000 | AB2: Open | AC2: No | AD2: Yes | AE2: I762314 | AF2: 8.1962264 | AG2: 1.509434 | AH2: 209.81132 | AI2: 4.1962264 | AJ2: 8.1962264 | AK2: 46154 | AL2: N | AM2: N | AN2: 0 | AS2: 46387
A3: Stefan Steinle | B3: =VLOOKUP(A3,'Data Validation'!S:T,2,FALSE) -> Customer Solution Support and Innovation | C3: Kabadzhova, Kremena <kremena.kabadzhova@sap.com> | D3: Source Code | E3: On-Premise | F3: P2 | G3: S1 | H3: Y | I3: Incremental ONLY | J3: SAP Cloud Appliance Library 4.60 | K3: N/A | L3: 46282 | M3: 46294 | N3: GTLC India | O3: Apoorva | P3: Done | Q3: Y | R3: 46283 | S3: 46293 | AA3: 500000 | AB3: Open | AC3: No | AD3: =IF((AND((AS3-TODAY())<=30,(L3-TODAY())<=0,(F4="P1")))=TRUE,"Yes",IF(AND((AS3-TODAY())<=30,(L3-TODAY())<=0,(F4="P2"))=TRUE,"Yes","No")) -> Yes | AE3: =VLOOKUP(O3,'Data Validation'!I:J,2,FALSE) -> C5367590 | AF3: =IF(AJ3<=53,AJ3,AJ3-52) -> 41.060377 | AG3: =IF(H3="Y",(((160/1000000)*AA3)/5.3)*0.1,((160/1000000)*AA3)/5.3) -> 1.509434 | AH3: =SUM($AG$2:AG3) -> 3.0188679 | AI3: =AH3/50 -> 0.060377358 | AJ3: =WEEKNUM(TODAY())+AI3 -> 41.060377 | AK3: 46006 | AL3: Y | AM3: N | AN3: =AS3-S3 -> 3 | AS3: 46296
A4: Stefan Steinle | B4: =VLOOKUP(A4,'Data Validation'!S:T,2,FALSE) -> Customer Solution Support and Innovation | C4: Kabadzhova, Kremena <kremena.kabadzhova@sap.com> | D4: Source Code | E4: On-Premise | F4: P2 | G4: S1 | H4: Y | I4: Incremental ONLY | J4: SAP Cloud Appliance Library 4.61 | K4: N/A | L4: 46310 | M4: 46322 | N4: GLOBAL | O4: Global | P4: Backlog | Q4: Y | AA4: 500000 | AB4: Open | AC4: No | AD4: =IF((AND((AS4-TODAY())<=30,(L4-TODAY())<=0,(F5="P1")))=TRUE,"Yes",IF(AND((AS4-TODAY())<=30,(L4-TODAY())<=0,(F5="P2"))=TRUE,"Yes","No")) -> No | AE4: =VLOOKUP(O4,'Data Validation'!I:J,2,FALSE) -> Global | AF4: =IF(AJ4<=53,AJ4,AJ4-52) -> 41.090566 | AG4: =IF(H4="Y",(((160/1000000)*AA4)/5.3)*0.1,((160/1000000)*AA4)/5.3) -> 1.509434 | AH4: =SUM($AG$2:AG4) -> 4.5283019 | AI4: =AH4/50 -> 0.090566038 | AJ4: =WEEKNUM(TODAY())+AI4 -> 41.090566 | AK4: 46006 | AL4: Y | AM4: N | AN4: =AS4-S4 -> 46324 | AS4: 46324
A5: Stefan Steinle | B5: =VLOOKUP(A5,'Data Validation'!S:T,2,FALSE) -> Customer Solution Support and Innovation | C5: Kabadzhova, Kremena <kremena.kabadzhova@sap.com> | D5: Source Code | E5: On-Premise | F5: P2 | G5: S1 | H5: Y | I5: Incremental ONLY | J5: SAP Cloud Appliance Library 4.62 | K5: N/A | L5: 46338 | M5: 46350 | N5: GLOBAL | O5: Global | P5: Backlog | Q5: Y | AA5: 500000 | AB5: Open | AC5: No | AD5: =IF((AND((AS5-TODAY())<=30,(L5-TODAY())<=0,(F6="P1")))=TRUE,"Yes",IF(AND((AS5-TODAY())<=30,(L5-TODAY())<=0,(F6="P2"))=TRUE,"Yes","No")) -> No | AE5: =VLOOKUP(O5,'Data Validation'!I:J,2,FALSE) -> Global | AF5: =IF(AJ5<=53,AJ5,AJ5-52) -> 41.120755 | AG5: =IF(H5="Y",(((160/1000000)*AA5)/5.3)*0.1,((160/1000000)*AA5)/5.3) -> 1.509434 | AH5: =SUM($AG$2:AG5) -> 6.0377358 | AI5: =AH5/50 -> 0.12075472 | AJ5: =WEEKNUM(TODAY())+AI5 -> 41.120755 | AK5: 46006 | AL5: Y | AM5: N | AN5: =AS5-S5 -> 46352 | AS5: 46352
A6: Stefan Steinle | B6: =VLOOKUP(A6,'Data Validation'!S:T,2,FALSE) -> Customer Solution Support and Innovation | C6: Kabadzhova, Kremena <kremena.kabadzhova@sap.com> | D6: Source Code | E6: On-Premise | F6: P2 | G6: S1 | H6: Y | I6: Incremental ONLY | J6: SAP Cloud Appliance Library 4.63 | K6: N/A | L6: 46394 | M6: 46406 | N6: GLOBAL | O6: Global | P6: Backlog | Q6: Y | AA6: 500000 | AB6: Open | AC6: No | AD6: No | AE6: =VLOOKUP(O6,'Data Validation'!I:J,2,FALSE) -> Global | AF6: =IF(AJ6<=53,AJ6,AJ6-52) -> 41.150943 | AG6: =IF(H6="Y",(((160/1000000)*AA6)/5.3)*0.1,((160/1000000)*AA6)/5.3) -> 1.509434 | AH6: =SUM($AG$2:AG6) -> 7.5471698 | AI6: =AH6/50 -> 0.1509434 | AJ6: =WEEKNUM(TODAY())+AI6 -> 41.150943 | AK6: 46006 | AL6: Y | AM6: N | AN6: =AS6-S6 -> 46408 | AS6: 46408
A7: Michael Ameling | B7: =VLOOKUP(A7,'Data Validation'!S:T,2,FALSE) -> Cross Architecture | C7: Yadav, Prashant<prashant.yadav03@sap.com> | D7: On-Mobile Device | E7: On-Mobile Device | F7: P2 | G7: S2 | H7: Y | I7: Incremental ONLY | J7: TripIt Mobile Android 09/2026 | K7: N/A | L7: 46268 | M7: 46283 | N7: GTLC India | O7: Sharath | P7: Done | Q7: Y | R7: 46280 | S7: 46282 | AA7: 500000 | AB7: Open | AC7: No | AD7: =IF((AND((AS7-TODAY())<=30,(L7-TODAY())<=0,(F7="P1")))=TRUE,"Yes",IF(AND((AS7-TODAY())<=30,(L7-TODAY())<=0,(F7="P2"))=TRUE,"Yes","No")) -> Yes | AE7: =VLOOKUP(O7,'Data Validation'!I:J,2,FALSE) -> C5385258 | AF7: =IF(AJ7<=53,AJ7,AJ7-52) -> 2.1622642 | AG7: =IF(H7="Y",(((160/1000000)*AA7)/5.3)*0.1,((160/1000000)*AA7)/5.3) -> 1.509434 | AH7: =SUM($AG$2:AG212) -> 658.11321 | AI7: =AH7/50 -> 13.162264 | AJ7: =WEEKNUM(TODAY())+AI7 -> 54.162264 | AK7: 46049 | AL7: Y | AM7: Y | AN7: =AS7-S7 -> -10 | AS7: 46272
A8: Michael Ameling | B8: =VLOOKUP(A8,'Data Validation'!S:T,2,FALSE) -> Cross Architecture | C8: Yadav, Prashant<prashant.yadav03@sap.com> | D8: On-Mobile Device | E8: On-Mobile Device | F8: P2 | G8: S2 | H8: Y | I8: Incremental ONLY | J8: TripIt Mobile iOS 09/2026 | K8: N/A | L8: 46268 | M8: 46283 | N8: GTLC India | O8: Sharath | P8: Done | Q8: Y | R8: 46280 | S8: 46282 | AA8: 500000 | AB8: Open | AC8: No | AD8: =IF((AND((AS8-TODAY())<=30,(L8-TODAY())<=0,(F8="P1")))=TRUE,"Yes",IF(AND((AS8-TODAY())<=30,(L8-TODAY())<=0,(F8="P2"))=TRUE,"Yes","No")) -> Yes | AE8: =VLOOKUP(O8,'Data Validation'!I:J,2,FALSE) -> C5385258 | AF8: =IF(AJ8<=53,AJ8,AJ8-52) -> 2.1924528 | AG8: =IF(H8="Y",(((160/1000000)*AA8)/5.3)*0.1,((160/1000000)*AA8)/5.3) -> 1.509434 | AH8: =SUM($AG$2:AG213) -> 659.62264 | AI8: =AH8/50 -> 13.192453 | AJ8: =WEEKNUM(TODAY())+AI8 -> 54.192453 | AK8: 46049 | AL8: Y | AM8: Y | AN8: =AS8-S8 -> -10 | AS8: 46272
A9: Peter Pluim | B9: Enterprise Cloud Services | C9: Yonchev, Tsonyo<tsonyo.yonchev@sap.com> | D9: On-Premise | E9: On-Premise | F9: P2 | G9: S2 | H9: Y | I9: Incremental ONLY | J9: LaMaRT 2026.17 | K9: 46117 | L9: 46262 | M9: 46279 | N9: GTLC Germany | O9: Sushma | P9: In Progress | Q9: Y | R9: 46268 | AA9: 500000 | AB9: Open | AC9: No | AD9: =IF((AND((AS9-TODAY())<=30,(L10-TODAY())<=0,(F9="P1")))=TRUE,"Yes",IF(AND((AS9-TODAY())<=30,(L10-TODAY())<=0,(F9="P2"))=TRUE,"Yes","No")) -> Yes | AE9: =VLOOKUP(O9,'Data Validation'!I:J,2,FALSE) -> I773708 | AF9: =IF(AJ9<=53,AJ9,AJ9-52) -> 43.05283 | AG9: =IF(H9="Y",(((160/1000000)*AA9)/5.3)*0.1,((160/1000000)*AA9)/5.3) -> 1.509434 | AH9: =SUM($AG$2:AG51) -> 102.64151 | AI9: =AH9/50 -> 2.0528302 | AJ9: =WEEKNUM(TODAY())+AI9 -> 43.05283 | AK9: 46140 | AL9: Y | AM9: N | AN9: =AS9-S9 -> 46279 | AS9: 46279
A10: Michael Ameling | B10: =VLOOKUP(A10,'Data Validation'!S:T,2,FALSE) -> Cross Architecture | C10: Yadav, Prashant<prashant.yadav03@sap.com> | D10: On-Mobile Device | E10: On-Mobile Device | F10: P2 | G10: S2 | H10: Y | I10: Incremental ONLY | J10: SAP Concur Mobile iOS H1 2026 - Sep | K10: N/A | L10: 46279 | M10: 46286 | N10: GTLC India | O10: Sharath | P10: Done | Q10: Y | R10: 46280 | S10: 46282 | AA10: 500000 | AB10: Open | AC10: No | AD10: =IF((AND((AS10-TODAY())<=30,(L10-TODAY())<=0,(F59="P1")))=TRUE,"Yes",IF(AND((AS10-TODAY())<=30,(L10-TODAY())<=0,(F59="P2"))=TRUE,"Yes","No")) -> Yes | AE10: =VLOOKUP(O10,'Data Validation'!I:J,2,FALSE) -> C5385258 | AF10: =IF(AJ10<=53,AJ10,AJ10-52) -> 41.271698 | AG10: =IF(H10="Y",(((160/1000000)*AA10)/5.3)*0.1,((160/1000000)*AA10)/5.3) -> 1.509434 | AH10: =SUM($AG$2:AG10) -> 13.584906 | AI10: =AH10/50 -> 0.27169811 | AJ10: =WEEKNUM(TODAY())+AI10 -> 41.271698 | AK10: 46182 | AL10: Y | AM10: Y | AN10: =AS10-S10 -> 4 | AS10: 46286
A11: Michael Ameling | B11: =VLOOKUP(A11,'Data Validation'!S:T,2,FALSE) -> Cross Architecture | C11: Yadav, Prashant<prashant.yadav03@sap.com> | D11: On-Mobile Device | E11: On-Mobile Device | F11: P2 | G11: S2 | H11: Y | I11: Incremental ONLY | J11: SAP Concur Mobile Android H1 2026 - Sep | K11: N/A | L11: 46279 | M11: 46286 | N11: GTLC India | O11: Sharath | P11: Done | Q11: Y | R11: 46280 | S11: 46282 | AA11: 500000 | AB11: Open | AC11: No | AD11: =IF((AND((AS11-TODAY())<=30,(L11-TODAY())<=0,(F60="P1")))=TRUE,"Yes",IF(AND((AS11-TODAY())<=30,(L11-TODAY())<=0,(F60="P2"))=TRUE,"Yes","No")) -> Yes | AE11: =VLOOKUP(O11,'Data Validation'!I:J,2,FALSE) -> C5385258 | AF11: =IF(AJ11<=53,AJ11,AJ11-52) -> 41.301887 | AG11: =IF(H11="Y",(((160/1000000)*AA11)/5.3)*0.1,((160/1000000)*AA11)/5.3) -> 1.509434 | AH11: =SUM($AG$2:AG11) -> 15.09434 | AI11: =AH11/50 -> 0.30188679 | AJ11: =WEEKNUM(TODAY())+AI11 -> 41.301887 | AK11: 46182 | AL11: Y | AM11: Y | AN11: =AS11-S11 -> 4 | AS11: 46286
A12: Dominik Metzger | B12: People Growth Management Office UK | C12: Reichenbach, Zsolt<zsolt.reichenbach@sap.com> | D12: On-Premise | E12: On-Premise | F12: P2 | G12: S2 | H12: Y | I12: Incremental ONLY | J12: IBP 2611 - Beta Release | K12: 46168 | L12: 46255 | M12: 46286 | N12: GTLC Germany | O12: Giang | P12: In Progress | Q12: Y | R12: 46268 | AA12: 500000 | AB12: Open | AC12: No | AD12: Yes | AE12: I541859 | AF12: 22.29434 | AG12: 1.509434 | AH12: 914.71699 | AI12: 18.29434 | AJ12: 22.29434 | AK12: 46260 | AL12: N | AM12: N | AN12: -13 | AS12: 46274
A13: Stefan Steinle | B13: Customer Solution Support and Innovation | C13: Andreev, Ivan <ivan.andreev02@sap.com> | D13: On-Premise | E13: On-Premise | F13: P2 | G13: S2 | H13: Y | I13: Incremental ONLY | J13: SL Toolset for Cloud 2605Bb(T2026.27) | K13: N/A | L13: 46272 | M13: 46287 | N13: GTLC India | O13: Arpitha | P13: Done | Q13: Y | R13: 46273 | S13: 46276 | AA13: 500000 | AB13: Open | AC13: No | AD13: =IF((AND((AS13-TODAY())<=30,(L13-TODAY())<=0,(F14="P1")))=TRUE,"Yes",IF(AND((AS13-TODAY())<=30,(L13-TODAY())<=0,(F14="P2"))=TRUE,"Yes","No")) -> Yes | AE13: C5367590 | AF13: 22.415094 | AG13: 1.509434 | AH13: =SUM($AG$2:AG13) -> 18.113208 | AI13: 18.415094 | AJ13: 22.415094 | AK13: 46128 | AL13: Y | AM13: N | AN13: =AS13-S13 -> 11 | AS13: 46287
A14: Philipp Herzig | B14: =VLOOKUP(A14,'Data Validation'!S:T,2,FALSE) -> Product Engineering Intelligent Enterprise and Cross Architecture | C14: Mueller, Christian Mathias <christ.mueller@sap.com> | D14: Source Code | E14: On-Mobile Device | F14: P2 | G14: S2 | H14: Y | I14: Incremental ONLY | J14: AI Libraries and SDKs MDG 25 2609a | K14: N/A | L14: 46279 | M14: 46288 | N14: GLOBAL | O14: Global | P14: Cancelled | Q14: Y | Z14: No longer delivered | AA14: 500000 | AB14: Open | AC14: No | AD14: =IF((AND((AS14-TODAY())<=30,(L14-TODAY())<=0,(F14="P1")))=TRUE,"Yes",IF(AND((AS14-TODAY())<=30,(L14-TODAY())<=0,(F14="P2"))=TRUE,"Yes","No")) -> Yes | AE14: =VLOOKUP(O14,'Data Validation'!I:J,2,FALSE) -> Global | AF14: =IF(AJ14<=53,AJ14,AJ14-52) -> 49.392453 | AG14: =IF(H14="Y",(((160/1000000)*AA14)/5.3)*0.1,((160/1000000)*AA14)/5.3) -> 1.509434 | AH14: =SUM($AG$2:AG117) -> 419.62264 | AI14: =AH14/50 -> 8.3924528 | AJ14: =WEEKNUM(TODAY())+AI14 -> 49.392453 | AK14: 46029 | AL14: Y | AM14: N | AN14: =AS14-S14 -> 46288 | AS14: 46288
A15: Peter Pluim | B15: Enterprise Cloud Services | C15: Yonchev, Tsonyo<tsonyo.yonchev@sap.com> | D15: On-Premise | E15: On-Premise | F15: P2 | G15: S2 | H15: Y | I15: Incremental ONLY | J15: LaMaRT 2026.18 | K15: 46117 | L15: 46276 | M15: 46293 | N15: GTLC Germany | O15: Sushma | P15: In Progress | Q15: Y | R15: 46283 | AA15: 500000 | AB15: Open | AC15: No | AD15: =IF((AND((AS15-TODAY())<=30,(L16-TODAY())<=0,(F15="P1")))=TRUE,"Yes",IF(AND((AS15-TODAY())<=30,(L16-TODAY())<=0,(F15="P2"))=TRUE,"Yes","No")) -> Yes | AE15: =VLOOKUP(O15,'Data Validation'!I:J,2,FALSE) -> I773708 | AF15: =IF(AJ15<=53,AJ15,AJ15-52) -> 44.049057 | AG15: =IF(H15="Y",(((160/1000000)*AA15)/5.3)*0.1,((160/1000000)*AA15)/5.3) -> 1.509434 | AH15: =SUM($AG$2:AG57) -> 152.45283 | AI15: =AH15/50 -> 3.0490566 | AJ15: =WEEKNUM(TODAY())+AI15 -> 44.049057 | AK15: 46140 | AL15: Y | AM15: N | AN15: =AS15-S15 -> 46293 | AS15: 46293
A16: Peter Pluim | B16: =VLOOKUP(A16,'Data Validation'!S:T,2,FALSE) -> Enterprise Cloud Services | C16: Chakalova, Stela<stela.chakalova@sap.com> | D16: On-Premise | E16: On-Premise | F16: P2 | G16: S2 | H16: Y | I16: Incremental ONLY | J16: Edge Lifecycle Management 1.64 | K16: N/A | L16: 46269 | M16: 46297 | N16: GTLC India | O16: Viswa | P16: Done | Q16: Y | R16: 46269 | S16: 46280 | AA16: 500000 | AB16: Open | AC16: No | AD16: =IF((AND((AS16-TODAY())<=30,(L16-TODAY())<=0,(F17="P1")))=TRUE,"Yes",IF(AND((AS16-TODAY())<=30,(L16-TODAY())<=0,(F17="P2"))=TRUE,"Yes","No")) -> Yes | AE16: =VLOOKUP(O16,'Data Validation'!I:J,2,FALSE) -> C5366020 | AF16: 22.173585 | AG16: 1.509434 | AH16: =SUM($AG$2:AG16) -> 22.641509 | AI16: 18.173585 | AJ16: 22.173585 | AK16: 46045 | AL16: Y | AM16: N | AN16: -15 | AS16: 46297
A17: Peter Pluim | B17: Enterprise Cloud Services | C17: Yonchev, Tsonyo<tsonyo.yonchev@sap.com> | D17: On-Premise | E17: On-Premise | F17: P2 | G17: S2 | H17: Y | I17: Incremental ONLY | J17: LaMaRT 2026.19 | K17: 46117 | L17: 46290 | M17: 46307 | N17: GTLC India | O17: Apoorva | P17: In Progress | Q17: Y | R17: 46301 | AA17: 500000 | AB17: Open | AC17: No | AD17: =IF((AND((AS17-TODAY())<=30,(L18-TODAY())<=0,(F17="P1")))=TRUE,"Yes",IF(AND((AS17-TODAY())<=30,(L18-TODAY())<=0,(F17="P2"))=TRUE,"Yes","No")) -> Yes | AE17: =VLOOKUP(O17,'Data Validation'!I:J,2,FALSE) -> C5367590 | AF17: =IF(AJ17<=53,AJ17,AJ17-52) -> 44.109434 | AG17: =IF(H17="Y",(((160/1000000)*AA17)/5.3)*0.1,((160/1000000)*AA17)/5.3) -> 1.509434 | AH17: =SUM($AG$2:AG59) -> 155.4717 | AI17: =AH17/50 -> 3.109434 | AJ17: =WEEKNUM(TODAY())+AI17 -> 44.109434 | AK17: 46140 | AL17: Y | AM17: N | AN17: =AS17-S17 -> 46307 | AS17: 46307
A18: Michael Ameling | B18: =VLOOKUP(A18,'Data Validation'!S:T,2,FALSE) -> Cross Architecture | C18: Singh, Shubham<shubham.singh04@sap.com> | D18: On-Premise | E18: On-Premise | F18: P2 | G18: S2 | H18: Y | I18: Incremental ONLY | J18: APIM_EDGE_IC_2609 | K18: N/A | L18: 46283 | M18: 46311 | N18: GTLC India | O18: Soumya Pawar | P18: Done | Q18: Y | R18: 46283 | S18: 46293 | AA18: 500000 | AB18: Open | AC18: No | AD18: =IF((AND((AS18-TODAY())<=30,(L18-TODAY())<=0,(F20="P1")))=TRUE,"Yes",IF(AND((AS18-TODAY())<=30,(L18-TODAY())<=0,(F20="P2"))=TRUE,"Yes","No")) -> Yes | AE18: =VLOOKUP(O18,'Data Validation'!I:J,2,FALSE) -> C5385243 | AF18: =IF(AJ18<=53,AJ18,AJ18-52) -> 41.513208 | AG18: =IF(H18="Y",(((160/1000000)*AA18)/5.3)*0.1,((160/1000000)*AA18)/5.3) -> 1.509434 | AH18: =SUM($AG$2:AG18) -> 25.660377 | AI18: =AH18/50 -> 0.51320755 | AJ18: =WEEKNUM(TODAY())+AI18 -> 41.513208 | AK18: 46122 | AL18: Y | AM18: N | AN18: =AS18-S18 -> 18 | AS18: 46311
A19: Michael Ameling | B19: =VLOOKUP(A19,'Data Validation'!S:T,2,FALSE) -> Cross Architecture | C19: Yadav, Prashant<prashant.yadav03@sap.com> | D19: On-Mobile Device | E19: On-Mobile Device | F19: P2 | G19: S2 | H19: Y | I19: Incremental ONLY | J19: SAP Concur Mobile iOS H1 2026 - Oct | K19: N/A | L19: 46303 | M19: 46311 | N19: GLOBAL | O19: Global | P19: Backlog | Q19: Y | AA19: 500000 | AB19: Open | AC19: No | AD19: =IF((AND((AS19-TODAY())<=30,(L19-TODAY())<=0,(#REF!="P1")))=TRUE,"Yes",IF(AND((AS19-TODAY())<=30,(L19-TODAY())<=0,(#REF!="P2"))=TRUE,"Yes","No")) -> #REF! | AE19: =VLOOKUP(O19,'Data Validation'!I:J,2,FALSE) -> Global | AF19: =IF(AJ19<=53,AJ19,AJ19-52) -> 41.543396 | AG19: =IF(H19="Y",(((160/1000000)*AA19)/5.3)*0.1,((160/1000000)*AA19)/5.3) -> 1.509434 | AH19: =SUM($AG$2:AG19) -> 27.169811 | AI19: =AH19/50 -> 0.54339623 | AJ19: =WEEKNUM(TODAY())+AI19 -> 41.543396 | AK19: 46182 | AL19: Y | AM19: Y | AN19: =AS19-S19 -> 46311 | AS19: 46311
A20: Michael Ameling | B20: =VLOOKUP(A20,'Data Validation'!S:T,2,FALSE) -> Cross Architecture | C20: Yadav, Prashant<prashant.yadav03@sap.com> | D20: On-Mobile Device | E20: On-Mobile Device | F20: P2 | G20: S2 | H20: Y | I20: Incremental ONLY | J20: SAP Concur Mobile Android H1 2026 - Oct | K20: N/A | L20: 46303 | M20: 46311 | N20: GLOBAL | O20: Global | P20: Backlog | Q20: Y | AA20: 500000 | AB20: Open | AC20: No | AD20: =IF((AND((AS20-TODAY())<=30,(L20-TODAY())<=0,(F68="P1")))=TRUE,"Yes",IF(AND((AS20-TODAY())<=30,(L20-TODAY())<=0,(F68="P2"))=TRUE,"Yes","No")) -> No | AE20: =VLOOKUP(O20,'Data Validation'!I:J,2,FALSE) -> Global | AF20: =IF(AJ20<=53,AJ20,AJ20-52) -> 41.573585 | AG20: =IF(H20="Y",(((160/1000000)*AA20)/5.3)*0.1,((160/1000000)*AA20)/5.3) -> 1.509434 | AH20: =SUM($AG$2:AG20) -> 28.679245 | AI20: =AH20/50 -> 0.57358491 | AJ20: =WEEKNUM(TODAY())+AI20 -> 41.573585 | AK20: 46182 | AL20: Y | AM20: Y | AN20: =AS20-S20 -> 46311 | AS20: 46311
A21: Michael Ameling | B21: =VLOOKUP(A21,'Data Validation'!S:T,2,FALSE) -> Cross Architecture | C21: Yadav, Prashant<prashant.yadav03@sap.com> | D21: On-Mobile Device | E21: On-Mobile Device | F21: P2 | G21: S2 | H21: Y | I21: Incremental ONLY | J21: TripIt Mobile Android 10/2026 | K21: N/A | L21: 46310 | M21: 46314 | N21: GLOBAL | O21: Global | P21: Backlog | Q21: Y | AA21: 500000 | AB21: Open | AC21: No | AD21: =IF((AND((AS21-TODAY())<=30,(L21-TODAY())<=0,(F21="P1")))=TRUE,"Yes",IF(AND((AS21-TODAY())<=30,(L21-TODAY())<=0,(F21="P2"))=TRUE,"Yes","No")) -> No | AE21: =VLOOKUP(O21,'Data Validation'!I:J,2,FALSE) -> Global | AF21: =IF(AJ21<=53,AJ21,AJ21-52) -> 2.5849057 | AG21: =IF(H21="Y",(((160/1000000)*AA21)/5.3)*0.1,((160/1000000)*AA21)/5.3) -> 1.509434 | AH21: =SUM($AG$2:AG226) -> 679.24528 | AI21: =AH21/50 -> 13.584906 | AJ21: =WEEKNUM(TODAY())+AI21 -> 54.584906 | AK21: 46049 | AL21: Y | AM21: Y | AN21: =AS21-S21 -> 46314 | AS21: 46314
A22: Michael Ameling | B22: =VLOOKUP(A22,'Data Validation'!S:T,2,FALSE) -> Cross Architecture | C22: Yadav, Prashant<prashant.yadav03@sap.com> | D22: On-Mobile Device | E22: On-Mobile Device | F22: P2 | G22: S2 | H22: Y | I22: Incremental ONLY | J22: TripIt Mobile iOS 10/2026 | K22: N/A | L22: 46310 | M22: 46314 | N22: GLOBAL | O22: Global | P22: Backlog | Q22: Y | AA22: 500000 | AB22: Open | AC22: No | AD22: =IF((AND((AS22-TODAY())<=30,(L22-TODAY())<=0,(F22="P1")))=TRUE,"Yes",IF(AND((AS22-TODAY())<=30,(L22-TODAY())<=0,(F22="P2"))=TRUE,"Yes","No")) -> No | AE22: =VLOOKUP(O22,'Data Validation'!I:J,2,FALSE) -> Global | AF22: =IF(AJ22<=53,AJ22,AJ22-52) -> 2.6150943 | AG22: =IF(H22="Y",(((160/1000000)*AA22)/5.3)*0.1,((160/1000000)*AA22)/5.3) -> 1.509434 | AH22: =SUM($AG$2:AG227) -> 680.75472 | AI22: =AH22/50 -> 13.615094 | AJ22: =WEEKNUM(TODAY())+AI22 -> 54.615094 | AK22: 46049 | AL22: Y | AM22: Y | AN22: =AS22-S22 -> 46314 | AS22: 46314
A23: Stefan Steinle | B23: Customer Solution Support and Innovation | C23: Andreev, Ivan <ivan.andreev02@sap.com> | D23: On-Premise | E23: On-Premise | F23: P2 | G23: S2 | H23: Y | I23: Incremental ONLY | J23: SL Toolset for Cloud 2605Bb(T2026.27) | K23: N/A | L23: 46300 | M23: 46315 | N23: GTLC India | O23: Arpitha | P23: In Progress | Q23: Y | R23: 46301 | AA23: 500000 | AB23: Open | AC23: No | AD23: =IF((AND((AS23-TODAY())<=30,(L23-TODAY())<=0,(F24="P1")))=TRUE,"Yes",IF(AND((AS23-TODAY())<=30,(L23-TODAY())<=0,(F24="P2"))=TRUE,"Yes","No")) -> Yes | AE23: C5367590 | AF23: 22.415094 | AG23: 1.509434 | AH23: =SUM($AG$2:AG23) -> 33.207547 | AI23: 18.415094 | AJ23: 22.415094 | AK23: 46128 | AL23: Y | AM23: N | AN23: =AS23-S23 -> 46315 | AS23: 46315
A24: Peter Pluim | B24: Enterprise Cloud Services | C24: Yonchev, Tsonyo<tsonyo.yonchev@sap.com> | D24: On-Premise | E24: On-Premise | F24: P2 | G24: S2 | H24: Y | I24: Incremental ONLY | J24: LaMaRT 2026.20 | K24: 46117 | L24: 46304 | M24: 46321 | N24: GLOBAL | O24: Global | P24: Backlog | Q24: Y | AA24: 500000 | AB24: Open | AC24: No | AD24: =IF((AND((AS24-TODAY())<=30,(L25-TODAY())<=0,(F24="P1")))=TRUE,"Yes",IF(AND((AS24-TODAY())<=30,(L25-TODAY())<=0,(F24="P2"))=TRUE,"Yes","No")) -> Yes | AE24: =VLOOKUP(O24,'Data Validation'!I:J,2,FALSE) -> Global | AF24: =IF(AJ24<=53,AJ24,AJ24-52) -> 44.320755 | AG24: =IF(H24="Y",(((160/1000000)*AA24)/5.3)*0.1,((160/1000000)*AA24)/5.3) -> 1.509434 | AH24: =SUM($AG$2:AG66) -> 166.03774 | AI24: =AH24/50 -> 3.3207547 | AJ24: =WEEKNUM(TODAY())+AI24 -> 44.320755 | AK24: 46140 | AL24: Y | AM24: N | AN24: =AS24-S24 -> 46321 | AS24: 46321
A25: Peter Pluim | B25: =VLOOKUP(A25,'Data Validation'!S:T,2,FALSE) -> Enterprise Cloud Services | C25: Chakalova, Stela<stela.chakalova@sap.com> | D25: On-Premise | E25: On-Premise | F25: P2 | G25: S2 | H25: Y | I25: Incremental ONLY | J25: Edge Lifecycle Management 1.65 | K25: N/A | L25: 46297 | M25: 46325 | N25: GTLC India | O25: Arun | P25: In Progress | Q25: Y | R25: 46301 | AA25: 500000 | AB25: Open | AC25: No | AD25: =IF((AND((AS25-TODAY())<=30,(L25-TODAY())<=0,(F26="P1")))=TRUE,"Yes",IF(AND((AS25-TODAY())<=30,(L25-TODAY())<=0,(F26="P2"))=TRUE,"Yes","No")) -> Yes | AE25: =VLOOKUP(O25,'Data Validation'!I:J,2,FALSE) -> C5381614 | AF25: 22.173585 | AG25: 1.509434 | AH25: =SUM($AG$2:AG25) -> 36.226415 | AI25: 18.173585 | AJ25: 22.173585 | AK25: 46045 | AL25: Y | AM25: N | AN25: -15 | AS25: 46325
A26: Peter Pluim | B26: Enterprise Cloud Services | C26: Yonchev, Tsonyo<tsonyo.yonchev@sap.com> | D26: On-Premise | E26: On-Premise | F26: P2 | G26: S2 | H26: Y | I26: Incremental ONLY | J26: LaMaRT 2026.21 | K26: 46117 | L26: 46318 | M26: 46335 | N26: GLOBAL | O26: Global | P26: Backlog | Q26: Y | AA26: 500000 | AB26: Open | AC26: No | AD26: =IF((AND((AS26-TODAY())<=30,(L27-TODAY())<=0,(F26="P1")))=TRUE,"Yes",IF(AND((AS26-TODAY())<=30,(L27-TODAY())<=0,(F26="P2"))=TRUE,"Yes","No")) -> No | AE26: =VLOOKUP(O26,'Data Validation'!I:J,2,FALSE) -> Global | AF26: =IF(AJ26<=53,AJ26,AJ26-52) -> 44.350943 | AG26: =IF(H26="Y",(((160/1000000)*AA26)/5.3)*0.1,((160/1000000)*AA26)/5.3) -> 1.509434 | AH26: =SUM($AG$2:AG67) -> 167.54717 | AI26: =AH26/50 -> 3.3509434 | AJ26: =WEEKNUM(TODAY())+AI26 -> 44.350943 | AK26: 46140 | AL26: Y | AM26: N | AN26: =AS26-S26 -> 46335 | AS26: 46335
A27: Michael Ameling | B27: =VLOOKUP(A27,'Data Validation'!S:T,2,FALSE) -> Cross Architecture | C27: Singh, Shubham<shubham.singh04@sap.com> | D27: On-Premise | E27: On-Premise | F27: P2 | G27: S2 | H27: Y | I27: Incremental ONLY | J27: APIM_EDGE_IC_2610 | K27: N/A | L27: 46311 | M27: 46339 | N27: GLOBAL | O27: Global | P27: Backlog | Q27: Y | AA27: 500000 | AB27: Open | AC27: No | AD27: =IF((AND((AS27-TODAY())<=30,(L27-TODAY())<=0,(F29="P1")))=TRUE,"Yes",IF(AND((AS27-TODAY())<=30,(L27-TODAY())<=0,(F29="P2"))=TRUE,"Yes","No")) -> No | AE27: =VLOOKUP(O27,'Data Validation'!I:J,2,FALSE) -> Global | AF27: =IF(AJ27<=53,AJ27,AJ27-52) -> 41.784906 | AG27: =IF(H27="Y",(((160/1000000)*AA27)/5.3)*0.1,((160/1000000)*AA27)/5.3) -> 1.509434 | AH27: =SUM($AG$2:AG27) -> 39.245283 | AI27: =AH27/50 -> 0.78490566 | AJ27: =WEEKNUM(TODAY())+AI27 -> 41.784906 | AK27: 46122 | AL27: Y | AM27: N | AN27: =AS27-S27 -> 46339 | AS27: 46339
A28: Michael Ameling | B28: =VLOOKUP(A28,'Data Validation'!S:T,2,FALSE) -> Cross Architecture | C28: Yadav, Prashant<prashant.yadav03@sap.com> | D28: On-Mobile Device | E28: On-Mobile Device | F28: P2 | G28: S2 | H28: Y | I28: Incremental ONLY | J28: SAP Concur Mobile iOS H1 2026 - Nov | K28: N/A | L28: 46337 | M28: 46342 | N28: GLOBAL | O28: Global | P28: Backlog | Q28: Y | AA28: 500000 | AB28: Open | AC28: No | AD28: =IF((AND((AS28-TODAY())<=30,(L28-TODAY())<=0,(F76="P1")))=TRUE,"Yes",IF(AND((AS28-TODAY())<=30,(L28-TODAY())<=0,(F76="P2"))=TRUE,"Yes","No")) -> No | AE28: =VLOOKUP(O28,'Data Validation'!I:J,2,FALSE) -> Global | AF28: =IF(AJ28<=53,AJ28,AJ28-52) -> 41.815094 | AG28: =IF(H28="Y",(((160/1000000)*AA28)/5.3)*0.1,((160/1000000)*AA28)/5.3) -> 1.509434 | AH28: =SUM($AG$2:AG28) -> 40.754717 | AI28: =AH28/50 -> 0.81509434 | AJ28: =WEEKNUM(TODAY())+AI28 -> 41.815094 | AK28: 46182 | AL28: Y | AM28: Y | AN28: =AS28-S28 -> 46342 | AS28: 46342
A29: Michael Ameling | B29: =VLOOKUP(A29,'Data Validation'!S:T,2,FALSE) -> Cross Architecture | C29: Yadav, Prashant<prashant.yadav03@sap.com> | D29: On-Mobile Device | E29: On-Mobile Device | F29: P2 | G29: S2 | H29: Y | I29: Incremental ONLY | J29: SAP Concur Mobile Android H1 2026 - Nov | K29: N/A | L29: 46337 | M29: 46342 | N29: GLOBAL | O29: Global | P29: Backlog | Q29: Y | AA29: 500000 | AB29: Open | AC29: No | AD29: =IF((AND((AS29-TODAY())<=30,(L29-TODAY())<=0,(F77="P1")))=TRUE,"Yes",IF(AND((AS29-TODAY())<=30,(L29-TODAY())<=0,(F77="P2"))=TRUE,"Yes","No")) -> No | AE29: =VLOOKUP(O29,'Data Validation'!I:J,2,FALSE) -> Global | AF29: =IF(AJ29<=53,AJ29,AJ29-52) -> 41.845283 | AG29: =IF(H29="Y",(((160/1000000)*AA29)/5.3)*0.1,((160/1000000)*AA29)/5.3) -> 1.509434 | AH29: =SUM($AG$2:AG29) -> 42.264151 | AI29: =AH29/50 -> 0.84528302 | AJ29: =WEEKNUM(TODAY())+AI29 -> 41.845283 | AK29: 46182 | AL29: Y | AM29: Y | AN29: =AS29-S29 -> 46342 | AS29: 46342
A30: Stefan Steinle | B30: Customer Solution Support and Innovation | C30: Andreev, Ivan <ivan.andreev02@sap.com> | D30: On-Premise | E30: On-Premise | F30: P2 | G30: S2 | H30: Y | I30: Incremental ONLY | J30: SL Toolset for Cloud 2605Bb(T2026.27) | K30: N/A | L30: 46328 | M30: 46343 | N30: GLOBAL | O30: Global | P30: Backlog | Q30: Y | AA30: 500000 | AB30: Open | AC30: No | AD30: =IF((AND((AS30-TODAY())<=30,(L30-TODAY())<=0,(F32="P1")))=TRUE,"Yes",IF(AND((AS30-TODAY())<=30,(L30-TODAY())<=0,(F32="P2"))=TRUE,"Yes","No")) -> No | AE30: C5367590 | AF30: 22.415094 | AG30: 1.509434 | AH30: =SUM($AG$2:AG30) -> 43.773585 | AI30: 18.415094 | AJ30: 22.415094 | AK30: 46128 | AL30: Y | AM30: N | AN30: =AS30-S30 -> 46343 | AS30: 46343
A31: Peter Pluim | B31: Enterprise Cloud Services | C31: Yonchev, Tsonyo<tsonyo.yonchev@sap.com> | D31: On-Premise | E31: On-Premise | F31: P2 | G31: S2 | H31: Y | I31: Incremental ONLY | J31: LaMaRT 2026.22 | K31: 46117 | L31: 46332 | M31: 46349 | N31: GLOBAL | O31: Global | P31: Backlog | Q31: Y | AA31: 500000 | AB31: Open | AC31: No | AD31: =IF((AND((AS31-TODAY())<=30,(L32-TODAY())<=0,(F31="P1")))=TRUE,"Yes",IF(AND((AS31-TODAY())<=30,(L32-TODAY())<=0,(F31="P2"))=TRUE,"Yes","No")) -> No | AE31: =VLOOKUP(O31,'Data Validation'!I:J,2,FALSE) -> Global | AF31: =IF(AJ31<=53,AJ31,AJ31-52) -> 44.501887 | AG31: =IF(H31="Y",(((160/1000000)*AA31)/5.3)*0.1,((160/1000000)*AA31)/5.3) -> 1.509434 | AH31: =SUM($AG$2:AG72) -> 175.09434 | AI31: =AH31/50 -> 3.5018868 | AJ31: =WEEKNUM(TODAY())+AI31 -> 44.501887 | AK31: 46140 | AL31: Y | AM31: N | AN31: =AS31-S31 -> 46349 | AS31: 46349
A32: Peter Pluim | B32: =VLOOKUP(A32,'Data Validation'!S:T,2,FALSE) -> Enterprise Cloud Services | C32: Chakalova, Stela<stela.chakalova@sap.com> | D32: On-Premise | E32: On-Premise | F32: P2 | G32: S2 | H32: Y | I32: Incremental ONLY | J32: Edge Lifecycle Management 1.66 | K32: N/A | L32: 46325 | M32: 46353 | N32: GLOBAL | O32: Global | P32: Backlog | Q32: Y | AA32: 500000 | AB32: Open | AC32: No | AD32: =IF((AND((AS32-TODAY())<=30,(L32-TODAY())<=0,(#REF!="P1")))=TRUE,"Yes",IF(AND((AS32-TODAY())<=30,(L32-TODAY())<=0,(#REF!="P2"))=TRUE,"Yes","No")) -> #REF! | AE32: =VLOOKUP(O32,'Data Validation'!I:J,2,FALSE) -> Global | AF32: 22.173585 | AG32: 1.509434 | AH32: =SUM($AG$2:AG32) -> 46.792453 | AI32: 18.173585 | AJ32: 22.173585 | AK32: 46045 | AL32: Y | AM32: N | AN32: -15 | AS32: 46353
A33: Peter Pluim | B33: Enterprise Cloud Services | C33: Yonchev, Tsonyo<tsonyo.yonchev@sap.com> | D33: On-Premise | E33: On-Premise | F33: P2 | G33: S2 | H33: Y | I33: Incremental ONLY | J33: LaMaRT 2026.23 | K33: 46117 | L33: 46346 | M33: 46363 | N33: GLOBAL | O33: Global | P33: Backlog | Q33: Y | AA33: 500000 | AB33: Open | AC33: No | AD33: =IF((AND((AS33-TODAY())<=30,(L34-TODAY())<=0,(F33="P1")))=TRUE,"Yes",IF(AND((AS33-TODAY())<=30,(L34-TODAY())<=0,(F33="P2"))=TRUE,"Yes","No")) -> No | AE33: =VLOOKUP(O33,'Data Validation'!I:J,2,FALSE) -> Global | AF33: =IF(AJ33<=53,AJ33,AJ33-52) -> 44.562264 | AG33: =IF(H33="Y",(((160/1000000)*AA33)/5.3)*0.1,((160/1000000)*AA33)/5.3) -> 1.509434 | AH33: =SUM($AG$2:AG74) -> 178.11321 | AI33: =AH33/50 -> 3.5622642 | AJ33: =WEEKNUM(TODAY())+AI33 -> 44.562264 | AK33: 46140 | AL33: Y | AM33: N | AN33: =AS33-S33 -> 46363 | AS33: 46363
A34: Michael Ameling | B34: =VLOOKUP(A34,'Data Validation'!S:T,2,FALSE) -> Cross Architecture | C34: Yadav, Prashant<prashant.yadav03@sap.com> | D34: On-Mobile Device | E34: On-Mobile Device | F34: P2 | G34: S2 | H34: Y | I34: Incremental ONLY | J34: TripIt Mobile Android 11/2026 | K34: N/A | L34: 46359 | M34: 46363 | N34: GLOBAL | O34: Global | P34: Backlog | Q34: Y | AA34: 500000 | AB34: Open | AC34: No | AD34: =IF((AND((AS34-TODAY())<=30,(L34-TODAY())<=0,(F34="P1")))=TRUE,"Yes",IF(AND((AS34-TODAY())<=30,(L34-TODAY())<=0,(F34="P2"))=TRUE,"Yes","No")) -> No | AE34: =VLOOKUP(O34,'Data Validation'!I:J,2,FALSE) -> Global | AF34: =IF(AJ34<=53,AJ34,AJ34-52) -> 2.9773585 | AG34: =IF(H34="Y",(((160/1000000)*AA34)/5.3)*0.1,((160/1000000)*AA34)/5.3) -> 1.509434 | AH34: =SUM($AG$2:AG239) -> 698.86792 | AI34: =AH34/50 -> 13.977358 | AJ34: =WEEKNUM(TODAY())+AI34 -> 54.977358 | AK34: 46049 | AL34: Y | AM34: Y | AN34: =AS34-S34 -> 46363 | AS34: 46363
A35: Michael Ameling | B35: =VLOOKUP(A35,'Data Validation'!S:T,2,FALSE) -> Cross Architecture | C35: Yadav, Prashant<prashant.yadav03@sap.com> | D35: On-Mobile Device | E35: On-Mobile Device | F35: P2 | G35: S2 | H35: Y | I35: Incremental ONLY | J35: TripIt Mobile iOS 11/2026 | K35: N/A | L35: 46359 | M35: 46363 | N35: GLOBAL | O35: Global | P35: Backlog | Q35: Y | AA35: 500000 | AB35: Open | AC35: No | AD35: =IF((AND((AS35-TODAY())<=30,(L35-TODAY())<=0,(F35="P1")))=TRUE,"Yes",IF(AND((AS35-TODAY())<=30,(L35-TODAY())<=0,(F35="P2"))=TRUE,"Yes","No")) -> No | AE35: =VLOOKUP(O35,'Data Validation'!I:J,2,FALSE) -> Global | AF35: =IF(AJ35<=53,AJ35,AJ35-52) -> 3.0075472 | AG35: =IF(H35="Y",(((160/1000000)*AA35)/5.3)*0.1,((160/1000000)*AA35)/5.3) -> 1.509434 | AH35: =SUM($AG$2:AG240) -> 700.37736 | AI35: =AH35/50 -> 14.007547 | AJ35: =WEEKNUM(TODAY())+AI35 -> 55.007547 | AK35: 46049 | AL35: Y | AM35: Y | AN35: =AS35-S35 -> 46363 | AS35: 46363
A36: Michael Ameling | B36: =VLOOKUP(A36,'Data Validation'!S:T,2,FALSE) -> Cross Architecture | C36: Yadav, Prashant<prashant.yadav03@sap.com> | D36: On-Mobile Device | E36: On-Mobile Device | F36: P2 | G36: S2 | H36: Y | I36: Incremental ONLY | J36: SAP Concur Mobile iOS H1 2026 - Dec | K36: N/A | L36: 46363 | M36: 46370 | N36: GLOBAL | O36: Global | P36: Backlog | Q36: Y | AA36: 500000 | AB36: Open | AC36: No | AD36: =IF((AND((AS36-TODAY())<=30,(L36-TODAY())<=0,(F84="P1")))=TRUE,"Yes",IF(AND((AS36-TODAY())<=30,(L36-TODAY())<=0,(F84="P2"))=TRUE,"Yes","No")) -> No | AE36: =VLOOKUP(O36,'Data Validation'!I:J,2,FALSE) -> Global | AF36: =IF(AJ36<=53,AJ36,AJ36-52) -> 42.056604 | AG36: =IF(H36="Y",(((160/1000000)*AA36)/5.3)*0.1,((160/1000000)*AA36)/5.3) -> 1.509434 | AH36: =SUM($AG$2:AG36) -> 52.830189 | AI36: =AH36/50 -> 1.0566038 | AJ36: =WEEKNUM(TODAY())+AI36 -> 42.056604 | AK36: 46182 | AL36: Y | AM36: Y | AN36: =AS36-S36 -> 46370 | AS36: 46370
A37: Michael Ameling | B37: =VLOOKUP(A37,'Data Validation'!S:T,2,FALSE) -> Cross Architecture | C37: Yadav, Prashant<prashant.yadav03@sap.com> | D37: On-Mobile Device | E37: On-Mobile Device | F37: P2 | G37: S2 | H37: Y | I37: Incremental ONLY | J37: SAP Concur Mobile Android H1 2026 - Dec | K37: N/A | L37: 46363 | M37: 46370 | N37: GLOBAL | O37: Global | P37: Backlog | Q37: Y | AA37: 500000 | AB37: Open | AC37: No | AD37: =IF((AND((AS37-TODAY())<=30,(L37-TODAY())<=0,(F85="P1")))=TRUE,"Yes",IF(AND((AS37-TODAY())<=30,(L37-TODAY())<=0,(F85="P2"))=TRUE,"Yes","No")) -> No | AE37: =VLOOKUP(O37,'Data Validation'!I:J,2,FALSE) -> Global | AF37: =IF(AJ37<=53,AJ37,AJ37-52) -> 42.086792 | AG37: =IF(H37="Y",(((160/1000000)*AA37)/5.3)*0.1,((160/1000000)*AA37)/5.3) -> 1.509434 | AH37: =SUM($AG$2:AG37) -> 54.339623 | AI37: =AH37/50 -> 1.0867925 | AJ37: =WEEKNUM(TODAY())+AI37 -> 42.086792 | AK37: 46182 | AL37: Y | AM37: Y | AN37: =AS37-S37 -> 46370 | AS37: 46370
A38: Michael Ameling | B38: =VLOOKUP(A38,'Data Validation'!S:T,2,FALSE) -> Cross Architecture | C38: Singh, Shubham<shubham.singh04@sap.com> | D38: On-Premise | E38: On-Premise | F38: P2 | G38: S2 | H38: Y | I38: Incremental ONLY | J38: APIM_EDGE_IC_2611 | K38: N/A | L38: 46339 | M38: 46371 | N38: GLOBAL | O38: Global | P38: Backlog | Q38: Y | AA38: 500000 | AB38: Open | AC38: No | AD38: =IF((AND((AS38-TODAY())<=30,(L38-TODAY())<=0,(F40="P1")))=TRUE,"Yes",IF(AND((AS38-TODAY())<=30,(L38-TODAY())<=0,(F40="P2"))=TRUE,"Yes","No")) -> No | AE38: =VLOOKUP(O38,'Data Validation'!I:J,2,FALSE) -> Global | AF38: =IF(AJ38<=53,AJ38,AJ38-52) -> 42.116981 | AG38: =IF(H38="Y",(((160/1000000)*AA38)/5.3)*0.1,((160/1000000)*AA38)/5.3) -> 1.509434 | AH38: =SUM($AG$2:AG38) -> 55.849057 | AI38: =AH38/50 -> 1.1169811 | AJ38: =WEEKNUM(TODAY())+AI38 -> 42.116981 | AK38: 46122 | AL38: Y | AM38: N | AN38: =AS38-S38 -> 46371 | AS38: 46371
A39: Peter Pluim | B39: Enterprise Cloud Services | C39: Yonchev, Tsonyo<tsonyo.yonchev@sap.com> | D39: On-Premise | E39: On-Premise | F39: P2 | G39: S2 | H39: Y | I39: Incremental ONLY | J39: LaMaRT 2026.24 | K39: 46117 | L39: 46360 | M39: 46377 | N39: GLOBAL | O39: Global | P39: Backlog | Q39: Y | AA39: 500000 | AB39: Open | AC39: No | AD39: No | AE39: =VLOOKUP(O39,'Data Validation'!I:J,2,FALSE) -> Global | AF39: =IF(AJ39<=53,AJ39,AJ39-52) -> 45.316981 | AG39: =IF(H39="Y",(((160/1000000)*AA39)/5.3)*0.1,((160/1000000)*AA39)/5.3) -> 1.509434 | AH39: =SUM($AG$2:AG81) -> 215.84906 | AI39: =AH39/50 -> 4.3169811 | AJ39: =WEEKNUM(TODAY())+AI39 -> 45.316981 | AK39: 46140 | AL39: Y | AM39: N | AN39: =AS39-S39 -> 46377 | AS39: 46377
A40: Peter Pluim | B40: =VLOOKUP(A40,'Data Validation'!S:T,2,FALSE) -> Enterprise Cloud Services | C40: Chakalova, Stela<stela.chakalova@sap.com> | D40: On-Premise | E40: On-Premise | F40: P2 | G40: S2 | H40: Y | I40: Incremental ONLY | J40: Edge Lifecycle Management 1.67 | K40: N/A | L40: 46353 | M40: 46381 | N40: GLOBAL | O40: Global | P40: Backlog | Q40: Y | AA40: 500000 | AB40: Open | AC40: No | AD40: =IF((AND((AS40-TODAY())<=30,(L40-TODAY())<=0,(F36="P1")))=TRUE,"Yes",IF(AND((AS40-TODAY())<=30,(L40-TODAY())<=0,(F36="P2"))=TRUE,"Yes","No")) -> No | AE40: =VLOOKUP(O40,'Data Validation'!I:J,2,FALSE) -> Global | AF40: 22.173585 | AG40: 1.509434 | AH40: =SUM($AG$2:AG40) -> 58.867925 | AI40: 18.173585 | AJ40: 22.173585 | AK40: 46045 | AL40: Y | AM40: N | AN40: -15 | AS40: 46381
A41: Michael Ameling | B41: =VLOOKUP(A41,'Data Validation'!S:T,2,FALSE) -> Cross Architecture | C41: Singh, Shubham<shubham.singh04@sap.com> | D41: On-Premise | E41: On-Premise | F41: P2 | G41: S2 | H41: Y | I41: Incremental ONLY | J41: APIM_EDGE_IC_2612 | K41: N/A | L41: 46367 | M41: 46395 | N41: GLOBAL | O41: Global | P41: Backlog | Q41: Y | AA41: 500000 | AB41: Open | AC41: No | AD41: =IF((AND((AS41-TODAY())<=30,(L41-TODAY())<=0,(F51="P1")))=TRUE,"Yes",IF(AND((AS41-TODAY())<=30,(L41-TODAY())<=0,(F51="P2"))=TRUE,"Yes","No")) -> No | AE41: =VLOOKUP(O41,'Data Validation'!I:J,2,FALSE) -> Global | AF41: =IF(AJ41<=53,AJ41,AJ41-52) -> 42.207547 | AG41: =IF(H41="Y",(((160/1000000)*AA41)/5.3)*0.1,((160/1000000)*AA41)/5.3) -> 1.509434 | AH41: =SUM($AG$2:AG41) -> 60.377358 | AI41: =AH41/50 -> 1.2075472 | AJ41: =WEEKNUM(TODAY())+AI41 -> 42.207547 | AK41: 46122 | AL41: Y | AM41: N | AN41: =AS41-S41 -> 46395 | AS41: 46395
A42: Michael Ameling | B42: =VLOOKUP(A42,'Data Validation'!S:T,2,FALSE) -> Cross Architecture | C42: Yadav, Prashant<prashant.yadav03@sap.com> | D42: On-Mobile Device | E42: On-Mobile Device | F42: P2 | G42: S2 | H42: Y | I42: Incremental ONLY | J42: TripIt Mobile Android 01/2027 | K42: N/A | L42: 46415 | M42: 46419 | N42: GLOBAL | O42: Global | P42: Backlog | Q42: Y | AA42: 500000 | AB42: Open | AC42: No | AD42: =IF((AND((AS42-TODAY())<=30,(L42-TODAY())<=0,(F42="P1")))=TRUE,"Yes",IF(AND((AS42-TODAY())<=30,(L42-TODAY())<=0,(F42="P2"))=TRUE,"Yes","No")) -> No | AE42: =VLOOKUP(O42,'Data Validation'!I:J,2,FALSE) -> Global | AF42: =IF(AJ42<=53,AJ42,AJ42-52) -> 3.2188679 | AG42: =IF(H42="Y",(((160/1000000)*AA42)/5.3)*0.1,((160/1000000)*AA42)/5.3) -> 1.509434 | AH42: =SUM($AG$2:AG247) -> 710.9434 | AI42: =AH42/50 -> 14.218868 | AJ42: =WEEKNUM(TODAY())+AI42 -> 55.218868 | AK42: 46049 | AL42: Y | AM42: Y | AN42: =AS42-S42 -> 46419 | AS42: 46419
A43: Michael Ameling | B43: =VLOOKUP(A43,'Data Validation'!S:T,2,FALSE) -> Cross Architecture | C43: Yadav, Prashant<prashant.yadav03@sap.com> | D43: On-Mobile Device | E43: On-Mobile Device | F43: P2 | G43: S2 | H43: Y | I43: Incremental ONLY | J43: TripIt Mobile iOS 01/2027 | K43: N/A | L43: 46415 | M43: 46419 | N43: GLOBAL | O43: Global | P43: Backlog | Q43: Y | AA43: 500000 | AB43: Open | AC43: No | AD43: =IF((AND((AS43-TODAY())<=30,(L43-TODAY())<=0,(F43="P1")))=TRUE,"Yes",IF(AND((AS43-TODAY())<=30,(L43-TODAY())<=0,(F43="P2"))=TRUE,"Yes","No")) -> No | AE43: =VLOOKUP(O43,'Data Validation'!I:J,2,FALSE) -> Global | AF43: =IF(AJ43<=53,AJ43,AJ43-52) -> 3.2490566 | AG43: =IF(H43="Y",(((160/1000000)*AA43)/5.3)*0.1,((160/1000000)*AA43)/5.3) -> 1.509434 | AH43: =SUM($AG$2:AG248) -> 712.45283 | AI43: =AH43/50 -> 14.249057 | AJ43: =WEEKNUM(TODAY())+AI43 -> 55.249057 | AK43: 46049 | AL43: Y | AM43: Y | AN43: =AS43-S43 -> 46419 | AS43: 46419
A44: Michael Ameling | B44: =VLOOKUP(A44,'Data Validation'!S:T,2,FALSE) -> Cross Architecture | C44: Singh, Shubham<shubham.singh04@sap.com> | D44: On-Premise | E44: On-Premise | F44: P2 | G44: S2 | H44: Y | I44: Incremental ONLY | J44: APIM_EDGE_IC_2613 | K44: N/A | L44: 46395 | M44: 46423 | N44: GLOBAL | O44: Global | P44: Backlog | Q44: Y | AA44: 500000 | AB44: Open | AC44: No | AD44: =IF((AND((AS44-TODAY())<=30,(L44-TODAY())<=0,(F54="P1")))=TRUE,"Yes",IF(AND((AS44-TODAY())<=30,(L44-TODAY())<=0,(F54="P2"))=TRUE,"Yes","No")) -> No | AE44: =VLOOKUP(O44,'Data Validation'!I:J,2,FALSE) -> Global | AF44: =IF(AJ44<=53,AJ44,AJ44-52) -> 42.298113 | AG44: =IF(H44="Y",(((160/1000000)*AA44)/5.3)*0.1,((160/1000000)*AA44)/5.3) -> 1.509434 | AH44: =SUM($AG$2:AG44) -> 64.90566 | AI44: =AH44/50 -> 1.2981132 | AJ44: =WEEKNUM(TODAY())+AI44 -> 42.298113 | AK44: 46122 | AL44: Y | AM44: N | AN44: =AS44-S44 -> 46423 | AS44: 46423
A45: Michael Ameling | B45: =VLOOKUP(A45,'Data Validation'!S:T,2,FALSE) -> Cross Architecture | C45: Yadav, Prashant<prashant.yadav03@sap.com> | D45: On-Mobile Device | E45: On-Mobile Device | F45: P2 | G45: S2 | H45: Y | I45: Incremental ONLY | J45: TripIt Mobile Android 02/2027 | K45: N/A | L45: 46457 | M45: 46461 | N45: GLOBAL | O45: Global | P45: Backlog | Q45: Y | AA45: 500000 | AB45: Open | AC45: No | AD45: =IF((AND((AS45-TODAY())<=30,(L45-TODAY())<=0,(F45="P1")))=TRUE,"Yes",IF(AND((AS45-TODAY())<=30,(L45-TODAY())<=0,(F45="P2"))=TRUE,"Yes","No")) -> No | AE45: =VLOOKUP(O45,'Data Validation'!I:J,2,FALSE) -> Global | AF45: =IF(AJ45<=53,AJ45,AJ45-52) -> 3.309434 | AG45: =IF(H45="Y",(((160/1000000)*AA45)/5.3)*0.1,((160/1000000)*AA45)/5.3) -> 1.509434 | AH45: =SUM($AG$2:AG250) -> 715.4717 | AI45: =AH45/50 -> 14.309434 | AJ45: =WEEKNUM(TODAY())+AI45 -> 55.309434 | AK45: 46049 | AL45: Y | AM45: Y | AN45: =AS45-S45 -> 46461 | AS45: 46461
A46: Michael Ameling | B46: =VLOOKUP(A46,'Data Validation'!S:T,2,FALSE) -> Cross Architecture | C46: Yadav, Prashant<prashant.yadav03@sap.com> | D46: On-Mobile Device | E46: On-Mobile Device | F46: P2 | G46: S2 | H46: Y | I46: Incremental ONLY | J46: TripIt Mobile iOS 02/2027 | K46: N/A | L46: 46457 | M46: 46461 | N46: GLOBAL | O46: Global | P46: Backlog | Q46: Y | AA46: 500000 | AB46: Open | AC46: No | AD46: =IF((AND((AS46-TODAY())<=30,(L46-TODAY())<=0,(F46="P1")))=TRUE,"Yes",IF(AND((AS46-TODAY())<=30,(L46-TODAY())<=0,(F46="P2"))=TRUE,"Yes","No")) -> No | AE46: =VLOOKUP(O46,'Data Validation'!I:J,2,FALSE) -> Global | AF46: =IF(AJ46<=53,AJ46,AJ46-52) -> 3.3396226 | AG46: =IF(H46="Y",(((160/1000000)*AA46)/5.3)*0.1,((160/1000000)*AA46)/5.3) -> 1.509434 | AH46: =SUM($AG$2:AG251) -> 716.98113 | AI46: =AH46/50 -> 14.339623 | AJ46: =WEEKNUM(TODAY())+AI46 -> 55.339623 | AK46: 46049 | AL46: Y | AM46: Y | AN46: =AS46-S46 -> 46461 | AS46: 46461
A47: Michael Ameling | B47: =VLOOKUP(A47,'Data Validation'!S:T,2,FALSE) -> Cross Architecture | C47: Yadav, Prashant<prashant.yadav03@sap.com> | D47: On-Mobile Device | E47: On-Mobile Device | F47: P2 | G47: S2 | H47: Y | I47: Incremental ONLY | J47: TripIt Mobile Android 04/2027 | K47: N/A | L47: 46499 | M47: 46503 | N47: GLOBAL | O47: Global | P47: Backlog | Q47: Y | AA47: 500000 | AB47: Open | AC47: No | AD47: =IF((AND((AS47-TODAY())<=30,(L47-TODAY())<=0,(F47="P1")))=TRUE,"Yes",IF(AND((AS47-TODAY())<=30,(L47-TODAY())<=0,(F47="P2"))=TRUE,"Yes","No")) -> No | AE47: =VLOOKUP(O47,'Data Validation'!I:J,2,FALSE) -> Global | AF47: =IF(AJ47<=53,AJ47,AJ47-52) -> 3.3698113 | AG47: =IF(H47="Y",(((160/1000000)*AA47)/5.3)*0.1,((160/1000000)*AA47)/5.3) -> 1.509434 | AH47: =SUM($AG$2:AG252) -> 718.49057 | AI47: =AH47/50 -> 14.369811 | AJ47: =WEEKNUM(TODAY())+AI47 -> 55.369811 | AK47: 46049 | AL47: Y | AM47: Y | AN47: =AS47-S47 -> 46503 | AS47: 46503
A48: Michael Ameling | B48: =VLOOKUP(A48,'Data Validation'!S:T,2,FALSE) -> Cross Architecture | C48: Yadav, Prashant<prashant.yadav03@sap.com> | D48: On-Mobile Device | E48: On-Mobile Device | F48: P2 | G48: S2 | H48: Y | I48: Incremental ONLY | J48: TripIt Mobile iOS 04/2027 | K48: N/A | L48: 46499 | M48: 46503 | N48: GLOBAL | O48: Global | P48: Backlog | Q48: Y | AA48: 500000 | AB48: Open | AC48: No | AD48: =IF((AND((AS48-TODAY())<=30,(L48-TODAY())<=0,(F48="P1")))=TRUE,"Yes",IF(AND((AS48-TODAY())<=30,(L48-TODAY())<=0,(F48="P2"))=TRUE,"Yes","No")) -> No | AE48: =VLOOKUP(O48,'Data Validation'!I:J,2,FALSE) -> Global | AF48: =IF(AJ48<=53,AJ48,AJ48-52) -> 3.4 | AG48: =IF(H48="Y",(((160/1000000)*AA48)/5.3)*0.1,((160/1000000)*AA48)/5.3) -> 1.509434 | AH48: =SUM($AG$2:AG253) -> 720 | AI48: =AH48/50 -> 14.4 | AJ48: =WEEKNUM(TODAY())+AI48 -> 55.4 | AK48: 46049 | AL48: Y | AM48: Y | AN48: =AS48-S48 -> 46503 | AS48: 46503
A49: Sindhu Gangadharan | B49: =VLOOKUP(A49,'Data Validation'!S:T,2,FALSE) -> SAP User Enabl Mgmt SE | C49: Fromme, Martin<m.fromme@sap.com> | D49: On-Premise | E49: On-Premise | F49: P2 | G49: S2 | H49: Y | I49: Incremental ONLY | J49: 304969951_CSD_BAnst_PT_Pensionsverwaltung | K49: N/A | L49: 46437 | M49: 46534 | N49: GLOBAL | O49: Global | P49: Backlog | Q49: Y | AA49: 500000 | AB49: Open | AC49: No | AD49: =IF((AND((AS49-TODAY())<=30,(L49-TODAY())<=0,(F162="P1")))=TRUE,"Yes",IF(AND((AS49-TODAY())<=30,(L49-TODAY())<=0,(F162="P2"))=TRUE,"Yes","No")) -> No | AE49: =VLOOKUP(O49,'Data Validation'!I:J,2,FALSE) -> Global | AF49: =IF(AJ49<=53,AJ49,AJ49-52) -> 42.449057 | AG49: =IF(H49="Y",(((160/1000000)*AA49)/5.3)*0.1,((160/1000000)*AA49)/5.3) -> 1.509434 | AH49: =SUM($AG$2:AG49) -> 72.45283 | AI49: =AH49/50 -> 1.4490566 | AJ49: =WEEKNUM(TODAY())+AI49 -> 42.449057 | AK49: 46142 | AL49: N | AM49: N | AN49: =AS49-S49 -> 46534 | AS49: 46534
A50: Sindhu Gangadharan | B50: SAP User Enabl Mgmt SE | C50: Gorges,Timo<timo.gorges@sap.com> | D50: On-Premise | E50: On-Premise | F50: P2 | G50: S3 | H50: N | I50: Incremental ONLY | J50: 305734821_AI Supplier Quotation Data_Porsche | K50: 46188 | L50: 46267 | M50: 46280 | N50: GTLC India | O50: Gayathri | P50: Done | Q50: Y | R50: 46275 | S50: 46275 | Z50: Delay from Dev | AA50: 500000 | AB50: Open | AC50: No | AD50: =IF((AND((AS50-TODAY())<=30,(L50-TODAY())<=0,(F51="P1")))=TRUE,"Yes",IF(AND((AS50-TODAY())<=30,(L50-TODAY())<=0,(F51="P2"))=TRUE,"Yes","No")) -> Yes | AE50: C5381614 | AF50: 27.335849 | AG50: 15.09434 | AH50: =SUM($AG$2:AG50) -> 87.54717 | AI50: 23.335849 | AJ50: 27.335849 | AK50: 46252 | AL50: N | AM50: N | AN50: =AS50-S50 -> 5 | AS50: 46280
A51: Sindhu Gangadharan | B51: =VLOOKUP(A51,'Data Validation'!S:T,2,FALSE) -> SAP User Enabl Mgmt SE | C51: Kraemer, Tobias<tobias.kraemer@sap.com> | D51: On-Premise | E51: On-Premise | F51: P2 | G51: S3 | H51: N | I51: Incremental ONLY | J51: AfDB SAP Cloud Portal | K51: 44440 | L51: 46353 | M51: 46377 | N51: GLOBAL | O51: Global | P51: Backlog | Q51: Y | AA51: 500000 | AB51: Open | AC51: No | AD51: =IF((AND((AS51-TODAY())<=30,(L51-TODAY())<=0,(F234="P1")))=TRUE,"Yes",IF(AND((AS51-TODAY())<=30,(L51-TODAY())<=0,(F234="P2"))=TRUE,"Yes","No")) -> No | AE51: =VLOOKUP(O51,'Data Validation'!I:J,2,FALSE) -> Global | AF51: =IF(AJ51<=53,AJ51,AJ51-52) -> 43.05283 | AG51: =IF(H51="Y",(((160/1000000)*AA51)/5.3)*0.1,((160/1000000)*AA51)/5.3) -> 15.09434 | AH51: =SUM($AG$2:AG51) -> 102.64151 | AI51: =AH51/50 -> 2.0528302 | AJ51: =WEEKNUM(TODAY())+AI51 -> 43.05283 | AK51: 46210 | AL51: N | AM51: N | AN51: =AS51-S51 -> 46374 | AS51: 46374
A52: Sindhu Gangadharan | B52: =VLOOKUP(A52,'Data Validation'!S:T,2,FALSE) -> SAP User Enabl Mgmt SE | C52: Gupta, Rubal<rubal.gupta@sap.com> | D52: On-Premise | E52: On-Premise | F52: P2 | G52: S3 | H52: N | I52: Incremental ONLY | J52: 306198073_CSD_JVUpload_HZL | K52: N/A | L52: 46277 | M52: 46295 | N52: GTLC India | O52: Yashwant | P52: Done | Q52: Y | R52: 46283 | S52: 46286 | AA52: 500000 | AB52: Open | AC52: No | AD52: =IF((AND((AS52-TODAY())<=30,(L52-TODAY())<=0,(F87="P1")))=TRUE,"Yes",IF(AND((AS52-TODAY())<=30,(L52-TODAY())<=0,(F87="P2"))=TRUE,"Yes","No")) -> Yes | AE52: =VLOOKUP(O52,'Data Validation'!I:J,2,FALSE) -> C5403671 | AF52: =IF(AJ52<=53,AJ52,AJ52-52) -> 43.354717 | AG52: =IF(H52="Y",(((160/1000000)*AA52)/5.3)*0.1,((160/1000000)*AA52)/5.3) -> 15.09434 | AH52: =SUM($AG$2:AG52) -> 117.73585 | AI52: =AH52/50 -> 2.354717 | AJ52: =WEEKNUM(TODAY())+AI52 -> 43.354717 | AK52: 46230 | AL52: N | AM52: N | AN52: =AS52-S52 -> 2 | AS52: 46288
A53: Sindhu Gangadharan | B53: =VLOOKUP(A53,'Data Validation'!S:T,2,FALSE) -> SAP User Enabl Mgmt SE | C53: Goyal, Mayank<mayank.goyal01@sap.com> | D53: On-Premise | E53: On-Premise | F53: P2 | G53: S3 | H53: N | I53: Incremental ONLY | J53: 306149039_CSD_M-Checks_Migros | K53: 46167 | L53: 46304 | M53: 46367 | N53: GLOBAL | O53: Global | P53: Backlog | Q53: Y | AA53: 500000 | AB53: Open | AC53: No | AD53: =IF((AND((AS53-TODAY())<=30,(L53-TODAY())<=0,(F248="P1")))=TRUE,"Yes",IF(AND((AS53-TODAY())<=30,(L53-TODAY())<=0,(F248="P2"))=TRUE,"Yes","No")) -> No | AE53: =VLOOKUP(O53,'Data Validation'!I:J,2,FALSE) -> Global | AF53: =IF(AJ53<=53,AJ53,AJ53-52) -> 43.656604 | AG53: =IF(H53="Y",(((160/1000000)*AA53)/5.3)*0.1,((160/1000000)*AA53)/5.3) -> 15.09434 | AH53: =SUM($AG$2:AG53) -> 132.83019 | AI53: =AH53/50 -> 2.6566038 | AJ53: =WEEKNUM(TODAY())+AI53 -> 43.656604 | AK53: 46241 | AL53: N | AM53: N | AN53: =AS53-S53 -> 46360 | AS53: 46360
A54: Sindhu Gangadharan | B54: =VLOOKUP(A54,'Data Validation'!S:T,2,FALSE) -> SAP User Enabl Mgmt SE | C54: Varmani, Kapil<kapil.varmani@sap.com> | D54: On-Premise | E54: On-Premise | F54: P2 | G54: S3 | H54: N | I54: Incremental ONLY | J54: 305650509_CSD_Synapxe_NBS2 | K54: 45810 | L54: 46234 | M54: 46538 | N54: GLOBAL | O54: Global | P54: Backlog | Q54: Y | AA54: 500000 | AB54: Open | AC54: No | AD54: =IF((AND((AS54-TODAY())<=30,(L54-TODAY())<=0,(F107="P1")))=TRUE,"Yes",IF(AND((AS54-TODAY())<=30,(L54-TODAY())<=0,(F107="P2"))=TRUE,"Yes","No")) -> No | AE54: =VLOOKUP(O54,'Data Validation'!I:J,2,FALSE) -> Global | AF54: =IF(AJ54<=53,AJ54,AJ54-52) -> 43.958491 | AG54: =IF(H54="Y",(((160/1000000)*AA54)/5.3)*0.1,((160/1000000)*AA54)/5.3) -> 15.09434 | AH54: =SUM($AG$2:AG54) -> 147.92453 | AI54: =AH54/50 -> 2.9584906 | AJ54: =WEEKNUM(TODAY())+AI54 -> 43.958491 | AK54: 46013 | AL54: N | AM54: N | AN54: =AS54-S54 -> 46538 | AS54: 46538
A55: Michael Ameling | B55: =VLOOKUP(A55,'Data Validation'!S:T,2,FALSE) -> Cross Architecture | C55: Dominic Kunnappally, Josep <joseph.dominic.kunnappally@sap.com> | D55: On-Premise | E55: On-Premise | F55: P2 | G55: S4 | H55: Y | I55: Incremental ONLY | J55: SAP MDK TOOLS 1.17 | K55: 46216 | L55: 46269 | M55: 46280 | N55: GTLC India | O55: Gayathri | P55: Done | Q55: Y | R55: 46269 | S55: 46269 | AA55: 500000 | AB55: Open | AC55: No | AD55: =IF((AND((AS55-TODAY())<=30,(L55-TODAY())<=0,(F55="P1")))=TRUE,"Yes",IF(AND((AS55-TODAY())<=30,(L55-TODAY())<=0,(F55="P2"))=TRUE,"Yes","No")) -> Yes | AE55: =VLOOKUP(O55,'Data Validation'!I:J,2,FALSE) -> C5385241 | AF55: =IF(AJ55<=53,AJ55,AJ55-52) -> 43.988679 | AG55: =IF(H55="Y",(((160/1000000)*AA55)/5.3)*0.1,((160/1000000)*AA55)/5.3) -> 1.509434 | AH55: =SUM($AG$2:AG55) -> 149.43396 | AI55: =AH55/50 -> 2.9886792 | AJ55: =WEEKNUM(TODAY())+AI55 -> 43.988679 | AK55: 46258 | AL55: N | AM55: Y | AN55: =AS55-S55 -> 10 | AS55: 46279
A56: Michael Ameling | B56: =VLOOKUP(A56,'Data Validation'!S:T,2,FALSE) -> Cross Architecture | C56: Asapu, Ajai kumar<ajai.kumar.asapu@sap.com> | D56: On-Mobile Device | E56: On-Mobile Device | F56: P2 | G56: S4 | H56: Y | I56: Incremental ONLY | J56: Joule Work 3.2 iOS | K56: N/A | L56: 46274 | M56: 46295 | N56: GTLC India | O56: Arpitha | P56: Done | Q56: Y | R56: 46280 | S56: 46287 | AA56: 500000 | AB56: Open | AC56: No | AD56: =IF((AND((AS56-TODAY())<=30,(L56-TODAY())<=0,(F57="P1")))=TRUE,"Yes",IF(AND((AS56-TODAY())<=30,(L56-TODAY())<=0,(F57="P2"))=TRUE,"Yes","No")) -> Yes | AE56: =VLOOKUP(O56,'Data Validation'!I:J,2,FALSE) -> C5396309 | AF56: =IF(AJ56<=53,AJ56,AJ56-52) -> 44.018868 | AG56: =IF(H56="Y",(((160/1000000)*AA56)/5.3)*0.1,((160/1000000)*AA56)/5.3) -> 1.509434 | AH56: =SUM($AG$2:AG56) -> 150.9434 | AI56: =AH56/50 -> 3.0188679 | AJ56: =WEEKNUM(TODAY())+AI56 -> 44.018868 | AK56: 46154 | AL56: N | AM56: N | AN56: =AS56-S56 -> -88 | AS56: 46199
A57: Michael Ameling | B57: =VLOOKUP(A57,'Data Validation'!S:T,2,FALSE) -> Cross Architecture | C57: Hayat, Umair Abbas<umair.abbas.hayat@sap.com> | D57: On-Mobile Device | E57: On-Mobile Device | F57: P2 | G57: S4 | H57: Y | I57: Incremental ONLY | J57: Joule Work 3.2 Android | K57: N/A | L57: 46274 | M57: 46295 | N57: GTLC India | O57: Arpitha | P57: Done | Q57: Y | R57: 46280 | S57: 46290 | AA57: 500000 | AB57: Open | AC57: No | AD57: =IF((AND((AS57-TODAY())<=30,(L57-TODAY())<=0,(F377="P1")))=TRUE,"Yes",IF(AND((AS57-TODAY())<=30,(L57-TODAY())<=0,(F377="P2"))=TRUE,"Yes","No")) -> Yes | AE57: =VLOOKUP(O57,'Data Validation'!I:J,2,FALSE) -> C5396309 | AF57: =IF(AJ57<=53,AJ57,AJ57-52) -> 44.049057 | AG57: =IF(H57="Y",(((160/1000000)*AA57)/5.3)*0.1,((160/1000000)*AA57)/5.3) -> 1.509434 | AH57: =SUM($AG$2:AG57) -> 152.45283 | AI57: =AH57/50 -> 3.0490566 | AJ57: =WEEKNUM(TODAY())+AI57 -> 44.049057 | AK57: 46225 | AL57: N | AM57: N | AN57: =AS57-S57 -> 3 | AS57: 46293
A58: Michael Ameling | B58: =VLOOKUP(A58,'Data Validation'!S:T,2,FALSE) -> Cross Architecture | C58: Koehl, Felix <felix.koehl@sap.com> | D58: On-Premise | E58: On-Premise | F58: P2 | G58: S4 | H58: Y | I58: Incremental ONLY | J58: SAPUI5 1.153 | K58: N/A | L58: 46281 | M58: 46296 | N58: GTLC India | O58: Yashwant | P58: Done | Q58: Y | R58: 46283 | S58: 46287 | AA58: 500000 | AB58: Open | AC58: No | AD58: =IF((AND((AS58-TODAY())<=30,(L58-TODAY())<=0,(F58="P1")))=TRUE,"Yes",IF(AND((AS58-TODAY())<=30,(L58-TODAY())<=0,(F58="P2"))=TRUE,"Yes","No")) -> Yes | AE58: =VLOOKUP(O58,'Data Validation'!I:J,2,FALSE) -> C5403671 | AF58: =IF(AJ58<=53,AJ58,AJ58-52) -> 44.079245 | AG58: =IF(H58="Y",(((160/1000000)*AA58)/5.3)*0.1,((160/1000000)*AA58)/5.3) -> 1.509434 | AH58: =SUM($AG$2:AG58) -> 153.96226 | AI58: =AH58/50 -> 3.0792453 | AJ58: =WEEKNUM(TODAY())+AI58 -> 44.079245 | AK58: 45981 | AL58: Y | AM58: N | AN58: =AS58-S58 -> 9 | AS58: 46296
A59: Michael Ameling | B59: =VLOOKUP(A59,'Data Validation'!S:T,2,FALSE) -> Cross Architecture | C59: Koehl, Felix <felix.koehl@sap.com> | D59: On-Premise | E59: On-Premise | F59: P2 | G59: S4 | H59: Y | I59: Incremental ONLY | J59: SAPUI5 1.154 | K59: N/A | L59: 46309 | M59: 46324 | N59: GLOBAL | O59: Global | P59: Backlog | Q59: Y | AA59: 500000 | AB59: Open | AC59: No | AD59: =IF((AND((AS59-TODAY())<=30,(L59-TODAY())<=0,(F59="P1")))=TRUE,"Yes",IF(AND((AS59-TODAY())<=30,(L59-TODAY())<=0,(F59="P2"))=TRUE,"Yes","No")) -> No | AE59: =VLOOKUP(O59,'Data Validation'!I:J,2,FALSE) -> Global | AF59: =IF(AJ59<=53,AJ59,AJ59-52) -> 44.109434 | AG59: =IF(H59="Y",(((160/1000000)*AA59)/5.3)*0.1,((160/1000000)*AA59)/5.3) -> 1.509434 | AH59: =SUM($AG$2:AG59) -> 155.4717 | AI59: =AH59/50 -> 3.109434 | AJ59: =WEEKNUM(TODAY())+AI59 -> 44.109434 | AK59: 45981 | AL59: Y | AM59: N | AN59: =AS59-S59 -> 46324 | AS59: 46324
A60: Michael Ameling | B60: =VLOOKUP(A60,'Data Validation'!S:T,2,FALSE) -> Cross Architecture | C60: Koehl, Felix <felix.koehl@sap.com> | D60: On-Premise | E60: On-Premise | F60: P2 | G60: S4 | H60: Y | I60: Incremental ONLY | J60: SAPUI5 1.155 | K60: N/A | L60: 46337 | M60: 46352 | N60: GLOBAL | O60: Global | P60: Backlog | Q60: Y | AA60: 500000 | AB60: Open | AC60: No | AD60: =IF((AND((AS60-TODAY())<=30,(L60-TODAY())<=0,(F60="P1")))=TRUE,"Yes",IF(AND((AS60-TODAY())<=30,(L60-TODAY())<=0,(F60="P2"))=TRUE,"Yes","No")) -> No | AE60: =VLOOKUP(O60,'Data Validation'!I:J,2,FALSE) -> Global | AF60: =IF(AJ60<=53,AJ60,AJ60-52) -> 44.139623 | AG60: =IF(H60="Y",(((160/1000000)*AA60)/5.3)*0.1,((160/1000000)*AA60)/5.3) -> 1.509434 | AH60: =SUM($AG$2:AG60) -> 156.98113 | AI60: =AH60/50 -> 3.1396226 | AJ60: =WEEKNUM(TODAY())+AI60 -> 44.139623 | AK60: 45981 | AL60: Y | AM60: N | AN60: =AS60-S60 -> 46352 | AS60: 46352
A61: Manoj Swaminathan | B61: ISBN CloudOps Cross COPS | C61: Jain, Vimal Mohan<vimal.mohan.jain@sap.com> | D61: On-Premise | E61: On-Premise | F61: P2 | G61: S4 | H61: Y | I61: Incremental ONLY | J61: SAP GRC FOR SAP HANA 1.0 SP02 | K61: 46041 | L61: 46248 | M61: 46353 | N61: GTLC India | O61: Yashwant | P61: In Progress | Q61: Y | R61: 46294 | AA61: 500000 | AB61: Open | AC61: No | AD61: =IF((AND((AS61-TODAY())<=30,(L61-TODAY())<=0,(F62="P1")))=TRUE,"Yes",IF(AND((AS61-TODAY())<=30,(L61-TODAY())<=0,(F62="P2"))=TRUE,"Yes","No")) -> No | AE61: =VLOOKUP(O61,'Data Validation'!I:J,2,FALSE) -> C5403671 | AF61: =IF(AJ61<=53,AJ61,AJ61-52) -> 44.169811 | AG61: =IF(H61="Y",(((160/1000000)*AA61)/5.3)*0.1,((160/1000000)*AA61)/5.3) -> 1.509434 | AH61: =SUM($AG$2:AG61) -> 158.49057 | AI61: =AH61/50 -> 3.1698113 | AJ61: =WEEKNUM(TODAY())+AI61 -> 44.169811 | AK61: 46231 | AL61: N | AM61: N | AN61: =AS61-S61 -> 46353 | AS61: 46353
A62: Michael Ameling | B62: Cross Architecture | C62: Noack, Jason <jason.noack@sap.com> | D62: Outbound OEM | E62: On-Premise | F62: P1 | G62: S2 | H62: Y | I62: Incremental ONLY | J62: Sybase IQ 16.1 SPS05 PL18 | K62: N/A | L62: 46192 | M62: 46233 | N62: GTLC India | O62: Yashwant | P62: In Progress | Q62: Y | R62: 46210 | AA62: 500000 | AB62: Open | AC62: No | AD62: Yes | AE62: C5380108 | AF62: 19.909434 | AG62: 1.509434 | AH62: 795.4717 | AI62: 15.909434 | AJ62: 19.909434 | AK62: 46192 | AL62: N | AM62: Y | AN62: 18 | AS62: 46220
A63: Michael Ameling | B63: Cross Architecture | C63: Noack, Jason <jason.noack@sap.com> | D63: Outbound OEM | E63: On-Premise | F63: P1 | G63: S2 | H63: Y | I63: Incremental ONLY | J63: Sybase IQ 16.2 SPS00 PL02 | K63: N/A | L63: 46192 | M63: 46233 | N63: GTLC India | O63: Yashwant | P63: In Progress | Q63: Y | R63: 46210 | AA63: 500000 | AB63: Open | AC63: No | AD63: Yes | AE63: C5380108 | AF63: 19.909434 | AG63: 1.509434 | AH63: 795.4717 | AI63: 15.909434 | AJ63: 19.909434 | AK63: 46192 | AL63: N | AM63: Y | AN63: 18 | AS63: 46220
A64: Philipp Herzig | B64: Product Engineering Intelligent Enterprise and Cross Architecture | C64: Yadav, Bharati<bharati.yadav@sap.com> | D64: Outbound OEM | E64: On-Premise | F64: P1 | G64: S2 | H64: Y | I64: Incremental ONLY | J64: OS 16.1 SP01 PL00 | K64: 46023 | L64: 46218 | M64: 46273 | N64: GTLC India | O64: Yashwant | P64: In Progress | Q64: Y | R64: 46237 | AA64: 500000 | AB64: Open | AC64: No | AD64: Yes | AE64: C5380108 | AF64: 8.1358491 | AG64: 1.509434 | AH64: 206.79245 | AI64: 4.1358491 | AJ64: 8.1358491 | AK64: 46209 | AL64: N | AM64: N | AN64: 34 | AO64: 3 | AP64: 4 | AQ64: 150 | AS64: 46261
A65: Philipp Herzig | B65: Product Engineering Intelligent Enterprise and Cross Architecture | C65: Yadav, Bharati<bharati.yadav@sap.com> | D65: Outbound OEM | E65: On-Premise | F65: P1 | G65: S2 | H65: Y | I65: Incremental ONLY | J65: SDK 16.1 Sp01 PL00 | K65: 46023 | L65: 46218 | M65: 46273 | N65: GTLC India | O65: Apoorva | P65: In Progress | Q65: Y | R65: 46231 | AA65: 500000 | AB65: Open | AC65: No | AD65: Yes | AE65: C5380108 | AF65: 8.1358491 | AG65: 1.509434 | AH65: 206.79245 | AI65: 4.1358491 | AJ65: 8.1358491 | AK65: 46209 | AL65: N | AM65: N | AN65: 34 | AO65: 15 | AP65: 5 | AQ65: 288 | AS65: 46261
A66: Michael Ameling | B66: =VLOOKUP(A66,'Data Validation'!S:T,2,FALSE) -> Cross Architecture | C66: Dong, Zhi-peng <zhi-peng.dong@sap.com> | D66: Outbound OEM | E66: On-Premise | F66: P1 | G66: S2 | H66: Y | I66: Incremental ONLY | J66: ASE 16.1 SP01 PL00 | K66: N/A | L66: 46199 | M66: 46279 | N66: GTLC India | O66: Arun | P66: In Progress | Q66: Y | R66: 46224 | AA66: 500000 | AB66: Open | AC66: No | AD66: =IF((AND((AS66-TODAY())<=30,(L66-TODAY())<=0,(#REF!="P1")))=TRUE,"Yes",IF(AND((AS66-TODAY())<=30,(L66-TODAY())<=0,(#REF!="P2"))=TRUE,"Yes","No")) -> #REF! | AE66: =VLOOKUP(O66,'Data Validation'!I:J,2,FALSE) -> C5381614 | AF66: =IF(AJ66<=53,AJ66,AJ66-52) -> 44.350943 | AG66: =IF(H66="Y",(((160/1000000)*AA66)/5.3)*0.1,((160/1000000)*AA66)/5.3) -> 1.509434 | AH66: =SUM($AG$2:AG67) -> 167.54717 | AI66: =AH66/50 -> 3.3509434 | AJ66: =WEEKNUM(TODAY())+AI66 -> 44.350943 | AK66: 46213 | AL66: N | AM66: N | AN66: =AS66-S66 -> 46272 | AO66: 9 | AP66: 5 | AQ66: 686 | AS66: 46272
A67: Michael Ameling | B67: =VLOOKUP(A67,'Data Validation'!S:T,2,FALSE) -> Cross Architecture | C67: Zhong, Gary <gary.zhong@sap.com> | D67: Outbound OEM | E67: On-Premise | F67: P1 | G67: S2 | H67: Y | I67: Incremental ONLY | J67: SRS 16.1 SP01 PL00 | K67: N/A | L67: 46190 | M67: 46279 | N67: GTLC India | O67: Yashwant | P67: In Progress | Q67: Y | R67: 46226 | AA67: 500000 | AB67: Open | AC67: No | AD67: =IF((AND((AS67-TODAY())<=30,(L67-TODAY())<=0,(F67="P1")))=TRUE,"Yes",IF(AND((AS67-TODAY())<=30,(L67-TODAY())<=0,(F67="P2"))=TRUE,"Yes","No")) -> Yes | AE67: =VLOOKUP(O67,'Data Validation'!I:J,2,FALSE) -> C5403671 | AF67: =IF(AJ67<=53,AJ67,AJ67-52) -> 44.350943 | AG67: =IF(H67="Y",(((160/1000000)*AA67)/5.3)*0.1,((160/1000000)*AA67)/5.3) -> 1.509434 | AH67: =SUM($AG$2:AG67) -> 167.54717 | AI67: =AH67/50 -> 3.3509434 | AJ67: =WEEKNUM(TODAY())+AI67 -> 44.350943 | AK67: 46212 | AL67: N | AM67: N | AN67: =AS67-S67 -> 46272 | AO67: 13 | AP67: 5 | AQ67: 8 | AS67: 46272
A68: Sindhu Gangadharan | B68: =VLOOKUP(A68,'Data Validation'!S:T,2,FALSE) -> SAP User Enabl Mgmt SE | C68: Fromme, Martin<m.fromme@sap.com> | D68: On-Premise | E68: On-Premise | F68: P2 | G68: S2 | H68: Y | I68: Incremental ONLY | J68: 304969951_CSD_BAnst_PT_Pensionsverwaltung(Initial) | K68: N/A | L68: 46153 | M68: 46198 | N68: GTLC Germany | O68: Iliyan | P68: In Progress | Q68: Y | R68: 46160 | AA68: 500000 | AB68: Open | AC68: No | AD68: =IF((AND((AS68-TODAY())<=30,(L68-TODAY())<=0,(F185="P1")))=TRUE,"Yes",IF(AND((AS68-TODAY())<=30,(L68-TODAY())<=0,(F185="P2"))=TRUE,"Yes","No")) -> Yes | AE68: =VLOOKUP(O68,'Data Validation'!I:J,2,FALSE) -> I757367 | AF68: =IF(AJ68<=53,AJ68,AJ68-52) -> 44.381132 | AG68: =IF(H68="Y",(((160/1000000)*AA68)/5.3)*0.1,((160/1000000)*AA68)/5.3) -> 1.509434 | AH68: =SUM($AG$2:AG68) -> 169.0566 | AI68: =AH68/50 -> 3.3811321 | AJ68: =WEEKNUM(TODAY())+AI68 -> 44.381132 | AK68: 46142 | AL68: N | AM68: N | AN68: =AS68-S68 -> 46173 | AS68: 46173
A69: Peter Pluim | B69: Enterprise Cloud Services | C69: Yonchev, Tsonyo<tsonyo.yonchev@sap.com> | D69: On-Premise | E69: On-Premise | F69: P2 | G69: S2 | H69: Y | I69: Incremental ONLY | J69: LaMaRT 2026.16 | K69: 46117 | L69: 46248 | M69: 46265 | N69: GTLC Germany | O69: Sushma | P69: In Progress | Q69: Y | R69: 46251 | AA69: 500000 | AB69: Open | AC69: No | AD69: =IF((AND((AS69-TODAY())<=30,(L70-TODAY())<=0,(F69="P1")))=TRUE,"Yes",IF(AND((AS69-TODAY())<=30,(L70-TODAY())<=0,(F69="P2"))=TRUE,"Yes","No")) -> Yes | AE69: =VLOOKUP(O69,'Data Validation'!I:J,2,FALSE) -> I773708 | AF69: =IF(AJ69<=53,AJ69,AJ69-52) -> 48.426415 | AG69: =IF(H69="Y",(((160/1000000)*AA69)/5.3)*0.1,((160/1000000)*AA69)/5.3) -> 1.509434 | AH69: =SUM($AG$2:AG112) -> 371.32075 | AI69: =AH69/50 -> 7.4264151 | AJ69: =WEEKNUM(TODAY())+AI69 -> 48.426415 | AK69: 46140 | AL69: Y | AM69: N | AN69: =AS69-S69 -> 46265 | AS69: 46265
A70: Philipp Herzig | B70: =VLOOKUP(A70,'Data Validation'!S:T,2,FALSE) -> Product Engineering Intelligent Enterprise and Cross Architecture | C70: Videnov, Iliyan<iliyan.videnov@sap.com> | D70: On-Premise | E70: On-Premise | F70: P2 | G70: S2 | H70: Y | I70: Incremental ONLY | J70: FS on K8s Delivery 2608b | K70: 46244 | L70: 46255 | M70: 46268 | N70: GTLC India | O70: Ankitha | P70: Done | Q70: Y | R70: 46260 | S70: 46267 | Z70: Delay from Dev | AA70: 500000 | AB70: Open | AC70: No | AD70: =IF((AND((AS70-TODAY())<=30,(L70-TODAY())<=0,(F80="P1")))=TRUE,"Yes",IF(AND((AS70-TODAY())<=30,(L70-TODAY())<=0,(F80="P2"))=TRUE,"Yes","No")) -> Yes | AE70: I758929 | AF70: 21.449057 | AG70: 1.509434 | AH70: =SUM($AG$2:AG70) -> 172.07547 | AI70: 17.449057 | AJ70: 21.449057 | AK70: 46253 | AL70: N | AM70: Y | AN70: =AS70-S70 -> 0 | AR70: -1 | AS70: 46267
A71: Dominik Metzger | B71: People Growth Management Office UK | C71: Gusmao, Felipe<f.gusmao@sap.com> | D71: On-Premise | E71: On-Premise | F71: P2 | G71: S2 | H71: Y | I71: Incremental ONLY | J71: 306034556_CSD_Marathon_Smart_Search_Phase2 | K71: 46118 | L71: 46248 | M71: 46289 | N71: GTLC India | O71: Gayathri | P71: Done | Q71: Y | R71: 46260 | S71: 46281 | Z71: Delay from Dev | AA71: 500000 | AB71: Open | AC71: No | AD71: =IF((AND((AS71-TODAY())<=30,(L71-TODAY())<=0,(F72="P1")))=TRUE,"Yes",IF(AND((AS71-TODAY())<=30,(L71-TODAY())<=0,(F72="P2"))=TRUE,"Yes","No")) -> Yes | AE71: I540507 | AF71: 21.479245 | AG71: 1.509434 | AH71: =SUM($AG$2:AG71) -> 173.58491 | AI71: 17.479245 | AJ71: 21.479245 | AK71: 46247 | AL71: N | AM71: N | AN71: =AS71-S71 -> -20 | AS71: 46261
A72: Peter Pluim | B72: =VLOOKUP(A72,'Data Validation'!S:T,2,FALSE) -> Enterprise Cloud Services | C72: Chakalova, Stela<stela.chakalova@sap.com> | D72: On-Premise | E72: On-Premise | F72: P2 | G72: S2 | H72: Y | I72: Incremental ONLY | J72: Edge Lifecycle Management 1.63 | K72: N/A | L72: 46241 | M72: 46269 | N72: GTLC India | O72: Viswa | P72: Done | Q72: Y | R72: 46244 | S72: 46280 | AA72: 500000 | AB72: Open | AC72: No | AD72: =IF((AND((AS72-TODAY())<=30,(L72-TODAY())<=0,(F73="P1")))=TRUE,"Yes",IF(AND((AS72-TODAY())<=30,(L72-TODAY())<=0,(F73="P2"))=TRUE,"Yes","No")) -> Yes | AE72: =VLOOKUP(O72,'Data Validation'!I:J,2,FALSE) -> C5366020 | AF72: 22.173585 | AG72: 1.509434 | AH72: =SUM($AG$2:AG72) -> 175.09434 | AI72: 18.173585 | AJ72: 22.173585 | AK72: 46045 | AL72: Y | AM72: N | AN72: -15 | AS72: 46269
A73: Michael Ameling | B73: Cross Architecture | C73: Branker, India <india.branker@sap.com> | D73: On-Premise | E73: On-Premise | F73: P2 | G73: S2 | H73: Y | I73: Incremental ONLY | J73: MDK Windows 4.1 | K73: 46125 | L73: 46220 | M73: 46276 | N73: GTLC India | O73: Arpitha | P73: Done | Q73: Y | R73: 46246 | S73: 46268 | Z73: Delay from Dev | AA73: 500000 | AB73: Open | AC73: No | AD73: Yes | AE73: C5403671 | AF73: 21.932076 | AG73: 1.509434 | AH73: 896.60378 | AI73: 17.932076 | AJ73: 21.932076 | AK73: 46239 | AL73: N | AM73: N | AN73: -20 | AS73: 46274
A74: Manoj Swaminathan | B74: ISBN CloudOps Cross COPS | C74: Cui, Charlene<charlene.cui@sap.com> | D74: On-Premise | E74: On-Premise | F74: P2 | G74: S2 | H74: Y | I74: Incremental ONLY | J74: Integration framework for SMEs 1.0 PL20 | K74: N/A | L74: 46255 | M74: 46276 | N74: GTLC India | O74: Arpitha | P74: Done | Q74: Y | R74: 46260 | S74: 46275 | Z74: Delay from Dev | AA74: 500000 | AB74: Open | AC74: No | AD74: =IF((AND((AS74-TODAY())<=30,(L74-TODAY())<=0,(F74="P1")))=TRUE,"Yes",IF(AND((AS74-TODAY())<=30,(L74-TODAY())<=0,(F74="P2"))=TRUE,"Yes","No")) -> Yes | AE74: =VLOOKUP(O74,'Data Validation'!I:J,2,FALSE) -> C5396309 | AF74: =IF(AJ74<=53,AJ74,AJ74-52) -> 6.8716981 | AG74: =IF(H74="Y",(((160/1000000)*AA74)/5.3)*0.1,((160/1000000)*AA74)/5.3) -> 1.509434 | AH74: =SUM($AG$2:AG323) -> 893.58491 | AI74: =AH74/50 -> 17.871698 | AJ74: =WEEKNUM(TODAY())+AI74 -> 58.871698 | AK74: 46259 | AL74: N | AM74: N | AN74: =AS74-S74 -> 1 | AS74: 46276
A75: Michael Ameling | B75: =VLOOKUP(A75,'Data Validation'!S:T,2,FALSE) -> Cross Architecture | C75: Singh, Shubham<shubham.singh04@sap.com> | D75: On-Premise | E75: On-Premise | F75: P2 | G75: S2 | H75: Y | I75: Incremental ONLY | J75: APIM_EDGE_IC_2608 | K75: N/A | L75: 46255 | M75: 46283 | N75: GTLC Germany | O75: Sushma | P75: Done | Q75: Y | R75: 46259 | S75: 46265 | AA75: 500000 | AB75: Open | AC75: No | AD75: =IF((AND((AS75-TODAY())<=30,(L75-TODAY())<=0,(F76="P1")))=TRUE,"Yes",IF(AND((AS75-TODAY())<=30,(L75-TODAY())<=0,(F76="P2"))=TRUE,"Yes","No")) -> Yes | AE75: =VLOOKUP(O75,'Data Validation'!I:J,2,FALSE) -> I773708 | AF75: =IF(AJ75<=53,AJ75,AJ75-52) -> 44.592453 | AG75: =IF(H75="Y",(((160/1000000)*AA75)/5.3)*0.1,((160/1000000)*AA75)/5.3) -> 1.509434 | AH75: =SUM($AG$2:AG75) -> 179.62264 | AI75: =AH75/50 -> 3.5924528 | AJ75: =WEEKNUM(TODAY())+AI75 -> 44.592453 | AK75: 46122 | AL75: Y | AM75: N | AN75: =AS75-S75 -> 18 | AS75: 46283
A76: Stefan Steinle | B76: Customer Solution Support and Innovation | C76: Michel, Annett<a.michel@sap.com> | D76: On-Premise | E76: On-Premise | F76: P2 | G76: S2 | H76: Y | I76: Incremental ONLY | J76: SAP Solution Manager 7.2 FP22 | K76: 46235 | L76: 46213 | M76: 46311 | N76: GTLC Germany | O76: Iliyan | P76: In Progress | Q76: Y | R76: 46247 | AA76: 500000 | AB76: Open | AC76: No | AD76: Yes | AE76: I559269 | AF76: 31.290566 | AG76: 1.509434 | AH76: 1364.5283 | AI76: 27.290566 | AJ76: 31.290566 | AK76: 46225 | AL76: N | AM76: N | AN76: 42 | AS76: 46310
A77: Michael Ameling | B77: Cross Architecture | C77: G., Anil Kumar <anil.kumar.g@sap.com> | D77: On-Premise | E77: On-Premise | F77: P2 | G77: S2 | H77: Y | I77: Incremental ONLY | J77: NetWeaver 7.50 SP37 | K77: 46139 | L77: 46216 | M77: 46325 | N77: GTLC Vietnam | O77: Hoan | P77: Done | Q77: Y | R77: 46189 | S77: 46283 | AA77: 500000 | AB77: Open | AC77: No | AD77: Yes | AE77: I758150 | AF77: 21.388679 | AG77: 1.509434 | AH77: 869.43397 | AI77: 17.388679 | AJ77: 21.388679 | AK77: 46259 | AL77: N | AM77: N | AN77: 17 | AS77: 46314
A78: Dominik Metzger | B78: People Growth Management Office UK | C78: Liyakathali,Suhair<suhair.liyakathali@sap.com> | D78: On-Premise | E78: On-Premise | F78: P2 | G78: S4 | H78: Y | I78: Incremental ONLY | J78: Digital Manufacturing Production Connector 2608 | K78: 46160 | L78: 46220 | M78: 46249 | N78: GTLC Germany | O78: Giang | P78: Done | Q78: Y | R78: 46223 | S78: 46258 | Z78: Delay from Dev | AA78: 500000 | AB78: Open | AC78: No | AD78: =IF((AND((AS78-TODAY())<=30,(L78-TODAY())<=0,(F79="P1")))=TRUE,"Yes",IF(AND((AS78-TODAY())<=30,(L78-TODAY())<=0,(F79="P2"))=TRUE,"Yes","No")) -> Yes | AE78: I540507 | AF78: 21.479245 | AG78: 1.509434 | AH78: =SUM($AG$2:AG78) -> 184.15094 | AI78: 17.479245 | AJ78: 21.479245 | AK78: 46204 | AL78: N | AM78: N | AN78: =AS78-S78 -> -11 | AS78: 46247
A79: Daniel Mueller | B79: Strategy & Transformation, Customer Success | C79: Shasho, Chen<chen.shasho@sap.com> | D79: On-Premise | E79: On-Premise | F79: P2 | G79: S4 | H79: Y | I79: Incremental ONLY | J79: WalkMe Q3 2026 | K79: N/A | L79: 46250 | M79: 46292 | N79: GTLC Germany | O79: Giang | P79: Done | Q79: Y | R79: 46237 | S79: 46273 | Z79: Delay from Dev | AA79: 500000 | AB79: Open | AC79: No | AD79: Yes | AE79: C5367590 | AF79: 27.637736 | AG79: 15.09434 | AH79: 1181.8868 | AI79: 23.637736 | AJ79: 27.637736 | AK79: 46236 | AL79: N | AM79: Y | AN79: 8 | AS79: 46279
A80: Uma Rani T M | B80: Strategy & Transformation, Customer Success | C80: Thyagarajan, Harsha Varadhan<harsha.varadhan.thyagarajan@sap.com> | D80: On-Premise | E80: On-Premise | F80: P2 | G80: S4 | H80: Y | I80: Incremental ONLY | J80: SAP UI Logging for S/4HANA 2011 SP08 | K80: 46113 | L80: 46248 | M80: 46310 | N80: GTLC Germany | O80: Sushma | P80: Done | Q80: Y | R80: 46260 | S80: 46280 | Z80: Delay from Dev | AA80: 500000 | AB80: Open | AC80: No | AD80: No | AE80: C5367590 | AF80: 31.984906 | AG80: 1.509434 | AH80: 1399.2453 | AI80: 27.984906 | AJ80: 31.984906 | AK80: 46177 | AL80: N | AM80: N | AN80: =AS80-S80 -> 0 | AS80: 46280
A81: Sindhu Gangadharan | B81: SAP User Enabl Mgmt SE | C81: Arumugam, Surendren<surendren.arumugam@sap.com> | D81: Source Code | E81: On-Premise | F81: P1 | G81: S1 | H81: N | I81: Incremental ONLY | J81: 305012457_CAE_Boehringer_Ingelheim | K81: 45838 | L81: 45991 | M81: 45998 | N81: GTLC India | O81: Apoorva | P81: Done | Q81: Y | R81: 46078 | S81: 46084 | AA81: 500000 | AB81: Open | AC81: No | AD81: =IF((AND((AS81-TODAY())<=30,(L81-TODAY())<=0,(F82="P1")))=TRUE,"Yes",IF(AND((AS81-TODAY())<=30,(L81-TODAY())<=0,(F82="P2"))=TRUE,"Yes","No")) -> Yes | AE81: C5385241 | AF81: 17.615094 | AG81: 15.09434 | AH81: =SUM($AG$2:AG81) -> 215.84906 | AI81: 13.615094 | AJ81: 17.615094 | AK81: 46042 | AL81: N | AM81: N | AN81: =AS81-S81 -> 16 | AS81: 46100
A82: Sindhu Gangadharan | B82: SAP User Enabl Mgmt SE | C82: Pandey, Ashish<ashish.pandey02@sap.com> | D82: On-Premise | E82: On-Premise | F82: P1 | G82: S1 | H82: N | I82: Incremental ONLY | J82: QRO Online Enhancements Release3e | K82: N/A | L82: 46014 | M82: 46045 | N82: GTLC China | O82: Yi Zhang | P82: Done | Q82: Y | R82: 46024 | S82: 46038 | Z82: Delay from Dev | AA82: 500000 | AB82: Open | AC82: No | AD82: =IF((AND((AS82-TODAY())<=30,(L82-TODAY())<=0,(F83="P1")))=TRUE,"Yes",IF(AND((AS82-TODAY())<=30,(L82-TODAY())<=0,(F83="P2"))=TRUE,"Yes","No")) -> Yes | AE82: C5366020 | AF82: 16.588679 | AG82: 15.09434 | AH82: =SUM($AG$2:AG82) -> 230.9434 | AI82: 12.588679 | AJ82: 16.588679 | AK82: 46014 | AL82: N | AM82: N | AN82: =AS82-S82 -> 14 | AO82: 2 | AP82: 0 | AQ82: 0 | AS82: 46052
A83: Sindhu Gangadharan | B83: SAP User Enabl Mgmt SE | C83: Srivastava, Avikalpa<avikalpa.srivastava@sap.com> | D83: On-Premise | E83: On-Premise | F83: P1 | G83: S1 | H83: N | I83: Incremental ONLY | J83: QRO Online Enhancements Release3e-CF source code | K83: 45427 | L83: 45980 | M83: 46087 | N83: GTLC India | O83: Apoorva | P83: Done | Q83: Y | R83: 46069 | S83: 46079 | Z83: Delay from Dev | AA83: 500000 | AB83: Open | AC83: No | AD83: =IF((AND((AS83-TODAY())<=30,(L83-TODAY())<=0,(F84="P1")))=TRUE,"Yes",IF(AND((AS83-TODAY())<=30,(L83-TODAY())<=0,(F84="P2"))=TRUE,"Yes","No")) -> Yes | AE83: C5366020 | AF83: 16.588679 | AG83: 15.09434 | AH83: =SUM($AG$2:AG83) -> 246.03774 | AI83: 12.588679 | AJ83: 16.588679 | AK83: 46058 | AL83: N | AM83: N | AN83: =AS83-S83 -> 0 | AS83: 46079
A84: Sindhu Gangadharan | B84: =VLOOKUP(A84,'Data Validation'!S:T,2,FALSE) -> SAP User Enabl Mgmt SE | C84: Schuewer, Matthias<matthias.schuewer@sap.com> | D84: On-Premise | E84: On-Premise | F84: P1 | G84: S1 | H84: N | I84: Incremental ONLY | J84: 306181513_Sprint 0 T-Systems | K84: 46110 | L84: 46153 | M84: 46155 | N84: GTLC India | O84: Viswa | P84: Done | Q84: Y | R84: 46154 | S84: 46155 | Z84: Delay from Dev | AA84: 500000 | AB84: Open | AC84: No | AD84: =IF((AND((AT84-TODAY())<=30,(L84-TODAY())<=0,(F84="P1")))=TRUE,"Yes",IF(AND((AT84-TODAY())<=30,(L84-TODAY())<=0,(F84="P2"))=TRUE,"Yes","No")) -> Yes | AE84: =VLOOKUP(O84,'Data Validation'!I:J,2,FALSE) -> C5366020 | AF84: =IF(AJ84<=53,AJ84,AJ84-52) -> 11.030189 | AG84: =IF(H84="Y",(((160/1000000)*AA84)/5.3)*0.1,((160/1000000)*AA84)/5.3) -> 15.09434 | AH84: =SUM($AH84:AH$640) -> 1.509434 | AI84: =AH84/50 -> 0.030188679 | AJ84: =WEEKNUM(TODAY())+AI84 -> 11.030189 | AK84: 46154 | AL84: N | AM84: N | AN84: =AT84-S84 -> -46155 | AS84: 46155
A85: Dominik Metzger | B85: People Growth Management Office UK | C85: Kispert, Daniel<daniel.kispert@sap.com> | D85: On-Mobile Device | E85: On-Mobile Device | F85: P1 | G85: S1 | H85: N | I85: Incremental ONLY | J85: Rural Sourcing Management 2607 | K85: N/A | L85: 46205 | M85: 46233 | N85: GTLC India | O85: Apoorva | P85: Done | Q85: Y | R85: 46210 | S85: 46217 | Z85: Delay from Dev | AA85: 500000 | AB85: Open | AC85: No | AD85: =IF((AND((AS85-TODAY())<=30,(L85-TODAY())<=0,(F93="P1")))=TRUE,"Yes",IF(AND((AS85-TODAY())<=30,(L85-TODAY())<=0,(F93="P2"))=TRUE,"Yes","No")) -> Yes | AE85: I540507 | AF85: 21.479245 | AG85: 1.509434 | AH85: =SUM($AG$2:AG85) -> 262.64151 | AI85: 17.479245 | AJ85: 21.479245 | AK85: 46205 | AL85: N | AM85: N | AN85: =AS85-S85 -> 8 | AS85: 46225
A86: Michael Ameling | B86: =VLOOKUP(A86,'Data Validation'!S:T,2,FALSE) -> Cross Architecture | C86: Liu, Feng<feng.liu01@sap.com> | D86: Outbound OEM | E86: On-Premise | F86: P1 | G86: S2 | H86: Y | I86: Incremental ONLY | J86: SDK 16.1 SP00 PL02 | K86: 45902 | L86: 45988 | M86: 46087 | N86: GTLC Vietnam | O86: Hoan | P86: Done | Q86: Y | R86: 46014 | S86: 46080 | Z86: Resource Constraints | AA86: 500000 | AB86: Open | AC86: No | AD86: =IF((AND((AS86-TODAY())<=30,(L86-TODAY())<=0,(F87="P1")))=TRUE,"Yes",IF(AND((AS86-TODAY())<=30,(L86-TODAY())<=0,(F87="P2"))=TRUE,"Yes","No")) -> Yes | AE86: =VLOOKUP(O86,'Data Validation'!I:J,2,FALSE) -> I758150 | AF86: =IF(AJ86<=53,AJ86,AJ86-52) -> 46.283019 | AG86: =IF(H86="Y",(((160/1000000)*AA86)/5.3)*0.1,((160/1000000)*AA86)/5.3) -> 1.509434 | AH86: =SUM($AG$2:AG86) -> 264.15094 | AI86: =AH86/50 -> 5.2830189 | AJ86: =WEEKNUM(TODAY())+AI86 -> 46.283019 | AK86: 46009 | AL86: N | AM86: N | AN86: =AS86-S86 -> -1 | AO86: 17 | AP86: 0 | AQ86: 299 | AS86: 46079
A87: Michael Ameling | B87: =VLOOKUP(A87,'Data Validation'!S:T,2,FALSE) -> Cross Architecture | C87: Liu, Feng<feng.liu01@sap.com> | D87: Outbound OEM | E87: On-Premise | F87: P1 | G87: S2 | H87: Y | I87: Incremental ONLY | J87: OS 16.1 SP00 PL02 | K87: 45902 | L87: 45988 | M87: 46087 | N87: GTLC Vietnam | O87: Nguyen | P87: Done | Q87: Y | R87: 46014 | S87: 46044 | AA87: 500000 | AB87: Open | AC87: No | AD87: =IF((AND((AS87-TODAY())<=30,(L87-TODAY())<=0,(F88="P1")))=TRUE,"Yes",IF(AND((AS87-TODAY())<=30,(L87-TODAY())<=0,(F88="P2"))=TRUE,"Yes","No")) -> Yes | AE87: =VLOOKUP(O87,'Data Validation'!I:J,2,FALSE) -> I762314 | AF87: =IF(AJ87<=53,AJ87,AJ87-52) -> 46.313208 | AG87: =IF(H87="Y",(((160/1000000)*AA87)/5.3)*0.1,((160/1000000)*AA87)/5.3) -> 1.509434 | AH87: =SUM($AG$2:AG87) -> 265.66038 | AI87: =AH87/50 -> 5.3132075 | AJ87: =WEEKNUM(TODAY())+AI87 -> 46.313208 | AK87: 46009 | AL87: N | AM87: N | AN87: =AS87-S87 -> 35 | AO87: 3 | AP87: 0 | AQ87: 139 | AS87: 46079
A88: Michael Ameling | B88: =VLOOKUP(A88,'Data Validation'!S:T,2,FALSE) -> Cross Architecture | C88: Dong, Zhi-peng <zhi-peng.dong@sap.com> | D88: Outbound OEM | E88: On-Premise | F88: P1 | G88: S2 | H88: Y | I88: Incremental ONLY | J88: ASE 16.1 SP00 PL02 | K88: 45988 | L88: 46003 | M88: 46087 | N88: GTLC Vietnam | O88: Thao | P88: Done | Q88: Y | R88: 46014 | S88: 46080 | Z88: Resource Constraints | AA88: 500000 | AB88: Open | AC88: No | AD88: =IF((AND((AS88-TODAY())<=30,(L88-TODAY())<=0,(F89="P1")))=TRUE,"Yes",IF(AND((AS88-TODAY())<=30,(L88-TODAY())<=0,(F89="P2"))=TRUE,"Yes","No")) -> Yes | AE88: =VLOOKUP(O88,'Data Validation'!I:J,2,FALSE) -> I758015 | AF88: =IF(AJ88<=53,AJ88,AJ88-52) -> 46.373585 | AG88: =IF(H88="Y",(((160/1000000)*AA88)/5.3)*0.1,((160/1000000)*AA88)/5.3) -> 1.509434 | AH88: =SUM($AG$2:AG89) -> 268.67925 | AI88: =AH88/50 -> 5.3735849 | AJ88: =WEEKNUM(TODAY())+AI88 -> 46.373585 | AK88: 46012 | AL88: N | AM88: N | AN88: =AS88-S88 -> -1 | AO88: 12 | AP88: 0 | AQ88: 18 | AS88: 46079
A89: Michael Ameling | B89: =VLOOKUP(A89,'Data Validation'!S:T,2,FALSE) -> Cross Architecture | C89: Zhong, Gary <gary.zhong@sap.com> | D89: Outbound OEM | E89: On-Premise | F89: P1 | G89: S2 | H89: Y | I89: Incremental ONLY | J89: SRS 16.1 SP00 PL02 | K89: N/A | L89: 46003 | M89: 46087 | N89: GTLC Vietnam | O89: Khoi | P89: Done | Q89: Y | R89: 46035 | S89: 46043 | AA89: 500000 | AB89: Open | AC89: No | AD89: =IF((AND((AS89-TODAY())<=30,(L89-TODAY())<=0,(F89="P1")))=TRUE,"Yes",IF(AND((AS89-TODAY())<=30,(L89-TODAY())<=0,(F89="P2"))=TRUE,"Yes","No")) -> Yes | AE89: =VLOOKUP(O89,'Data Validation'!I:J,2,FALSE) -> I758929 | AF89: =IF(AJ89<=53,AJ89,AJ89-52) -> 46.373585 | AG89: =IF(H89="Y",(((160/1000000)*AA89)/5.3)*0.1,((160/1000000)*AA89)/5.3) -> 1.509434 | AH89: =SUM($AG$2:AG89) -> 268.67925 | AI89: =AH89/50 -> 5.3735849 | AJ89: =WEEKNUM(TODAY())+AI89 -> 46.373585 | AK89: 46027 | AL89: N | AM89: N | AN89: =AS89-S89 -> 48 | AO89: 5 | AP89: 3 | AQ89: 4 | AS89: 46091
A90: Uma Rani T M | B90: Strategy & Transformation, Customer Success | C90: BAR, Pascal<pascal.bar@sap.com> | D90: Outbound OEM | E90: On-Premise | F90: P1 | G90: S2 | H90: Y | I90: Incremental ONLY | J90: SAP Convergent Charging 2025_FPS1 | K90: 45943 | L90: 46045 | M90: 46091 | N90: GTLC China | O90: Yi Zhang | P90: Done | Q90: Y | R90: 46079 | S90: 46091 | Z90: Delay from Dev | AA90: 500000 | AB90: Open | AC90: No | AD90: Yes | AE90: =VLOOKUP(O90,'Data Validation'!I:J,2,FALSE) -> I559269 | AF90: 7.5018868 | AG90: 1.509434 | AH90: 175.09434 | AI90: 3.5018868 | AJ90: 7.5018868 | AK90: 46072 | AL90: N | AM90: N | AN90: -6 | AS90: 46091
A91: Michael Ameling | B91: Cross Architecture | C91: Arroyo, Adrian<adrian.arroyo@sap.com> | D91: Source Code | E91: On-Premise | F91: P1 | G91: S2 | H91: Y | I91: Incremental ONLY | J91: Telco and Utilities Accelerator 2026-02-JDK21 | K91: 45972 | L91: 46055 | M91: 46092 | N91: GTLC India | O91: Arun | P91: Done | Q91: Y | R91: 46085 | S91: 46092 | Z91: Delay from Dev | AA91: 500000 | AB91: Open | AC91: No | AD91: Yes | AE91: C5403671 | AF91: 21.932076 | AG91: 1.509434 | AH91: 896.60378 | AI91: 17.932076 | AJ91: 21.932076 | AK91: 46079 | AL91: N | AM91: N | AN91: -20 | AS91: 45940
A92: Irfan Khan | B92: SAP HANA Database & Analytics | C92: Limberg, Angie <angie.limberg@sap.com> | D92: Outbound OEM | E92: On-Premise | F92: P1 | G92: S2 | H92: Y | I92: Incremental ONLY | J92: SAP HANA Cloud Integration,DS 2603 (1.0.11.60) | K92: 45945 | L92: 46066 | M92: 46101 | N92: GTLC China | O92: Yi Zhang | P92: Done | Q92: Y | R92: 46077 | S92: 46100 | AA92: 500000 | AB92: Open | AC92: No | AD92: Yes | AE92: =VLOOKUP(O92,'Data Validation'!I:J,2,FALSE) -> I559269 | AF92: 8.3471698 | AG92: 1.509434 | AH92: 217.35849 | AI92: 4.3471698 | AJ92: 8.3471698 | AK92: 46071 | AL92: N | AM92: N | AN92: 12 | AO92: 16 | AP92: 0 | AQ92: 2800 | AS92: 46100
A93: Michael Ameling | B93: Cross Architecture | C93: Arroyo, Adrian<adrian.arroyo@sap.com> | D93: Source Code | E93: On-Premise | F93: P1 | G93: S2 | H93: Y | I93: Incremental ONLY | J93: TUA SPA 2604-2609 MDG | K93: 46029 | L93: 46140 | M93: 46157 | N93: GTLC India | O93: Arun | P93: Done | Q93: Y | R93: 46154 | S93: 46154 | Z93: Delay from Dev | AA93: 500000 | AB93: Open | AC93: No | AD93: Yes | AE93: C5403671 | AF93: 21.932076 | AG93: 1.509434 | AH93: 896.60378 | AI93: 17.932076 | AJ93: 21.932076 | AK93: 46148 | AL93: N | AM93: N | AN93: -20 | AS93: 46157
A94: Michael Ameling | B94: =VLOOKUP(A94,'Data Validation'!S:T,2,FALSE) -> Cross Architecture | C94: Zhong, Gary <gary.zhong@sap.com> | D94: Outbound OEM | E94: On-Premise | F94: P1 | G94: S2 | H94: Y | I94: Incremental ONLY | J94: SRS 16.0 SP03 PL15 | K94: N/A | L94: 46157 | M94: 46162 | N94: GTLC India | O94: Arun | P94: Done | Q94: Y | R94: 46160 | S94: 46161 | Z94: Delay from Dev | AA94: 500000 | AB94: Open | AC94: No | AD94: =IF((AND((AS94-TODAY())<=30,(L94-TODAY())<=0,(F94="P1")))=TRUE,"Yes",IF(AND((AS94-TODAY())<=30,(L94-TODAY())<=0,(F94="P2"))=TRUE,"Yes","No")) -> Yes | AE94: =VLOOKUP(O94,'Data Validation'!I:J,2,FALSE) -> C5381614 | AF94: =IF(AJ94<=53,AJ94,AJ94-52) -> 18.1 | AG94: =IF(H94="Y",(((160/1000000)*AA94)/5.3)*0.1,((160/1000000)*AA94)/5.3) -> 1.509434 | AH94: =SUM($AG$2:AG521) -> 1455 | AI94: =AH94/50 -> 29.1 | AJ94: =WEEKNUM(TODAY())+AI94 -> 70.1 | AK94: 46154 | AL94: N | AM94: N | AN94: =AS94-S94 -> 1 | AS94: 46162
A95: Michael Ameling | B95: Cross Architecture | C95: Ettaki Manjunath, Adarsh<adarsh.ettaki.manjunath@sap.com> | D95: Source Code | E95: On-Premise | F95: P1 | G95: S2 | H95: Y | I95: Incremental ONLY | J95: HANA Clients QRC02/2026 | K95: N/A | L95: 46112 | M95: 46189 | N95: GTLC India | O95: Apoorva | P95: Done | Q95: Y | R95: 46133 | S95: 46178 | Z95: Delay from dev | AA95: 500000 | AB95: Open | AC95: No | AD95: Yes | AE95: C5367590 | AF95: 21.871698 | AG95: 1.509434 | AH95: 893.58491 | AI95: 17.871698 | AJ95: 21.871698 | AK95: 46112 | AL95: N | AM95: Y | AN95: 0 | AS95: 46146
A96: Michael Ameling | B96: =VLOOKUP(A96,'Data Validation'!S:T,2,FALSE) -> Cross Architecture | C96: Dong, Zhi-peng <zhi-peng.dong@sap.com> | D96: Outbound OEM | E96: On-Premise | F96: P1 | G96: S2 | H96: Y | I96: Incremental ONLY | J96: ASE 16.0 SP04 PL09 | K96: N/A | L96: 46101 | M96: 46190 | N96: GTLC India | O96: Apoorva | P96: Done | Q96: Y | R96: 46119 | S96: 46136 | AA96: 500000 | AB96: Open | AC96: No | AD96: =IF((AND((AS96-TODAY())<=30,(L96-TODAY())<=0,(F98="P1")))=TRUE,"Yes",IF(AND((AS96-TODAY())<=30,(L96-TODAY())<=0,(F98="P2"))=TRUE,"Yes","No")) -> Yes | AE96: =VLOOKUP(O96,'Data Validation'!I:J,2,FALSE) -> C5367590 | AF96: =IF(AJ96<=53,AJ96,AJ96-52) -> 46.645283 | AG96: =IF(H96="Y",(((160/1000000)*AA96)/5.3)*0.1,((160/1000000)*AA96)/5.3) -> 1.509434 | AH96: =SUM($AG$2:AG98) -> 282.26415 | AI96: =AH96/50 -> 5.645283 | AJ96: =WEEKNUM(TODAY())+AI96 -> 46.645283 | AK96: 46111 | AL96: N | AM96: N | AN96: =AS96-S96 -> 47 | AO96: 29 | AP96: 0 | AQ96: 129 | AS96: 46183
A97: Michael Ameling | B97: =VLOOKUP(A97,'Data Validation'!S:T,2,FALSE) -> Cross Architecture | C97: Liu, Feng<feng.liu01@sap.com> | D97: Outbound OEM | E97: On-Premise | F97: P1 | G97: S2 | H97: Y | I97: Incremental ONLY | J97: SDK 16.0 SP04 PL09 | K97: 45988 | L97: 46085 | M97: 46190 | N97: GTLC India | O97: Apoorva | P97: Done | Q97: Y | R97: 46113 | S97: 46139 | Z97: Delay from Dev | AA97: 500000 | AB97: Open | AC97: No | AD97: =IF((AND((AS97-TODAY())<=30,(L97-TODAY())<=0,(F98="P1")))=TRUE,"Yes",IF(AND((AS97-TODAY())<=30,(L97-TODAY())<=0,(F98="P2"))=TRUE,"Yes","No")) -> Yes | AE97: =VLOOKUP(O97,'Data Validation'!I:J,2,FALSE) -> C5367590 | AF97: =IF(AJ97<=53,AJ97,AJ97-52) -> 46.615094 | AG97: =IF(H97="Y",(((160/1000000)*AA97)/5.3)*0.1,((160/1000000)*AA97)/5.3) -> 1.509434 | AH97: =SUM($AG$2:AG97) -> 280.75472 | AI97: =AH97/50 -> 5.6150943 | AJ97: =WEEKNUM(TODAY())+AI97 -> 46.615094 | AK97: 46113 | AL97: N | AM97: N | AN97: =AS97-S97 -> -59 | AO97: 20 | AP97: 39 | AQ97: 300 | AS97: 46080
A98: Michael Ameling | B98: Cross Architecture | C98: Liu, Feng <feng.liu01@sap.com> | D98: Outbound OEM | E98: On-Premise | F98: P1 | G98: S2 | H98: Y | I98: Incremental ONLY | J98: OS 16.0 SP04 PL09 | K98: 45988 | L98: 46085 | M98: 46190 | N98: GTLC Vietnam | O98: Khoi | P98: Done | Q98: Y | R98: 46120 | S98: 46155 | AA98: 500000 | AB98: Open | AC98: No | AD98: Yes | AE98: C5380108 | AF98: 8.1358491 | AG98: 1.509434 | AH98: 206.79245 | AI98: 4.1358491 | AJ98: 8.1358491 | AK98: 46113 | AL98: N | AM98: N | AN98: 34 | AS98: 46183
A99: Michael Ameling | B99: =VLOOKUP(A99,'Data Validation'!S:T,2,FALSE) -> Cross Architecture | C99: Zhong, Gary <gary.zhong@sap.com> | D99: Outbound OEM | E99: On-Premise | F99: P1 | G99: S2 | H99: Y | I99: Incremental ONLY | J99: SRS 16.0 SP04 PL09 | K99: N/A | L99: 46099 | M99: 46190 | N99: GTLC Vietnam | O99: Thao | P99: Done | Q99: Y | R99: 46119 | S99: 46132 | AA99: 500000 | AB99: Open | AC99: No | AD99: =IF((AND((AS99-TODAY())<=30,(L99-TODAY())<=0,(F99="P1")))=TRUE,"Yes",IF(AND((AS99-TODAY())<=30,(L99-TODAY())<=0,(F99="P2"))=TRUE,"Yes","No")) -> Yes | AE99: =VLOOKUP(O99,'Data Validation'!I:J,2,FALSE) -> I758015 | AF99: =IF(AJ99<=53,AJ99,AJ99-52) -> 46.675472 | AG99: =IF(H99="Y",(((160/1000000)*AA99)/5.3)*0.1,((160/1000000)*AA99)/5.3) -> 1.509434 | AH99: =SUM($AG$2:AG99) -> 283.77358 | AI99: =AH99/50 -> 5.6754717 | AJ99: =WEEKNUM(TODAY())+AI99 -> 46.675472 | AK99: 46112 | AL99: N | AM99: N | AN99: =AS99-S99 -> 51 | AO99: 3 | AP99: 4 | AQ99: 5 | AS99: 46183
A100: Uma Rani T M | B100: Strategy & Transformation, Customer Success | C100: BAR, Pascal<pascal.bar@sap.com> | D100: Outbound OEM | E100: On-Premise | F100: P1 | G100: S2 | H100: Y | I100: Incremental ONLY | J100: SAP Convergent Charging 2023_SPS4 | K100: 46142 | L100: 46164 | M100: 46192 | N100: GTLC India | O100: Arun | P100: Done | Q100: Y | R100: 46174 | S100: 46189 | Z100: Delay from Dev | AA100: 500000 | AB100: Open | AC100: No | AD100: Yes | AE100: =VLOOKUP(O100,'Data Validation'!I:J,2,FALSE) -> C5381614 | AF100: 7.5018868 | AG100: 1.509434 | AH100: 175.09434 | AI100: 3.5018868 | AJ100: 7.5018868 | AK100: 46167 | AL100: N | AM100: N | AN100: -6 | AS100: 46191
...

Sheet Wiki
A1: SAP User Enabl Mgmt SE | B1: Source Code | C1: On-Premise | D1: P1 | E1: N | F1: 305012457_CAE_Boehringer_Ingelheim | G1: 45998 | H1: C5385241
A2: SAP User Enabl Mgmt SE | B2: On-Premise | C2: On-Premise | D2: P1 | E2: N | F2: QRO Online Enhancements Release3e | G2: 46045 | H2: C5366020
A3: SAP User Enabl Mgmt SE | B3: On-Premise | C3: On-Premise | D3: P1 | E3: N | F3: QRO Online Enhancements Release3e-CF source code | G3: 46087 | H3: C5366020
A4: SAP User Enabl Mgmt SE | B4: On-Premise | C4: On-Premise | D4: P1 | E4: N | F4: 306181513_Sprint 0 T-Systems | G4: 46155 | H4: C5366020
A5: People Growth Management Office UK | B5: On-Mobile Device | C5: On-Mobile Device | D5: P1 | E5: N | F5: Rural Sourcing Management 2607 | G5: 46233 | H5: I540507
A6: Cross Architecture | B6: Outbound OEM | C6: On-Premise | D6: P1 | E6: Y | F6: SDK 16.1 SP00 PL02 | G6: 46087 | H6: I758150
A7: Cross Architecture | B7: Outbound OEM | C7: On-Premise | D7: P1 | E7: Y | F7: OS 16.1 SP00 PL02 | G7: 46087 | H7: I762314
A8: Cross Architecture | B8: Outbound OEM | C8: On-Premise | D8: P1 | E8: Y | F8: ASE 16.1 SP00 PL02 | G8: 46087 | H8: I758015
A9: Cross Architecture | B9: Outbound OEM | C9: On-Premise | D9: P1 | E9: Y | F9: SRS 16.1 SP00 PL02 | G9: 46087 | H9: I758929
A10: Strategy & Transformation, Customer Success | B10: Outbound OEM | C10: On-Premise | D10: P1 | E10: Y | F10: SAP Convergent Charging 2025_FPS1 | G10: 46091 | H10: I559269
A11: Cross Architecture | B11: Source Code | C11: On-Premise | D11: P1 | E11: Y | F11: Telco and Utilities Accelerator 2026-02-JDK21 | G11: 46092 | H11: C5403671
A12: SAP HANA Database & Analytics | B12: Outbound OEM | C12: On-Premise | D12: P1 | E12: Y | F12: SAP HANA Cloud Integration,DS 2603 (1.0.11.60) | G12: 46101 | H12: I559269
... A146: SAP User Enabl Mgmt SE | B146: On-Premise | C146: On-Premise | D146: P2 | E146: Y | F146: 305974898_CAE RUN_NEO to CF Migration_Iren | G146: 46157 | H146: C5385241
B147: On-Premise | C147: On-Premise | D147: P2 | E147: Y | F147: FinProdSubledger 3.5 | G147: 46164 | H147: C5385241
A148: ISBN CloudOps Cross COPS | B148: On-Mobile Device | C148: On-Mobile Device | D148: P2 | E148: Y | F148: B1 Service App for iOS 1.0 PL20 | G148: 46164 | H148: C5385241
A149: ISBN CloudOps Cross COPS | B149: On-Mobile Device | C149: On-Mobile Device | D149: P2 | E149: Y | F149: B1 Service App for Android 1.0 PL14 | G149: 46164 | H149: C5385241
A150: Cross Architecture | B150: On-Premise | C150: On-Premise | D150: P2 | E150: Y | F150: FRUN 5.0 FP03 | G150: 46167 | H150: C5367590
A151: Enterprise Cloud Services | B151: On-Premise | C151: On-Premise | D151: P2 | E151: Y | F151: LaMaRT 2026.09 | G151: 46167 | H151: I757367
A152: ISBN CloudOps Cross COPS | B152: On-Mobile Device | C152: On-Mobile Device | D152: P2 | E152: Y | F152: B1 Mobile App for iOS 1.11 PL24 | G152: 46168 | H152: C5385241
A153: ISBN CloudOps Cross COPS | B153: On-Mobile Device | C153: On-Mobile Device | D153: P2 | E153: Y | F153: B1 Mobile App for Android 1.2 PL18 | G153: 46168 | H153: C5385241
A154: SAP S/4 HANA | B154: On-Mobile Device | C154: On-Mobile Device | D154: P2 | E154: Y | F154: SAP Sports One 1.0 - on Mobile - 2605 | G154: 46169 | H154: Global
A155: Cross Architecture | B155: On-Premise | C155: On-Premise | D155: P2 | E155: Y | F155: SAP Business Client 8.10 (Beta2) | G155: 46169 | H155: C5385241
A156: SAP S/4 HANA | B156: On-Mobile Device | C156: On-Mobile Device | D156: P2 | E156: Y | F156: SAP Sports One 1.0 - on Mobile - 2605 | G156: 46169 | H156: Global
A157: Cross Architecture | B157: On-Mobile Device | C157: On-Mobile Device | D157: P2 | E157: Y | F157: Complete Android H1 1.1(June 2026) | G157: 46170 | H157: C5381614
A158: Cross Architecture | B158: On-Mobile Device | C158: On-Mobile Device | D158: P2 | E158: Y | F158: Complete iOS H1 1.1(June 2026) | G158: 46170 | H158: C5381614
A159: Cross Architecture | B159: On-Mobile Device | C159: On-Mobile Device | D159: P2 | E159: Y | F159: SAP Concur Mobile iOS H1 2026 - May | G159: 46170 | H159: C5403671
... A307: ISBN CloudOps Cross COPS | B307: On-Demand (SaaS) | C307: On-Demand (SaaS) | D307: P3 | E307: Y | F307: ABAP in SAP BTP 2605 | G307: 46141 | H307: I501689

Sheet 2023_P3 IP Scan Removal
A1: L1 Manager | B1: L1 Development Unit | C1: Dev Contact | D1: Program Category | E1: Delivery Mode | F1: Priority | G1: Severity | H1: Previously Scanned | I1: Scan Category | J1: Program | K1: Start of Development | L1: End of Development | M1: RTC | N1: Location | O1: FOSS Analyst | P1: FOSS Scan State | Q1: Black Duck Scan | R1: FOSS Scan Assigned | S1: FOSS Scan Closed | T1: Commercial Scan Status | U1: Comm Analyst | V1: CTP Scan Ticket JIRA link | W1: Web Service Scan Status | X1: Web Service Analyst | Y1: WS Scan Ticket JIRA link | Z1: Comments | AA1: SLOC Count | AB1: Tracking System Ticket Status | AC1: RTC Passed | AD1: Recommended to Request Exemption | AE1: Owner # | AF1: Estimated Calendar Week (CW) for the scan to be "In Progress" | AG1: Estimated # of days to complete the first round of scan | AH1: Cumulative Days | AI1: CW to be added to the current CW | AJ1: Estimated CW for scan to be in progress | AK1: Scan Submission Date | AL1: Continuous scan
A2: Irfan Khan | B2: SAP HANA Database & Analytics | C2: JANOT, Nicolas <nicolas.janot@sap.com>; SIRE, Philippe <philippe.sire@sap.com> | D2: Docker Container | E2: On-Demand (SaaS) | F2: P3 | G2: S1 | H2: N | I2: OneTime Scan | J2: [Docker] SAC OD 2021.12 | K2: 44198 | L2: 44320 | M2: 44347 | N2: GLOBAL | O2: GLOBAL | P2: Backlog | AA2: 500000 | AB2: Open | AC2: No | AD2: No | AE2: Global | AF2: 2.720771 | AG2: 15.09434 | AH2: 86.038548 | AI2: 1.720771 | AJ2: 2.720771
A3: Michael Paul Weingartner | B3: SAP BTP Core | C3: Krastev, Anatoli <anatoli.krastev@sap.com>; Georgiev, Georgi <g.georgiev@sap.com> | D3: Docker Container | E3: On-Demand (SaaS) | F3: P3 | G3: S2 | H3: Y | I3: OneTime Scan | J3: [Docker] FS on K8s Delivery 2106a | K3: 44354 | L3: 44365 | M3: 44379 | N3: GLOBAL | O3: GLOBAL | P3: Backlog | V3: https://jira.tools.sap/browse/CTPSAPPRODUCT-4604 | Y3: https://jira.tools.sap/browse/WEBSERVSAPPRODUCT-3556 | Z3: Awaiting dev information for future releases. | AA3: 500000 | AB3: Open | AC3: No | AD3: No | AE3: Global | AF3: 2.7811483 | AG3: 1.509434 | AH3: 89.057416 | AI3: 1.7811483 | AJ3: 2.7811483 | AK3: 44627 | AL3: Y
A4: Michael Paul Weingartner | B4: SAP BTP Core | C4: Jain, Swati <swati.jain01@sap.com>; DL_5D44036925A7520279676E48@global.corp.sap <DL_5D44036925A7520279676E48@global.corp.sap> | D4: Docker Container | E4: On-Demand (SaaS) | F4: P3 | G4: S2 | H4: Y | I4: OneTime Scan | J4: [Docker] FS on K8s Delivery 2106b | L4: 44379 | M4: 44392 | N4: GLOBAL | O4: GLOBAL | P4: Backlog | V4: https://jira.tools.sap/browse/CTPSAPPRODUCT-4621 | W4: In Progress | X4: Yi Zhang | Y4: https://jira.tools.sap/browse/WEBSERVSAPPRODUCT-3572 | Z4: Export scan assigned to Chaitanya | AA4: 500000 | AB4: Open | AC4: No | AD4: No | AE4: Global | AF4: 2.7811483 | AG4: 1.509434 | AH4: 89.057416 | AI4: 1.7811483 | AJ4: 2.7811483 | AK4: 44720
A5: Michael Paul Weingartner | B5: SAP BTP Core | C5: Jain, Swati <swati.jain01@sap.com>; DL_5D44036925A7520279676E48@global.corp.sap | D5: Docker Container | E5: On-Demand (SaaS) | F5: P3 | G5: S2 | H5: Y | I5: OneTime Scan | J5: [Docker] FS on K8s Delivery 2108b | L5: 44437 | M5: 44449 | N5: GLOBAL | O5: GLOBAL | P5: Backlog | V5: https://jira.tools.sap/browse/CTPSAPPRODUCT-4605 | W5: In Progress | X5: Komal | Y5: https://jira.tools.sap/browse/WEBSERVSAPPRODUCT-3557 | Z5: Export scan assigned to Chaitanya | AA5: 500002 | AB5: Open | AC5: No | AD5: No | AE5: Global | AF5: 2.8113371 | AG5: 1.50944 | AH5: 90.566856 | AI5: 1.8113371 | AJ5: 2.8113371 | AK5: 44641
A6: Michael Paul Weingartner | B6: SAP BTP Core | C6: Jain, Swati <swati.jain01@sap.com>; DL_5D44036925A7520279676E48@global.corp.sap | D6: Docker Container | E6: On-Demand (SaaS) | F6: P3 | G6: S2 | H6: Y | I6: OneTime Scan | J6: [Docker] FS on K8s Delivery 2109b | L6: 44463 | M6: 44476 | N6: GLOBAL | O6: GLOBAL | P6: Backlog | V6: https://jira.tools.sap/browse/CTPSAPPRODUCT-4628 | W6: In Progress | X6: Yi Zhang | Y6: https://jira.tools.sap/browse/WEBSERVSAPPRODUCT-3580 | Z6: Export scan assigned to Sandhya | AA6: 500002 | AB6: Open | AC6: No | AD6: No | AE6: Global | AF6: 2.8415259 | AG6: 1.50944 | AH6: 92.076296 | AI6: 1.8415259 | AJ6: 2.8415259 | AK6: 44735

Sheet 2022_P3 IP Scan Removal
A1: L1 Manager | B1: L1 Development Unit | C1: Dev Contact | D1: Program Category | E1: Delivery Mode | F1: Priority | G1: Severity | H1: Previously Scanned | I1: Scan Category | J1: Program | K1: Start of Development | L1: End of Development | M1: RDM | N1: RTC | O1: Location | P1: FOSS Analyst | Q1: FOSS Scan State | R1: Black Duck Scan | S1: FOSS Scan Assigned | T1: FOSS Scan Closed | U1: Commercial Scan Status | V1: Comm Analyst | W1: CTP Scan Ticket JIRA link | X1: Web Service Scan Status | Y1: Web Service Analyst | Z1: WS Scan Ticket JIRA link | AA1: Comments | AB1: SLOC Count | AC1: Tracking System Ticket Status | AD1: RTC Passed | AE1: Recommended to Request Exemption | AF1: Owner # | AG1: Estimated Calendar Week (CW) for the scan to be "In Progress" | AH1: Estimated # of days to complete the first round of scan | AI1: Cumulative Days | AJ1: CW to be added to the current CW | AK1: Estimated CW for scan to be in progress | AL1: Scan Submission Date | AM1: Continuous scan
A2: Michael Paul Weingartner | B2: SAP BTP Core | C2: Mager-Bruhn, Nicole <nicole.mager-bruhn@sap.com> | D2: On-Demand (SaaS) | E2: On-Demand (SaaS) | F2: P3 | G2: S1 | H2: N | I2: Incremental ONLY | J2: SAP Master Data Governance, cloud edition 2202 | K2: 44473 | L2: 44519 | N2: 44611 | O2: GLOBAL | P2: GLOBAL | Q2: Backlog | W2: https://jira.tools.sap/browse/CTPSAPPRODUCT-4600 | X2: 500000 | Y2: Open | Z2: https://jira.tools.sap/browse/WEBSERVSAPPRODUCT-3552 | AA2: Export Scan required - Siva | AB2: 500000 | AC2: Open | AD2: No | AE2: No | AF2: GLOBAL | AG2: 7.7698147 | AH2: 15.09434 | AI2: 238.49074 | AJ2: 4.7698147 | AK2: 7.7698147 | AL2: 44615
A3: Harald Kuck | B3: TI ABAP Platform Mgmt (SE) | C3: Hong, Gyeongsu <gyeongsu.hong@sap.com> | D3: On-Demand (SaaS) | E3: On-Demand (SaaS) | F3: P3 | G3: S2 | H3: Y | I3: Incremental ONLY | J3: ABAP in SAP BTP 2211 | K3: 44735 | L3: 44781 | M3: 44854 | N3: 44862 | O3: GTLC Germany | P3: Ravi | Q3: Done | S3: 44816 | T3: 44818 | AB3: 500001 | AC3: Open | AD3: No | AE3: No | AF3: D072009 | AG3: 27.241529 | AH3: 1.509437 | AI3: 1212.0764 | AJ3: 24.241529 | AK3: 27.241529 | AL3: 44813

Sheet 2024 Done
A1: L1 Manager | B1: L1 Development Unit | C1: Dev Contact | D1: Program Category | E1: Delivery Mode | F1: Priority | G1: Severity | H1: Previously Scanned | I1: Scan Category | J1: Program | K1: Start of Development | L1: End of Development | M1: RDM | N1: RTC | O1: Location | P1: FOSS Analyst | Q1: FOSS Scan State | R1: Black Duck Scan | S1: FOSS Scan Assigned | T1: FOSS Scan Closed | U1: Commercial Scan Status | V1: Comm Analyst | W1: CTP Scan Ticket JIRA link | X1: Web Service Scan Status | Y1: Web Service Analyst | Z1: WS Scan Ticket JIRA link | AA1: Comments | AB1: SLOC Count | AC1: Tracking System Ticket Status | AD1: RTC Passed | AE1: Recommended to Request Exemption | AF1: Owner # | AG1: Estimated Calendar Week (CW) for the scan to be "In Progress" | AH1: Estimated # of days to complete the first round of scan | AI1: Cumulative Days | AJ1: CW to be added to the current CW | AK1: Estimated CW for scan to be in progress | AL1: Scan Submission Date | AM1: Continuous scan | AN1: Crown Jewel | AO1: Closed within SLA
A2: Claudio Muruzabal | B2: EMEA South, Customer Success | C2: Sikri, Sanjam <sanjam.sikri@sap.com> | D2: Source Code | E2: On-Premise | F2: P1 | G2: S1 | H2: N | I2: Incremental ONLY | J2: 304749634_CSD_TOYOTA_TSUSHO | L2: 45233 | M2: 45609 | N2: 45280 | O2: GTLC Germany | P2: Ravi | Q2: Done | R2: Y | S2: 45272 | T2: 45279 | AB2: 500002 | AC2: Open | AD2: No | AE2: Yes | AF2: D072009 | AG2: 6.9622654 | AH2: 15.0944 | AI2: 98.113268 | AJ2: 1.9622654 | AK2: 6.9622654 | AL2: 45272 | AN2: N | AO2: 1
A3: Irfan Khan | B3: SAP HANA Database & Analytics | C3: Chennappa Krishnamurthy, Lavanya <lavanya.chennappa.krishnamurthy@sap.com> | D3: Source Code | E3: On-Premise | F3: P1 | G3: S1 | H3: Y | I3: Incremental ONLY | J3: SAP Data Intelligence 3.3 | L3: 45264 | M3: 45615 | N3: 45284 | O3: GTLC Germany | P3: Giang | Q3: Done | R3: Y | S3: 45364 | T3: 45479 | U3: In Progress | V3: Chaitanya | W3: https://jira.tools.sap/browse/CTPSAPPRODUCT-4714 | X3: In Progress | Y3: Chaitanya | Z3: https://jira.tools.sap/browse/WEBSERVSAPPRODUCT-3666 | AA3: Export Scan required - Chaitanya | Reassigned from Chaitanya | AB3: 500000 | AC3: Open | AD3: No | AE3: Yes | AF3: I540507 | AG3: 6.992454 | AH3: 1.509434 | AI3: 99.622702 | AJ3: 1.992454 | AK3: 6.992454 | AL3: 45268 | AN3: N | AO3: -195
A4: Ritu Bhargava | B4: CX Management America | C4: Schmidt, Marcus <marcus.schmidt@sap.com> | D4: Source Code | E4: On-Premise | F4: P1 | G4: S1 | H4: Y | I4: OneTime Scan | J4: 303250779_UKHD_Data5.0 | L4: 45212 | M4: 45602 | N4: 45306 | O4: GTLC Germany | P4: Rajat | Q4: Done | R4: Y | S4: 45274 | T4: 45281 | AB4: 500000 | AC4: Open | AD4: No | AE4: Yes | AF4: I501689 | AG4: 7.0226427 | AH4: 1.509434 | AI4: 101.13214 | AJ4: 2.0226427 | AK4: 7.0226427 | AL4: 45274 | AN4: N | AO4: 25
A5: Ritu Bhargava | B5: CX Management America | C5: Sundaram, Lakshmi <lakshmi.sundaram@sap.com> | D5: Source Code | E5: On-Premise | F5: P1 | G5: S1 | H5: N | I5: OneTime Scan | J5: 304255988_Nestle_Comm_Cld_17 | L5: 45252 | M5: 45604 | N5: 45322 | O5: GTLC China | P5: Yi Zhang | Q5: Done | R5: Y | S5: 45264 | T5: 45296 | W5: [CTPSAPPRODUCT-4710] 304255988_Nestle_Comm_Cld_17 - SAPJIRA (tools.sap) | Y5: [WEBSERVSAPPRODUCT-3662] 304255988_Nestle_Comm_Cld_17 - SAPJIRA (tools.sap) | AA5: Export scan is assigned to Prashant | AB5: 500001 | AC5: Open | AD5: No | AE5: Yes | AF5: I559269 | AG5: 7.3245301 | AH5: 15.09437 | AI5: 116.22651 | AJ5: 2.3245301 | AK5: 7.3245301 | AL5: 45248 | AN5: N | AO5: 26
A6: Philipp Herzig | B6: Product Engineering Intelligent Enterprise and Cross Architecture | C6: Degac, Jennifer <jennifer.degac@sap.com> | D6: Source Code | E6: On-Premise | F6: P1 | G6: S1 | H6: N | I6: OneTime Scan | J6: 305067921_CSD_Peras_Onboarding_Process_Phase1 | L6: 45345 | M6: 45623 | N6: 45350 | O6: GTLC India | P6: Viswa | Q6: Done | R6: Y | S6: 45350 | T6: 45358 | AA6: CSD | BD Setup | AB6: 500000 | AC6: Open | AD6: No | AE6: Yes | AF6: C5366020 | AG6: 7.6264169 | AH6: 15.09434 | AI6: 131.32085 | AJ6: 2.6264169 | AK6: 7.6264169 | AL6: 45345 | AN6: N | AO6: -8
A7: Claudio Muruzabal | B7: EMEA South, Customer Success | C7: Kumar, Vivek <vivek.kumar11@sap.com>; Kumar, Rahul <rahul03.kumar@sap.com> | D7: Source Code | E7: On-Premise | F7: P1 | G7: S1 | H7: N | I7: Incremental ONLY | J7: 304542393_CSD_DTInboundLogBTPDev | L7: 45331 | M7: 45628 | N7: 45355 | O7: GTLC Germany | P7: Shweta | Q7: Done | R7: Y | S7: 45335 | T7: 45344 | W7: [CTPSAPPRODUCT-4724] 304542393_CSD_DTInboundLogBTPDev - SAPJIRA (tools.sap) | Z7: [WEBSERVSAPPRODUCT-3675] 304542393_CSD_DTInboundLogBTPDev - SAPJIRA (tools.sap) | AB7: 500000 | AC7: Open | AD7: No | AE7: Yes | AF7: D059874 | AG7: 7.9283037 | AH7: 15.09434 | AI7: 146.41518 | AJ7: 2.9283037 | AK7: 7.9283037 | AL7: 45323 | AN7: N | AO7: 11
A8: Claudio Muruzabal | B8: EMEA South, Customer Success | C8: Kumar, Vivek <vivek.kumar11@sap.com> | D8: Source Code | E8: On-Demand (SaaS) | F8: P1 | G8: S1 | H8: N | I8: OneTime Scan | J8: 304639959_CSD_FUJITSU_ORG_CHANGE_V2_FUJITSU | L8: 45345 | M8: 45622 | N8: 45359 | O8: GTLC India | P8: Apoorva | Q8: Done | R8: Y | S8: 45356 | T8: 45358 | AA8: Export Scan required - Chaitanya | Was assigend to Chaitnya on 23/2/24 but no update and OOO. Hence, reassigned | CSD | AB8: 500000 | AC8: Open | AD8: No | AE8: Yes | AF8: C5367590 | AG8: 8.2301905 | AH8: 15.09434 | AI8: 161.50952 | AJ8: 3.2301905 | AK8: 8.2301905 | AL8: 45345 | AN8: N | AO8: 1
A9: Claudio Muruzabal | B9: EMEA South, Customer Success | C9: Sikri, Sanjam <sanjam.sikri@sap.com>; Velumani, Srinivasan <srinivasan.velumani@sap.com> | D9: Source Code | E9: On-Premise | F9: P1 | G9: S1 | H9: N | I9: Incremental ONLY | J9: 304675208_CSD_ASDA_MDK | L9: 45331 | M9: 45622 | N9: 45370 | O9: GTLC China | P9: Yi Zhang | Q9: Done | R9: Y | S9: 45356 | T9: 45359 | W9: [CTPSAPPRODUCT-4725] 304675208_CSD_ASDA_MDK - SAPJIRA (tools.sap) | Z9: [WEBSERVSAPPRODUCT-3676] 304675208_CSD_ASDA_MDK - SAPJIRA (tools.sap) | AB9: 500000 | AC9: Open | AD9: No | AE9: Yes | AF9: I559269 | AG9: 8.5320773 | AH9: 15.09434 | AI9: 176.60386 | AJ9: 3.5320773 | AK9: 8.5320773 | AL9: 45313 | AN9: N | AO9: 11
A10: Ritu Bhargava | B10: CX Management America | C10: Ranadive, Saurabh <saurabh.ranadive@sap.com>; Alvarado Jimenez, Gilberto <gilberto.alvarado.jimenez@sap.com> | D10: Source Code | E10: On-Premise | F10: P1 | G10: S1 | H10: N | I10: Incremental ONLY | J10: MCS (Modern Commerce Solution) Pilot 2403 | K10: 45323 | L10: 45366 | M10: 45636 | N10: 45384 | O10: GTLC Germany | P10: Wilko | Q10: Done | R10: Y | S10: 45380 | T10: 45387 | AA10: Consultant assignment | AB10: 500000 | AC10: Open | AD10: No | AE10: Yes | AF10: I541859 | AG10: 8.8339641 | AH10: 15.09434 | AI10: 191.6982 | AJ10: 3.8339641 | AK10: 8.8339641 | AL10: 45378 | AM10: Y | AN10: Y | AO10: -3
A11: Ritu Bhargava | B11: CX Management America | C11: Behera, Sasmita <sasmita.behera@sap.com> | D11: Source Code | E11: On-Premise | F11: P1 | G11: S1 | H11: N | I11: OneTime Scan | J11: 303903251_CSR_POSitive | L11: 45359 | M11: 45651 | N11: 45392 | O11: GTLC Germany | P11: Wilko | Q11: Done | R11: Y | S11: 45364 | T11: 45379 | AA11: Awaiting Blackduck details | AB11: 500000 | AC11: Open | AD11: No | AE11: Yes | AF11: I541859 | AG11: 9.1358509 | AH11: 15.09434 | AI11: 206.79254 | AJ11: 4.1358509 | AK11: 9.1358509 | AL11: 45364 | AN11: N | AO11: 13
A12: Eva Zauke | B12: SAP Enterprise Adoption | C12: MAKAM R, Sudhir <sudhir.makam.r@sap.com> | D12: Source Code | E12: On-Demand (SaaS) | F12: P1 | G12: S1 | H12: N | I12: OneTime Scan | J12: SFSF Visa and Permits Management | K12: 45292 | L12: 45383 | M12: 44952 | N12: 45412 | O12: GTLC Germany | P12: Wilko | Q12: Done | R12: Y | S12: 45387 | T12: 45399 | AA12: Crypto scan - Assigned to Chaitanya | Consultant assignment | AB12: 500000 | AC12: Open | AD12: No | AE12: Yes | AF12: I541859 | AG12: 9.4377377 | AH12: 15.09434 | AI12: 221.88688 | AJ12: 4.4377377 | AK12: 9.4377377 | AL12: 45386 | AN12: Y | AO12: 13
A13: Claudio Muruzabal | B13: EMEA South, Customer Success | C13: Sikri, Sanjam <sanjam.sikri@sap.com>; Velumani, Srinivasan <srinivasan.velumani@sap.com> | D13: Source Code | E13: On-Premise | F13: P1 | G13: S1 | H13: N | I13: Incremental ONLY | J13: 304675208_CSD_ASDA_MDK - Drop 2 | L13: 45394 | M13: 45412 | N13: 45415 | O13: GTLC Germany | P13: Wilko | Q13: Done | R13: Y | S13: 45401 | T13: 45414 | AB13: 500000 | AC13: Open | AD13: No | AE13: Yes | AF13: I541859 | AG13: 9.7396245 | AH13: 15.09434 | AI13: 236.98122 | AJ13: 4.7396245 | AK13: 9.7396245 | AL13: 45399 | AN13: N | AO13: 1
A14: Philipp Herzig | B14: Product Engineering Intelligent Enterprise and Cross Architecture | C14: Mueller, Christian Mathias <christ.mueller@sap.com> | D14: Source Code | E14: On-Premise | F14: P1 | G14: S1 | H14: Y | I14: Incremental ONLY | J14: AI libraries and SDKs MDG 2405b | L14: 45435 | M14: 45572 | N14: 45442 | O14: GTLC China | P14: Yi Zhang | Q14: Done | R14: Y | S14: 45387 | T14: 45454 | AB14: 500000 | AC14: Open | AD14: No | AE14: Yes | AF14: I559269 | AG14: 9.7698131 | AH14: 1.509434 | AI14: 238.49066 | AJ14: 4.7698131 | AK14: 9.7698131 | AL14: 45369 | AM14: Y | AN14: N | AO14: -12
A15: Sindhu Gangadharan | B15: SAP User Enabl Mgmt SE | C15: Keenan, Leighvi <leighvi.keenan@sap.com> | D15: On-Demand (SaaS) | E15: On-Demand (SaaS) | F15: P1 | G15: S1 | H15: N | I15: Incremental ONLY | J15: 302845734_Velux_C4C | L15: 45485 | M15: 45314 | N15: 45492 | O15: GTLC Germany | P15: Giang | Q15: Done | R15: Y | S15: 45495 | T15: 45495 | AB15: 500000 | AC15: Open | AD15: No | AE15: Yes | AF15: I540507 | AG15: 10.0717 | AH15: 15.09434 | AI15: 253.585 | AJ15: 5.0716999 | AK15: 10.0717 | AL15: 45485 | AM15: Y | AN15: N | AO15: -3
A16: Jan Gilg | B16: SAP S/4 HANA | C16: Tselahuz, Dzmitry (external - Project) <dzmitry.tselahuz@sap.com> | D16: Source Code | E16: On-Premise | F16: P1 | G16: S1 | H16: N | I16: Incremental ONLY | J16: S/4HANA Payment Engine 1.0 (SP05) | K16: 45379 | L16: 45541 | M16: 45316 | N16: 45562 | O16: GTLC China | P16: Liye | Q16: Done | R16: Y | S16: 45539 | T16: 45548 | V16: Yi Zhang | AB16: 500000 | AC16: Open | AD16: No | AE16: Yes | AF16: I853975 | AG16: 11.007549 | AH16: 15.09434 | AI16: 300.37745 | AJ16: 6.007549 | AK16: 11.007549 | AL16: 45484 | AM16: Y | AN16: N | AO16: 14
A17: Ritu Bhargava | B17: CX Management America | C17: Chandra, Sahil <sahil.chandra@sap.com> | D17: Source Code | E17: On-Premise | F17: P1 | G17: S1 | H17: Y | I17: Incremental ONLY | J17: 304381480_Cargill_Livestock_Procurement_SP03 | L17: 45331 | M17: 45337 | N17: 45596 | O17: GTLC China | P17: Yi Zhang | Q17: Done | R17: Y | S17: 45492 | T17: 45495 | AB17: 500000 | AC17: Open | AD17: No | AE17: Yes | AF17: I559269 | AG17: 10.403775 | AH17: 1.509434 | AI17: 270.18877 | AJ17: 5.4037754 | AK17: 10.403775 | AL17: 45484 | AN17: N | AO17: 101
A18: Michael Ameling | B18: Cross Architecture | C18: Hellenschmidt, Michael <michael.hellenschmidt@sap.com> | D18: On-Premise | E18: On-Premise | F18: P1 | G18: S1 | H18: N | I18: Incremental ONLY | J18: SAP CP SDK for service development InA Adpt Node | K18: 45292 | L18: 45565 | M18: 45337 | N18: 45598 | O18: GTLC India | P18: Viswa | Q18: Done | R18: Y | S18: 45593 | T18: 45597 | AB18: 500000 | AC18: Open | AD18: No | AE18: Yes | AF18: C5366020 | AG18: 11.037738 | AH18: 15.09434 | AI18: 301.88688 | AJ18: 6.0377377 | AK18: 11.037738 | AL18: 45589 | AN18: N | AO18: 1
A19: Irfan Khan | B19: SAP HANA Database & Analytics | C19: Zhong, Gary <gary.zhong@sap.com> | D19: Outbound OEM | E19: On-Premise | F19: P1 | G19: S2 | H19: Y | I19: Incremental ONLY | J19: SRS SP04 PL05 | L19: 45215 | N19: 45307 | O19: GTLC China | P19: Yi Zhang | Q19: Done | R19: Y | S19: 45299 | T19: 45299 | W19: [CTPSAPPRODUCT-4706] SRS SP04 PL05 - SAPJIRA (tools.sap) | Z19: [WEBSERVSAPPRODUCT-3658] SRS SP04 PL05 - SAPJIRA (tools.sap) | AB19: 500000 | AC19: Open | AD19: No | AE19: Yes | AF19: I559269 | AG19: 10.735851 | AH19: 1.509434 | AI19: 286.79254 | AJ19: 5.7358509 | AK19: 10.735851 | AL19: 45238 | AN19: N | AO19: 8
A20: Irfan Khan | B20: SAP HANA Database & Analytics | C20: Noack, Jason <jason.noack@sap.com> | D20: Outbound OEM | E20: On-Premise | F20: P1 | G20: S2 | H20: Y | I20: Incremental ONLY | J20: SQL Anywhere 17.0 SP01 Q4/2023 | L20: 45265 | M20: 45357 | N20: 45317 | O20: GTLC Germany | P20: Giang | Q20: Done | R20: Y | S20: 45278 | T20: 45318 | U20: In Progress | V20: Yi Zhang | W20: https://jira.tools.sap/browse/CTPSAPPRODUCT-4716 | AB20: 500002 | AC20: Open | AD20: No | AE20: Yes | AF20: I540507 | AG20: 10.76604 | AH20: 1.50944 | AI20: 288.30198 | AJ20: 5.7660397 | AK20: 10.76604 | AL20: 45278 | AN20: N | AO20: -1
A21: Ritu Bhargava | B21: CX Management America | C21: Chakraborty, Anindita <anindita.chakraborty01@sap.com>; Premanand S, David <david.premanand.s@sap.com> | D21: On-Mobile Device | E21: On-Mobile Device | F21: P1 | G21: S2 | H21: Y | I21: Incremental ONLY | J21: Cloud for Customer 2402 | L21: 45273 | M21: 45358 | N21: 45340 | O21: GTLC India | P21: Assmitra | Q21: Done | R21: Y | S21: 45279 | T21: 45314 | W21: [CTPSAPPRODUCT-4715] Cloud for Customer 2402 - SAPJIRA (tools.sap) | Z21: [WEBSERVSAPPRODUCT-3667] Cloud for Customer 2402 - SAPJIRA (tools.sap) | AA21: Export Scan required - Prashant | AB21: 500002 | AC21: Open | AD21: No | AE21: Yes | AF21: I342117 | AG21: 10.796228 | AH21: 1.50944 | AI21: 289.81142 | AJ21: 5.7962285 | AK21: 10.796228 | AL21: 45273 | AN21: Y | AO21: 26
A22: Ritu Bhargava | B22: CX Management America | C22: Ranadive, Saurabh <saurabh.ranadive@sap.com>; Alvarado Jimenez, Gilberto <gilberto.alvarado.jimenez@sap.com> | D22: Source Code | E22: On-Premise | F22: P1 | G22: S2 | H22: Y | I22: Incremental ONLY | J22: Composable Storefront -MDG (2310-2403) 2402 | K22: 45308 | L22: 45329 | N22: 45342 | O22: GTLC India | P22: Sandhya | Q22: Done | R22: Y | S22: 45338 | T22: 45342 | AA22: Requested to configure Blackduck | AB22: 500000 | AC22: Open | AD22: No | AE22: Yes | AF22: I538189 | AG22: 10.826417 | AH22: 1.509434 | AI22: 291.32086 | AJ22: 5.8264171 | AK22: 10.826417 | AL22: 45311 | AN22: Y | AO22: 0
A23: Ritu Bhargava | B23: Artificial Intelligence | C23: Jevtic, Bojan (external - Partner) <bojan.jevtic@sap.com>; Kahlau, Hui <hui.kahlau@sap.com> | D23: Source Code | E23: On-Premise | F23: P1 | G23: S2 | H23: Y | I23: Incremental ONLY | J23: Financial Services Accelerator Spa 2402 | L23: 45306 | M23: 45365 | N23: 45342 | O23: GTLC Germany | P23: Wilko | Q23: Done | R23: Y | S23: 45324 | T23: 45335 | W23: [CTPSAPPRODUCT-4704] Financial Services Accelerator Spa 2402 - SAPJIRA (tools.sap) | Z23: [WEBSERVSAPPRODUCT-3656] Financial Services Accelerator Spa 2402 - SAPJIRA (tools.sap) | AA23: Export Scan required - Siva | AB23: 500001 | AC23: Open | AD23: No | AE23: Yes | AF23: I541859 | AG23: 10.856606 | AH23: 1.509437 | AI23: 292.83029 | AJ23: 5.8566059 | AK23: 10.856606 | AL23: 45111 | AN23: Y | AO23: 7
A24: Jan Gilg | B24: SAP S/4 HANA | C24: BAR, Pascal <pascal.bar@sap.com> | D24: Outbound OEM | E24: On-Premise | F24: P1 | G24: S2 | H24: Y | I24: Incremental ONLY | J24: SAP Convergent Charging 2023_FPS1 | K24: 45588 | L24: 45303 | N24: 45351 | O24: GTLC China | P24: Yi Zhang | Q24: Done | R24: Y | S24: 45343 | T24: 45355 | W24: [CTPSAPPRODUCT-4731] SAP Convergent Charging 2023_FPS1 - SAPJIRA (tools.sap) | Z24: [WEBSERVSAPPRODUCT-3682] SAP Convergent Charging 2023_FPS1 - SAPJIRA (tools.sap) | AA24: Requested to configure Blackduck | First warning sent for late submission | AB24: 500000 | AC24: Open | AD24: No | AE24: Yes | AF24: I559269 | AG24: 10.886795 | AH24: 1.509434 | AI24: 294.33973 | AJ24: 5.8867946 | AK24: 10.886795 | AL24: 45330 | AN24: N | AO24: -4
A25: Ritu Bhargava | B25: CX Management America | C25: C John, Thomas <thomas.c.john@sap.com> | D25: Source Code | E25: On-Premise | F25: P1 | G25: S2 | H25: Y | I25: Incremental ONLY | J25: Citizen Engagement Accelerator 2024-Q1 | L25: 45320 | M25: 45373 | N25: 45363 | O25: GTLC Germany | P25: Rajat | Q25: Done | R25: Y | S25: 45344 | T25: 45350 | W25: [CTPSAPPRODUCT-4711] Citizen Engagement Accelerator 2024-Q1 - SAPJIRA (tools.sap) | Z25: [WEBSERVSAPPRODUCT-3663] Citizen Engagement Accelerator 2024-Q1 - SAPJIRA (tools.sap) | AA25: Export Scan required - Siva | AB25: 500021 | AC25: Open | AD25: No | AE25: Yes | AF25: I501689 | AG25: 10.916985 | AH25: 1.5094974 | AI25: 295.84923 | AJ25: 5.9169845 | AK25: 10.916985 | AL25: 45251 | AN25: N | AO25: 13
A26: Jan Gilg | B26: SAP S/4 HANA | C26: Lotterer, Sherry <sherry.lotterer@sap.com>; Gelle, Sreenivasulu <sreenivasulu.gelle@sap.com> | D26: Source Code | E26: On-Premise | F26: P1 | G26: S2 | H26: Y | I26: Incremental ONLY | J26: SAP Data Services 4.3 SP03 | L26: 45322 | N26: 45366 | O26: GTLC Germany | P26: Ilona | Q26: Done | R26: Y | S26: 45356 | T26: 45366 | W26: [CTPSAPPRODUCT-4722] SAP Data Services 4.3 SP03 - SAPJIRA (tools.sap) | Z26: [WEBSERVSAPPRODUCT-3673] SAP Data Services 4.3 SP03 - SAPJIRA (tools.sap) | AA26: Reassigned from Giang | Export scan assigned to Siva | AB26: 500000 | AC26: Open | AD26: No | AE26: Yes | AF26: D042776 | AG26: 10.947173 | AH26: 1.509434 | AI26: 297.35866 | AJ26: 5.9471732 | AK26: 10.947173 | AL26: 45316 | AN26: N | AO26: 0
A27: Jan Gilg | B27: SAP S/4 HANA | C27: Lotterer, Sherry <sherry.lotterer@sap.com>; He, Min <m.he@sap.com> | D27: Source Code | E27: On-Premise | F27: P1 | G27: S2 | H27: Y | I27: Incremental ONLY | J27: SAP Data Quality Management SDK 4.3 SP03 | L27: 45322 | M27: 45393 | N27: 45366 | O27: GTLC Germany | P27: Giang | Q27: Done | R27: Y | S27: 45344 | T27: 45351 | W27: [CTPSAPPRODUCT-4720] SAP Data Quality Management SDK 4.3 SP03 - SAPJIRA (tools.sap) | Z27: [WEBSERVSAPPRODUCT-3671] SAP Data Quality Management SDK 4.3 SP03 - SAPJIRA (tools.sap) | AA27: Export scan assigned to Siva | AB27: 500000 | AC27: Open | AD27: No | AE27: Yes | AF27: I540507 | AG27: 10.977362 | AH27: 1.509434 | AI27: 298.86809 | AJ27: 5.9773619 | AK27: 10.977362 | AL27: 45316 | AN27: N | AO27: 15
A28: Jan Gilg | B28: SAP S/4 HANA | C28: Lotterer, Sherry <sherry.lotterer@sap.com>; He, Min <m.he@sap.com> | D28: Source Code | E28: On-Premise | F28: P1 | G28: S2 | H28: Y | I28: Incremental ONLY | J28: SAP Information Steward 4.3 SP03 | L28: 45322 | N28: 45366 | O28: GTLC Germany | P28: Giang | Q28: Done | R28: Y | S28: 45344 | T28: 45360 | W28: [CTPSAPPRODUCT-4721] SAP Information Steward 4.3 SP03 - SAPJIRA (tools.sap) | Z28: [WEBSERVSAPPRODUCT-3672] SAP Information Steward 4.3 SP03 - SAPJIRA (tools.sap) | AA28: Requested to configure Blackduck | Export scan assigned to Siva | AB28: 500000 | AC28: Open | AD28: No | AE28: Yes | AF28: I540507 | AG28: 11.007551 | AH28: 1.509434 | AI28: 300.37753 | AJ28: 6.0075506 | AK28: 11.007551 | AL28: 45316 | AN28: N | AO28: 6
A29: Irfan Khan | B29: SAP HANA Database & Analytics | C29: Lazar, Helga <helga.lazar@sap.com>; Bouhsas, Khaldoun <khaldoun.bouhsas@sap.com> | D29: Source Code | E29: On-Premise | F29: P1 | G29: S2 | H29: Y | I29: Incremental ONLY | J29: HANA Cloud CE 2024.02 (QRC 01/2024) | L29: 45300 | M29: 45404 | N29: 45370 | O29: GTLC Germany | P29: Domenik | Q29: Done | R29: Y | S29: 45316 | T29: 45370 | W29: [CTPSAPPRODUCT-4719] HANA Cloud CE 2024.02 (QRC 01/2024) - SAPJIRA (tools.sap) | Z29: [WEBSERVSAPPRODUCT-3670] HANA Cloud CE 2024.02 (QRC 01/2024) - SAPJIRA (tools.sap) | AB29: 500000 | AC29: Open | AD29: No | AE29: Yes | AF29: I500407 | AG29: 11.037739 | AH29: 1.509434 | AI29: 301.88696 | AJ29: 6.0377392 | AK29: 11.037739 | AL29: 45313 | AN29: Y | AO29: 0
A30: Philipp Herzig | B30: Product Engineering Intelligent Enterprise and Cross Architecture | C30: Mueller, Christian Mathias <christ.mueller@sap.com> | D30: Source Code | E30: On-Premise | F30: P1 | G30: S2 | H30: Y | I30: Incremental ONLY | J30: AI libraries and SDKs MDG 2403b | L30: 45372 | M30: 45404 | N30: 45379 | O30: GTLC Germany | P30: Wilko | Q30: Done | R30: Y | S30: 45376 | T30: 45386 | AA30: Consultant assignment | AB30: 500000 | AC30: Open | AD30: No | AE30: Yes | AF30: I541859 | AG30: 11.067928 | AH30: 1.509434 | AI30: 303.3964 | AJ30: 6.0679279 | AK30: 11.067928 | AL30: 45369 | AM30: Y | AN30: N | AO30: -7
A31: Ritu Bhargava | B31: CX Management America | C31: Lachmann, Rio <rio.lachmann@sap.com> | D31: Source Code | E31: On-Demand (SaaS) | F31: P1 | G31: S2 | H31: Y | I31: OneTime Scan | J31: 304255988_Nestle_Comm_Cld_17 | L31: 45252 | M31: 45404 | N31: 45380 | O31: GTLC Germany | P31: Wilko | Q31: Done | R31: Y | S31: 45362 | T31: 45369 | W31: [CTPSAPPRODUCT-4732] 304255988_Nestle_Comm_Cld_17 - SAPJIRA (tools.sap) | Z31: [WEBSERVSAPPRODUCT-3683] 304255988_Nestle_Comm_Cld_17 - SAPJIRA (tools.sap) | AA31: Consultant assignment | AB31: 500000 | AC31: Open | AD31: No | AE31: Yes | AF31: I541859 | AG31: 11.098117 | AH31: 1.509434 | AI31: 304.90583 | AJ31: 6.0981166 | AK31: 11.098117 | AL31: 45336 | AN31: N | AO31: 11
A32: Ritu Bhargava | B32: CX Management America | C32: Kahlau, Hui <hui.kahlau@sap.com> | D32: Source Code | E32: On-Premise | F32: P1 | G32: S2 | H32: Y | I32: Incremental ONLY | J32: Financial Services Accelerator Spa 2404 | L32: 45364 | M32: 45404 | N32: 45391 | O32: GTLC Germany | P32: Wilko | Q32: Done | R32: Y | S32: 45373 | T32: 45384 | AB32: 500001 | AC32: Open | AD32: No | AE32: Yes | AF32: I541859 | AG32: 11.128305 | AH32: 1.509437 | AI32: 306.41527 | AJ32: 6.1283053 | AK32: 11.128305 | AL32: 45366 | AN32: Y | AO32: 7
A33: Ritu Bhargava | B33: CX Management America | C33: Ranadive, Saurabh <saurabh.ranadive@sap.com>; Alvarado Jimenez, Gilberto <gilberto.alvarado.jimenez@sap.com> | D33: Source Code | E33: On-Premise | F33: P1 | G33: S2 | H33: Y | I33: Incremental ONLY | J33: MCS (Modern Commerce Solution) Pilot 2404 | L33: 45397 | N33: 45412 | O33: GTLC Germany | P33: Wilko | Q33: Done | R33: Y | S33: 45404 | T33: 45407 | AA33: Crypto scan required - Siva | AB33: 500000 | AC33: Open | AD33: No | AE33: Yes | AF33: I541859 | AG33: 11.158494 | AH33: 1.509434 | AI33: 307.9247 | AJ33: 6.158494 | AK33: 11.158494 | AL33: 45400 | AM33: Y | AN33: Y | AO33: 5
A34: Ritu Bhargava | B34: CX Management America | C34: Schultheiss, Alexandra <alexandra.schultheiss@sap.com> | D34: Source Code | E34: On-Premise | F34: P1 | G34: S2 | H34: Y | I34: Incremental ONLY | J34: Telco and Utilities Accelerator 2024-Q2 | L34: 45377 | M34: 45421 | N34: 45454 | O34: GTLC Germany | P34: Rajat | Q34: Done | R34: Y | S34: 45449 | T34: 45461 | AB34: 500001 | AC34: Open | AD34: No | AE34: Yes | AF34: I501689 | AG34: 11.188683 | AH34: 1.509437 | AI34: 309.43414 | AJ34: 6.1886827 | AK34: 11.188683 | AL34: 45448 | AN34: N | AO34: -7
A35: Michael Ameling | B35: Cross Architecture | C35: Hellenschmidt, Michael <michael.hellenschmidt@sap.com> | D35: Source Code | E35: On-Premise | F35: P1 | G35: S2 | H35: Y | I35: Incremental ONLY | J35: SAP CP SDK Enterprise Search Plugin | L35: 45443 | M35: 45422 | N35: 45460 | O35: GTLC China | P35: Yi Zhang | Q35: Done | R35: Y | S35: 45460 | T35: 45461 | AB35: 500000 | AC35: Open | AD35: No | AE35: Yes | AF35: I559269 | AG35: 11.218871 | AH35: 1.509434 | AI35: 310.94357 | AJ35: 6.2188714 | AK35: 11.218871 | AL35: 45456 | AN35: N | AO35: -1
A36: Eva Zauke | B36: SAP Enterprise Adoption | C36: Chauhan, Monika <monika.chauhan@sap.com>; Venugopalan, Dinesh <dinesh.venugopalan@sap.com> | D36: Outbound OEM | E36: On-Premise | F36: P1 | G36: S2 | H36: Y | I36: Incremental ONLY | J36: SAP Enable Now FP 2405(OP, oOEM, OD) | L36: 45404 | M36: 45441 | N36: 45471 | O36: GTLC Germany | P36: Rajat | Q36: Done | R36: Y | S36: 45455 | T36: 45469 | AB36: 500001 | AC36: Open | AD36: No | AE36: Yes | AF36: I501689 | AG36: 11.24906 | AH36: 1.509437 | AI36: 312.45301 | AJ36: 6.2490602 | AK36: 11.24906 | AL36: 45447 | AN36: N | AO36: 2
A37: Ritu Bhargava | B37: CX Management America | C37: Bhargava, Ritu <thomas.c.john@sap.com> | D37: Source Code | E37: On-Premise | F37: P1 | G37: S2 | H37: Y | I37: Incremental ONLY | J37: Citizen Engagement Accelerator SPA 2407 | L37: 45455 | N37: 45482 | O37: GTLC China | P37: Liye | Q37: Done | R37: Y | S37: 45461 | T37: 45463 | AB37: 500000 | AC37: Open | AD37: No | AE37: Yes | AF37: I853975 | AG37: 11.279249 | AH37: 1.509434 | AI37: 313.96244 | AJ37: 6.2792488 | AK37: 11.279249 | AL37: 45460 | AN37: Y | AO37: 19
A38: Eva Zauke | B38: SAP Enterprise Adoption | C38: Beck, Cornelius (external - Project) <cornelius.beck@sap.com>; Bansal, Bikash <bikash.bansal@sap.com> | D38: Outbound OEM | E38: On-Premise | F38: P1 | G38: S2 | H38: Y | I38: Incremental ONLY | J38: SAP Customer Checkout 2.0 FP20 | L38: 45432 | M38: 45449 | N38: 45493 | O38: GTLC Germany | P38: Giang | Q38: Done | R38: Y | S38: 45434 | T38: 45477 | AA38: Consultant assignment | AB38: 500000 | AC38: Open | AD38: No | AE38: Yes | AF38: I540507 | AG38: 11.309438 | AH38: 1.509434 | AI38: 315.47188 | AJ38: 6.3094375 | AK38: 11.309438 | AL38: 45313 | AN38: N | AO38: 16
A39: Irfan Khan | B39: SAP HANA Database & Analytics | C39: Zhong, Gary <gary.zhong@sap.com> | D39: Outbound OEM | E39: On-Premise | F39: P1 | G39: S2 | H39: Y | I39: Incremental ONLY | J39: SRS 16.0 SP03 PL15 | L39: 45412 | M39: 45469 | N39: 45495 | O39: GTLC Germany | P39: Giang | Q39: Done | R39: Y | S39: 45436 | T39: 45477 | V39: Yi Zhang | W39: [CTPSAPPRODUCT-4733] SRS 16.0 SP03 PL15 - SAPJIRA (tools.sap) | AA39: Consultant assignment | AB39: 500000 | AC39: Open | AD39: No | AE39: Yes | AF39: I540507 | AG39: 11.339626 | AH39: 1.509434 | AI39: 316.98131 | AJ39: 6.3396262 | AK39: 11.339626 | AL39: 45428 | AN39: N | AO39: 18
A40: Ritu Bhargava | B40: CX Management America | C40: Ranadive, Saurabh <saurabh.ranadive@sap.com>; Alvarado Jimenez, Gilberto <gilberto.alvarado.jimenez@sap.com> | D40: Source Code | E40: On-Premise | F40: P1 | G40: S2 | H40: Y | I40: Incremental ONLY | J40: MCS (Modern Commerce Solution) Pilot 2407 | L40: 45495 | M40: 45477 | N40: 45499 | O40: GTLC Canada | P40: Chaitanya | Q40: Done | R40: Y | S40: 45497 | T40: 45503 | AB40: 500000 | AC40: Open | AD40: No | AE40: Yes | AF40: I532200 | AG40: 11.369815 | AH40: 1.509434 | AI40: 318.49074 | AJ40: 6.3698149 | AK40: 11.369815 | AL40: 45405 | AM40: Y | AN40: Y | AO40: -4
A41: Ritu Bhargava | B41: CX Management America | C41: Ranadive, Saurabh <saurabh.ranadive@sap.com>; Alvarado Jimenez, Gilberto <gilberto.alvarado.jimenez@sap.com> | D41: Source Code | E41: On-Premise | F41: P1 | G41: S2 | H41: Y | I41: Incremental ONLY | J41: MCS (Modern Commerce Solution) Pilot 2408 | L41: 45530 | N41: 45534 | O41: GTLC Canada | P41: Chaitanya | Q41: Done | R41: Y | S41: 45530 | T41: 45530 | AB41: 500000 | AC41: Open | AD41: No | AE41: Yes | AF41: I532200 | AG41: 11.732079 | AH41: 1.509434 | AI41: 336.60395 | AJ41: 6.732079 | AK41: 11.732079 | AL41: 45405 | AM41: Y | AN41: Y | AO41: 4
A42: Irfan Khan | B42: SAP HANA Database & Analytics | C42: Limberg, Angie <angie.limberg@sap.com> | D42: Outbound OEM | E42: On-Premise | F42: P1 | G42: S2 | H42: Y | I42: Incremental ONLY | J42: SAP HANA Cloud Integration,DS 2409 (1.0.11.54) | K42: 45369 | L42: 45509 | M42: 45477 | N42: 45541 | O42: GTLC Germany | P42: Giang | Q42: Done | R42: Y | S42: 45527 | T42: 45540 | AB42: 500000 | AC42: Open | AD42: No | AE42: Yes | AF42: I540507 | AG42: 11.430192 | AH42: 1.509434 | AI42: 321.50961 | AJ42: 6.4301922 | AK42: 11.430192 | AL42: 23/08/2024 | AM42: N | AN42: N | AO42: 1
A43: Ritu Bhargava | B43: CX Management America | C43: Hui, Kahlau <hui.kahlau@sap.com> | D43: Source Code | E43: On-Premise | F43: P1 | G43: S2 | H43: Y | I43: Incremental ONLY | J43: Financial Services Accelerator 2024-Q3 | L43: 45461 | M43: 45485 | N43: 45544 | O43: GTLC Canada | P43: Chaitanya | Q43: Done | R43: Y | S43: 45463 | T43: 45518 | AA43: Exception to use BD production Server | AB43: 500000 | AC43: Open | AD43: No | AE43: Yes | AF43: I532200 | AG43: 11.460381 | AH43: 1.509434 | AI43: 323.01905 | AJ43: 6.4603809 | AK43: 11.460381 | AL43: 45461 | AM43: N | AN43: Y | AO43: 26
A44: Philipp Herzig | B44: Product Engineering Intelligent Enterprise and Cross Architecture | C44: Mueller, Christian Mathias <christ.mueller@sap.com> | D44: Source Code | E44: On-Premise | F44: P1 | G44: S2 | H44: Y | I44: Incremental ONLY | J44: AI Libraries and SDKs MDG 2409a | K44: 45536 | L44: 45544 | M44: 45485 | N44: 45551 | O44: GTLC Germany | P44: Ravi | Q44: Done | R44: Y | S44: 45544 | T44: 45551 | AB44: 500000 | AC44: Open | AD44: No | AE44: Yes | AF44: D072009 | AG44: 11.49057 | AH44: 1.509434 | AI44: 324.52848 | AJ44: 6.4905696 | AK44: 11.49057 | AL44: 45540 | AM44: Y | AN44: N | AO44: 0
A45: Florian Heretsch | B45: PE MXE Mgmt | C45: Schmitt, Frank <frank.schmitt@sap.com> | D45: Source Code | E45: On-Mobile Device | F45: P1 | G45: S2 | H45: Y | I45: Incremental ONLY | J45: SAP Mobile Start APP 2.0 iOS - SRC | L45: 45505 | M45: 45485 | N45: 45558 | O45: GTLC Germany | P45: Giang | Q45: Done | R45: Y | S45: 45533 | T45: 45554 | AB45: 500000 | AC45: Open | AD45: No | AE45: Yes | AF45: I540507 | AG45: 11.520758 | AH45: 1.509434 | AI45: 326.03791 | AJ45: 6.5207583 | AK45: 11.520758 | AL45: 45533 | AN45: N | AO45: 4
A46: Florian Heretsch | B46: PE MXE Mgmt | C46: Arora, Aditya <aditya.arora@sap.com> | D46: Source Code | E46: On-Mobile Device | F46: P1 | G46: S2 | H46: Y | I46: Incremental ONLY | J46: SAP Mobile Start App 2.0 Android - SRC | L46: 45504 | M46: 45505 | N46: 45558 | O46: GTLC China | P46: Liye | Q46: Done | R46: Y | S46: 45533 | T46: 45541 | AB46: 500000 | AC46: Open | AD46: No | AE46: Yes | AF46: I853975 | AG46: 11.550947 | AH46: 1.509434 | AI46: 327.54735 | AJ46: 6.550947 | AK46: 11.550947 | AL46: 45533 | AN46: N | AO46: 17
A47: Ritu Bhargava | B47: CX Management America | C47: Ranadive, Saurabh <saurabh.ranadive@sap.com>; Alvarado Jimenez, Gilberto <gilberto.alvarado.jimenez@sap.com> | D47: Source Code | E47: On-Premise | F47: P1 | G47: S2 | H47: Y | I47: Incremental ONLY | J47: MCS (Modern Commerce Solution) Pilot 2409 | L47: 45558 | M47: 45505 | N47: 45562 | O47: GTLC Canada | P47: Chaitanya | Q47: Done | R47: Y | S47: 45547 | T47: 45566 | AB47: 500000 | AC47: Open | AD47: No | AE47: Yes | AF47: I532200 | AG47: 11.913211 | AH47: 1.509434 | AI47: 345.66056 | AJ47: 6.9132111 | AK47: 11.913211 | AL47: 45405 | AM47: Y | AN47: Y | AO47: -4
A48: Jan Gilg | B48: SAP S/4 HANA | C48: BAR, Pascal <pascal.bar@sap.com> | D48: Outbound OEM | E48: On-Premise | F48: P1 | G48: S2 | H48: Y | I48: Incremental ONLY | J48: SAP Convergent Charging 2023_FPS2 | K48: 45320 | L48: 45527 | N48: 45575 | O48: GTLC China | P48: Yi Zhang | Q48: Done | R48: Y | S48: 45573 | T48: 45576 | AB48: 500000 | AC48: Open | AD48: No | AE48: Yes | AF48: I559269 | AG48: 11.611324 | AH48: 1.509434 | AI48: 330.56622 | AJ48: 6.6113243 | AK48: 11.611324 | AL48: 45572 | AN48: N | AO48: -1
A49: Ritu Bhargava | B49: CX Management America | C49: Ranadive, Saurabh <saurabh.ranadive@sap.com>; Alvarado Jimenez, Gilberto <gilberto.alvarado.jimenez@sap.com> | D49: Source Code | E49: On-Premise | F49: P1 | G49: S2 | H49: Y | I49: Incremental ONLY | J49: MCS (Modern Commerce Solution) Pilot 2410 | L49: 45586 | M49: 45533 | N49: 45590 | O49: GTLC Canada | P49: Chaitanya | Q49: Done | R49: Y | S49: 45567 | T49: 45603 | AB49: 500000 | AC49: Open | AD49: No | AE49: Yes | AF49: I532200 | AG49: 11.641513 | AH49: 1.509434 | AI49: 332.07565 | AJ49: 6.641513 | AK49: 11.641513 | AL49: 45405 | AM49: Y | AN49: Y | AO49: -13
A50: Ritu Bhargava | B50: CX Management America | C50: Gopinath, Vivek <vivek.gopinath@sap.com> | D50: Source Code | E50: On-Premise | F50: P1 | G50: S2 | H50: Y | I50: Incremental ONLY | J50: Financial Services Accelerator Spa 2411 | L50: 45582 | M50: 45533 | N50: 45608 | O50: GTLC Canada | P50: Chaitanya | Q50: Done | R50: Y | S50: 45588 | T50: 45607 | AB50: 500003 | AC50: Open | AD50: No | AE50: Yes | AF50: I532200 | AG50: 12.003777 | AH50: 1.509443 | AI50: 350.18887 | AJ50: 7.0037774 | AK50: 12.003777 | AL50: 45587 | AN50: Y | AO50: 1
A51: Irfan Khan | B51: SAP HANA Database & Analytics | C51: Limberg, Angie <angie.limberg@sap.com> | D51: Outbound OEM | E51: On-Premise | F51: P1 | G51: S2 | H51: Y | I51: Incremental ONLY | J51: SAP HANA Cloud Integration,DS 2411 (1.0.11.55) | K51: 45551 | L51: 45575 | N51: 45611 | O51: GTLC China | P51: Liye | Q51: Done | R51: Y | S51: 45582 | T51: 45596 | AB51: 500001 | AC51: Open | AD51: No | AE51: Yes | AF51: I853975 | AG51: 11.701891 | AH51: 1.509437 | AI51: 335.09453 | AJ51: 6.7018906 | AK51: 11.701891 | AL51: 45575 | AN51: N | AO51: 15
A52: Stefan Baeuerle | B52: BTP HANA Mgmt Office | C52: Lazar, Helga <helga.lazar@sap.com> | D52: Outbound OEM | E52: On-Premise | F52: P1 | G52: S2 | H52: Y | I52: Incremental ONLY | J52: HANA 2.0 SPS 08 | K52: 45205 | L52: 45517 | M52: 45548 | N52: 45616 | O52: GTLC Germany | P52: Rajat | Q52: Done | R52: Y | S52: 45554 | T52: 45606 | AB52: 500000 | AC52: Open | AD52: No | AE52: Yes | AF52: I501689 | AG52: 11.732079 | AH52: 1.509434 | AI52: 336.60396 | AJ52: 6.7320793 | AK52: 11.732079 | AL52: 45554 | AM52: Y | AN52: Y | AO52: 10
A53: Stefan Baeuerle | B53: BTP HANA Mgmt Office | C53: Zhu, Hongjun <hongjun.zhu@sap.com> | D53: Outbound OEM | E53: On-Premise | F53: P1 | G53: S2 | H53: Y | I53: Incremental ONLY | J53: SAP Web IDE on HANA 2.0 SPS 08 | L53: 45512 | M53: 45561 | N53: 45616 | O53: GTLC China | P53: Yi Zhang | Q53: Done | R53: Y | S53: 45545 | T53: 45555 | AB53: 500000 | AC53: Open | AD53: No | AE53: Yes | AF53: I559269 | AG53: 11.762268 | AH53: 1.509434 | AI53: 338.1134 | AJ53: 6.762268 | AK53: 11.762268 | AL53: 45532 | AN53: N | AO53: 61
A54: Gero Decker | B54: SAP Signavio Product & Engineering | C54: Chauhan, Monika <monika.chauhan@sap.com> | D54: Outbound OEM | E54: On-Premise | F54: P1 | G54: S2 | H54: Y | I54: Incremental ONLY | J54: SAP Enable Now FP 2411(OP, oOEM, OD) | L54: 45555 | N54: 45618 | O54: GTLC China | P54: Yi Zhang | Q54: Done | R54: Y | S54: 45594 | T54: 45601 | V54: Yi Zhang | AB54: 500000 | AC54: Open | AD54: No | AE54: Yes | AF54: I559269 | AG54: 12.124532 | AH54: 1.509434 | AI54: 356.22661 | AJ54: 7.1245321 | AK54: 12.124532 | AL54: 45582 | AN54: N | AO54: 17
A55: Ritu Bhargava | B55: CX Management America | C55: Ranadive, Saurabh <saurabh.ranadive@sap.com>; Alvarado Jimenez, Gilberto <gilberto.alvarado.jimenez@sap.com> | D55: Source Code | E55: On-Premise | F55: P1 | G55: S2 | H55: Y | I55: Incremental ONLY | J55: MCS (Modern Commerce Solution) Pilot 2411 | L55: 45621 | M55: 45566 | N55: 45625 | O55: GTLC Canada | P55: Chaitanya | Q55: Done | R55: Y | S55: 45594 | T55: 45622 | AB55: 500000 | AC55: Open | AD55: No | AE55: Yes | AF55: I532200 | AG55: 11.822645 | AH55: 1.509434 | AI55: 341.13227 | AJ55: 6.8226453 | AK55: 11.822645 | AL55: 45405 | AM55: Y | AN55: Y | AO55: 3
A56: Philipp Herzig | B56: Product Engineering Intelligent Enterprise and Cross Architecture | C56: Mueller, Christian Mathias <christ.mueller@sap.com> | D56: Source Code | E56: On-Premise | F56: P1 | G56: S2 | H56: Y | I56: Incremental ONLY | J56: AI Libraries and SDKs MDG 2411b | K56: 45536 | L56: 45621 | M56: 45589 | N56: 45628 | O56: GTLC Canada | P56: Duane | Q56: Done | R56: Y | S56: 45628 | T56: 45628 | AB56: 500000 | AC56: Open | AD56: No | AE56: Yes | AF56: C5380108 | AG56: 12.184909 | AH56: 1.509434 | AI56: 359.24547 | AJ56: 7.1849095 | AK56: 12.184909 | AL56: 45540 | AM56: Y | AN56: N | AO56: 0
A57: Florian Heretsch | B57: PE MXE Mgmt | C57: Arora, Aditya <aditya.arora@sap.com> | D57: Source Code | E57: On-Mobile Device | F57: P1 | G57: S2 | H57: Y | I57: Incremental ONLY | J57: SAP Mobile Start App 2.1 Android - SRC | L57: 45602 | M57: 45600 | N57: 45629 | O57: GTLC Canada | P57: Chaitanya | Q57: Done | R57: Y | S57: 45615 | T57: 45622 | AA57: Consultant assignment | AB57: 500000 | AC57: Open | AD57: No | AE57: Yes | AF57: I532200 | AG57: 12.184909 | AH57: 1.509434 | AI57: 359.24547 | AJ57: 7.1849095 | AK57: 12.184909 | AL57: 45512 | AN57: N | AO57: 7
A58: Florian Heretsch | B58: PE MXE Mgmt | C58: Schmitt, Frank <frank.schmitt@sap.com> | D58: Source Code | E58: On-Mobile Device | F58: P1 | G58: S2 | H58: Y | I58: Incremental ONLY | J58: SAP Mobile Start App 2.1 iOS - SRC | L58: 45602 | N58: 45629 | O58: GTLC Canada | P58: Deb | Q58: Done | R58: Y | S58: 45615 | T58: 45623 | AA58: Consultant assignment | AB58: 500000 | AC58: Open | AD58: No | AE58: Yes | AF58: I077275 | AG58: 11.913211 | AH58: 1.509434 | AI58: 345.66057 | AJ58: 6.9132114 | AK58: 11.913211 | AL58: 45512 | AN58: N | AO58: 6
A59: Andreas Heckman | B59: Customer Solution Support and Innovation | C59: Eskov, Valentin (external - Project) <valentin.eskov@sap.com> | D59: Outbound OEM | E59: On-Premise | F59: P1 | G59: S2 | H59: Y | I59: Incremental ONLY | J59: ETD 2.0 SCV Core DU SP07 On-Premise (10.2024) | L59: 45534 | M59: 45463 | N59: 45641 | O59: GTLC Canada | P59: Deb | Q59: Done | R59: Y | S59: 45607 | T59: 45629 | AA59: Consultant assignment | AB59: 500000 | AC59: Open | AD59: No | AE59: Yes | AF59: I077275 | AG59: 11.9434 | AH59: 1.509434 | AI59: 347.17 | AJ59: 6.9434 | AK59: 11.9434 | AL59: 45607 | AN59: N | AO59: 12
A60: Philipp Herzig | B60: Product Engineering Intelligent Enterprise and Cross Architecture | C60: Mueller, Christian Mathias <christ.mueller@sap.com> | D60: Source Code | E60: On-Premise | F60: P1 | G60: S2 | H60: Y | I60: Incremental ONLY | J60: AI Libraries and SDKs MDG 2412a | K60: 45536 | L60: 45635 | M60: 45300 | N60: 45642 | O60: GTLC Canada | P60: Mengjie | Q60: Done | R60: Y | S60: 45639 | T60: 45639 | AB60: 500000 | AC60: Open | AD60: No | AE60: Yes | AF60: C5390744 | AG60: 12.305664 | AH60: 1.509434 | AI60: 365.28321 | AJ60: 7.3056642 | AK60: 12.305664 | AL60: 45540 | AM60: Y | AN60: N | AO60: 3
A61: Ritu Bhargava | B61: CX Management America | C61: Ranadive, Saurabh <saurabh.ranadive@sap.com>; Alvarado Jimenez, Gilberto <gilberto.alvarado.jimenez@sap.com> | D61: Source Code | E61: On-Premise | F61: P1 | G61: S2 | H61: Y | I61: Incremental ONLY | J61: MCS (Modern Commerce Solution) Pilot 2412 | L61: 45649 | M61: 45463 | N61: 45653 | O61: GTLC Canada | P61: Chaitanya | Q61: Done | R61: Y | S61: 45635 | T61: 45644 | AB61: 500000 | AC61: Open | AD61: No | AE61: Yes | AF61: I532200 | AG61: 12.607552 | AH61: 1.509434 | AI61: 380.37761 | AJ61: 7.6075522 | AK61: 12.607552 | AL61: 45405 | AM61: Y | AN61: Y | AO61: 9
A62: Claudio Muruzabal | B62: EMEA South, Customer Success | C62: Pelluru, Rajesh <r.pelluru@sap.com> | D62: Source Code | E62: On-Premise | F62: P1 | G62: S3 | H62: N | I62: Incremental ONLY | J62: 304954824_CSD_Bayern_TrikotApp | L62: 45303 | M62: 45473 | N62: 45334 | O62: GTLC Germany | P62: Giang | Q62: Done | R62: Y | S62: 45302 | T62: 45317 | AB62: 500002 | AC62: Open | AD62: No | AE62: Yes | AF62: I540507 | AG62: 12.305665 | AH62: 15.0944 | AI62: 365.28327 | AJ62: 7.3056654 | AK62: 12.305665 | AL62: 45278 | AN62: N | AO62: 17
A63: Jan Gilg | B63: SAP S/4 HANA | C63: Jiang, Qiulin (external - Project) <qiulin.jiang@sap.com>; Li, Hank <hank.li@sap.com> | D63: Source Code | E63: On-Premise | F63: P1 | G63: S3 | H63: N | I63: Incremental ONLY | J63: SAP Innovation Management 2 SP04 Patch 16 | L63: 45394 | M63: 45476 | N63: 45429 | O63: GTLC Germany | P63: Wilko | Q63: Done | R63: Y | S63: 45385 | T63: 45405 | AA63: Crypto scan - Assigned to Siva | Consultant assignment | AB63: 500000 | AC63: Open | AD63: No | AE63: Yes | AF63: I541859 | AG63: 13.241515 | AH63: 15.09434 | AI63: 412.07575 | AJ63: 8.241515 | AK63: 13.241515 | AL63: 45385 | AN63: N | AO63: 24
A64: Philipp Herzig | B64: Product Engineering Intelligent Enterprise and Cross Architecture | C64: Mueller, Christian Mathias <christ.mueller@sap.com> | D64: Source Code | E64: On-Premise | F64: P1 | G64: S3 | H64: Y | I64: Incremental ONLY | J64: AI Libraries and SDKs MDG 2409b | K64: 45536 | L64: 45565 | M64: 45533 | N64: 45572 | O64: GTLC Canada | P64: Deb | Q64: Done | R64: Y | S64: 45559 | T64: 45568 | AA64: Consultant assignment | AB64: 500000 | AC64: Open | AD64: No | AE64: Yes | AF64: I077275 | AG64: 12.637741 | AH64: 1.509434 | AI64: 381.88704 | AJ64: 7.6377409 | AK64: 12.637741 | AL64: 45540 | AM64: Y | AN64: N | AO64: 4
A65: Philipp Herzig | B65: Artificial Intelligence | C65: Mueller, Christian Mathias <christ.mueller@sap.com> | D65: Source Code | E65: On-Premise | F65: P1 | G65: S4 | H65: Y | I65: Incremental ONLY | J65: AI libraries and SDKs 2311 | K65: 45232 | L65: 45294 | M65: 45559 | N65: 45302 | O65: GTLC Germany | P65: Rajat | Q65: Done | S65: 45279 | T65: 45282 | AA65: CTP and WS will be covered in next release | current scans show 0 Matches | AB65: 500002 | AC65: Open | AD65: No | AE65: Yes | AF65: I501689 | AG65: 28.901908 | AH65: 1.509434 | AI65: 1295.0954 | AJ65: 25.901908 | AK65: 28.901908 | AL65: 45250 | AN65: N | AO65: 20
A66: Gary Slater | B66: Global Cloud Services | C66: Kabadzhova, Kremena <kremena.kabadzhova@sap.com> | D66: Outbound OEM | E66: On-Premise | F66: P1 | G66: S4 | H66: Y | I66: Incremental ONLY | J66: SAP Cloud Appliance Library 4.28 | M66: 45582 | N66: 45320 | O66: GTLC Germany | P66: Wilko | Q66: Done | R66: Y | S66: 45315 | T66: 45320 | AB66: 500002 | AC66: Open | AD66: No | AE66: Yes | AF66: I541859 | AG66: 12.698118 | AH66: 1.50944 | AI66: 384.90592 | AJ66: 7.6981183 | AK66: 12.698118 | AL66: 44930 | AM66: Y | AN66: N | AO66: 0
A67: Irfan Khan | B67: SAP HANA Database & Analytics | C67: Chennappa Krishnamurthy, Lavanya <lavanya.chennappa.krishnamurthy@sap.com> | D67: Source Code | E67: On-Premise | F67: P1 | G67: S4 | H67: Y | I67: Incremental ONLY | J67: SAP Advanced SQL Migration Tool 3.5.3 | L67: 45315 | M67: 45300 | N67: 45331 | O67: GTLC Germany | P67: Giang | Q67: Done | R67: Y | S67: 45316 | T67: 45324 | AA67: CTP and WS yet to be assigned | AB67: 500000 | AC67: Open | AD67: No | AE67: Yes | AF67: I540507 | AG67: 12.728307 | AH67: 1.509434 | AI67: 386.41535 | AJ67: 7.728307 | AK67: 12.728307 | AL67: 45309 | AN67: N | AO67: 7
A68: Ritu Bhargava | B68: CX Management America | C68: Schultheiss, Alexandra <alexandra.schultheiss@sap.com> | D68: Source Code | E68: On-Premise | F68: P1 | G68: S4 | H68: Y | I68: Incremental ONLY | J68: Telco and utilities composable storefront 2402 | L68: 45299 | M68: 45275 | N68: 45342 | O68: GTLC Germany | P68: Rajat | Q68: Done | R68: Y | S68: 45328 | T68: 45343 | W68: [CTPSAPPRODUCT-4709] Telco and utilities composable storefront 2402 - SAPJIRA (tools.sap) | Z68: [WEBSERVSAPPRODUCT-3661] Telco and utilities composable storefront 2402 - SAPJIRA (tools.sap) | AA68: Export scan is assigned to Chaitanya | AB68: 500001 | AC68: Open | AD68: No | AE68: Yes | AF68: I501689 | AG68: 12.758496 | AH68: 1.509437 | AI68: 387.92479 | AJ68: 7.7584958 | AK68: 12.758496 | AL68: 45246 | AN68: N | AO68: -1
A69: Michael Paul Weingartner | B69: SAP BTP Core | C69: Muessig, Peter <peter.muessig@sap.com>; Koehl, Felix <felix.koehl@sap.com> | D69: On-Premise | E69: On-Premise | F69: P1 | G69: S4 | H69: Y | I69: Incremental ONLY | J69: SAPUI5 1.121 | K69: 45217 | L69: 45329 | M69: 45315 | N69: 45344 | O69: GTLC Germany | P69: Ilona | Q69: Done | R69: Y | S69: 45316 | T69: 45349 | AA69: Ravi configured Blackduck for this release | Informed on integrating Blackduck | AB69: 500000 | AC69: Open | AD69: No | AE69: Yes | AF69: D042776 | AG69: 12.788684 | AH69: 1.509434 | AI69: 389.43422 | AJ69: 7.7886844 | AK69: 12.788684 | AL69: 45309 | AM69: Y | AN69: N | AO69: -5
A70: Gary Slater | B70: Global Cloud Services | C70: Kabadzhova, Kremena <kremena.kabadzhova@sap.com> | D70: Outbound OEM | E70: On-Premise | F70: P1 | G70: S4 | H70: Y | I70: Incremental ONLY | J70: SAP Cloud Appliance Library 4.29 | M70: 45307 | N70: 45349 | O70: GTLC Germany | P70: Wilko | Q70: Done | R70: Y | S70: 45330 | T70: 45362 | AA70: Upgraded from P2 to P1 | AB70: 500002 | AC70: Open | AD70: No | AE70: Yes | AF70: I541859 | AG70: 12.818873 | AH70: 1.50944 | AI70: 390.94366 | AJ70: 7.8188732 | AK70: 12.818873 | AL70: 44930 | AM70: Y | AN70: N | AO70: -13
A71: Irfan Khan | B71: SAP HANA Database & Analytics | C71: Limberg, Angie <angie.limberg@sap.com>; Loebens, Maicon <maicon.loebens@sap.com> | D71: Outbound OEM | E71: On-Premise | F71: P1 | G71: S4 | H71: Y | I71: Incremental ONLY | J71: SAP HANA Cloud Integration,DS 2403 (1.0.11.53) | L71: 45352 | M71: 45317 | N71: 45359 | O71: GTLC China | P71: Yi Zhang | Q71: Done | R71: Y | S71: 45344 | T71: 45351 | W71: [CTPSAPPRODUCT-4728] SAP HANA Cloud Integration,DS 2403 (1.0.11.53) - SAPJIRA (tools.sap) | Z71: [WEBSERVSAPPRODUCT-3679] SAP HANA Cloud Integration,DS 2403 (1.0.11.53) - SAPJIRA (tools.sap) | AA71: Requested to configure Blackduck | AB71: 500000 | AC71: Open | AD71: No | AE71: Yes | AF71: I559269 | AG71: 12.849062 | AH71: 1.509434 | AI71: 392.4531 | AJ71: 7.8490619 | AK71: 12.849062 | AL71: 45328 | AN71: N | AO71: 8
A72: Ritu Bhargava | B72: CX Management America | C72: Kahlau, Hui <hui.kahlau@sap.com> | D72: Source Code | E72: On-Premise | F72: P1 | G72: S4 | H72: Y | I72: Incremental ONLY | J72: Financial Services Accelerator 2024-Q1 | L72: 45272 | M72: 45317 | N72: 45363 | O72: GTLC China | P72: Yi Zhang | Q72: Done | R72: Y | S72: 45356 | T72: 45357 | W72: [CTPSAPPRODUCT-4707] Financial Services Accelerator 2024-Q1 - SAPJIRA (tools.sap) | Y72: [WEBSERVSAPPRODUCT-3659] Financial Services Accelerator 2024-Q1 - SAPJIRA (tools.sap) | AA72: Export scan is assigned to Alekh. | AB72: 500001 | AC72: Open | AD72: No | AE72: Yes | AF72: I559269 | AG72: 12.879251 | AH72: 1.509437 | AI72: 393.96253 | AJ72: 7.8792507 | AK72: 12.879251 | AL72: 45244 | AN72: Y | AO72: 6
A73: Ritu Bhargava | B73: CX Management America | C73: Ranadive, Saurabh <saurabh.ranadive@sap.com>; Alvarado Jimenez, Gilberto <gilberto.alvarado.jimenez@sap.com> | D73: Source Code | E73: On-Premise | F73: P1 | G73: S4 | H73: Y | I73: Incremental ONLY | J73: Composable Storefront -MDG (2310-2403) 2403 | L73: 45350 | M73: 45314 | N73: 45363 | O73: GTLC India | P73: Sandhya | Q73: Done | R73: Y | S73: 45343 | T73: 45348 | AB73: 500000 | AC73: Open | AD73: No | AE73: Yes | AF73: I538189 | AG73: 12.909439 | AH73: 1.509434 | AI73: 395.47197 | AJ73: 7.9094393 | AK73: 12.909439 | AL73: 45311 | AN73: Y | AO73: 15
A74: Michael Paul Weingartner | B74: SAP BTP Core | C74: Muessig, Peter <peter.muessig@sap.com>; Koehl, Felix <felix.koehl@sap.com> | D74: On-Premise | E74: On-Premise | F74: P1 | G74: S4 | H74: Y | I74: Incremental ONLY | J74: SAPUI5 1.122 | K74: 45329 | L74: 45357 | M74: 45322 | N74: 45372 | O74: GTLC Germany | P74: Ilona | Q74: Done | R74: Y | S74: 45343 | T74: 45349 | AB74: 500000 | AC74: Open | AD74: No | AE74: Yes | AF74: D042776 | AG74: 12.939628 | AH74: 1.509434 | AI74: 396.9814 | AJ74: 7.939628 | AK74: 12.939628 | AL74: 45309 | AM74: Y | AN74: N | AO74: 23
A75: Gary Slater | B75: Global Cloud Services | C75: Kabadzhova, Kremena <kremena.kabadzhova@sap.com> | D75: Outbound OEM | E75: On-Premise | F75: P1 | G75: S4 | H75: Y | I75: Incremental ONLY | J75: SAP Cloud Appliance Library 4.30 | M75: 45328 | N75: 45377 | O75: GTLC Germany | P75: Wilko | Q75: Done | R75: Y | S75: 45362 | T75: 45371 | AA75: Upgraded from P2 to P1 | AB75: 500002 | AC75: Open | AD75: No | AE75: Yes | AF75: I541859 | AG75: 12.969817 | AH75: 1.50944 | AI75: 398.49084 | AJ75: 7.9698168 | AK75: 12.969817 | AL75: 44930 | AM75: Y | AN75: N | AO75: 6
A76: Eva Zauke | B76: SAP Enterprise Adoption | C76: Beck, Cornelius (external - Project) <cornelius.beck@sap.com> | D76: Outbound OEM | E76: On-Premise | F76: P1 | G76: S4 | H76: Y | I76: Incremental ONLY | J76: SAP Customer Checkout 2.0 FP19 | L76: 45335 | M76: 45327 | N76: 45377 | O76: GTLC Germany | P76: Wilko | Q76: Done | R76: Y | S76: 45362 | T76: 45371 | W76: [CTPSAPPRODUCT-4718] SAP Customer Checkout 2.0 FP19 - SAPJIRA (tools.sap) | Z76: [WEBSERVSAPPRODUCT-3669] SAP Customer Checkout 2.0 FP19 - SAPJIRA (tools.sap) | AB76: 500000 | AC76: Open | AD76: No | AE76: Yes | AF76: I541859 | AG76: 13.000005 | AH76: 1.509434 | AI76: 400.00027 | AJ76: 8.0000055 | AK76: 13.000005 | AL76: 45313 | AN76: N | AO76: 6
A77: Ritu Bhargava | B77: CX Management America | C77: Ranadive, Saurabh <saurabh.ranadive@sap.com>; Alvarado Jimenez, Gilberto <gilberto.alvarado.jimenez@sap.com> | D77: Source Code | E77: On-Premise | F77: P1 | G77: S4 | H77: Y | I77: Incremental ONLY | J77: Composable Storefront -MDG (2310-2403) 2404 | L77: 45378 | M77: 45307 | N77: 45391 | O77: GTLC Germany | P77: Wilko | Q77: Done | R77: Y | S77: 45390 | T77: 45391 | AB77: 500000 | AC77: Open | AD77: No | AE77: Yes | AF77: I541859 | AG77: 13.030194 | AH77: 1.509434 | AI77: 401.50971 | AJ77: 8.0301942 | AK77: 13.030194 | AL77: 45311 | AN77: Y | AO77: 0
A78: Michael Paul Weingartner | B78: SAP BTP Core | C78: Muessig, Peter <peter.muessig@sap.com>; Koehl, Felix <felix.koehl@sap.com> | D78: On-Premise | E78: On-Premise | F78: P1 | G78: S4 | H78: Y | I78: Incremental ONLY | J78: SAPUI5 1.123 | K78: 45357 | L78: 45385 | M78: 45278 | N78: 45400 | O78: GTLC Germany | P78: Ilona | Q78: Done | R78: Y | S78: 45390 | T78: 45434 | AB78: 500000 | AC78: Open | AD78: No | AE78: Yes | AF78: D042776 | AG78: 13.060383 | AH78: 1.509434 | AI78: 403.01914 | AJ78: 8.0603829 | AK78: 13.060383 | AL78: 45309 | AM78: Y | AN78: N | AO78: -34
A79: Gary Slater | B79: Global Cloud Services | C79: Kabadzhova, Kremena <kremena.kabadzhova@sap.com> | D79: Outbound OEM | E79: On-Premise | F79: P1 | G79: S4 | H79: Y | I79: Incremental ONLY | J79: SAP Cloud Appliance Library 4.31 | M79: 45341 | N79: 45405 | O79: GTLC Germany | P79: Wilko | Q79: Done | R79: Y | S79: 45395 | T79: 45398 | AA79: Upgraded from P2 to P1 | AB79: 500002 | AC79: Open | AD79: No | AE79: Yes | AF79: I541859 | AG79: 13.090572 | AH79: 1.50944 | AI79: 404.52858 | AJ79: 8.0905717 | AK79: 13.090572 | AL79: 44930 | AM79: Y | AN79: N | AO79: 7
A80: Irfan Khan | B80: SAP HANA Database & Analytics | C80: Dong, Zhi-peng <zhi-peng.dong@sap.com> | D80: Outbound OEM | E80: On-Premise | F80: P1 | G80: S4 | H80: Y | I80: Incremental ONLY | J80: ASE 16.0 SP04 PL06 | L80: 45328 | M80: 45345 | N80: 45411 | O80: GTLC Germany | P80: Wilko | Q80: Done | R80: Y | S80: 45328 | T80: 45407 | W80: [CTPSAPPRODUCT-4723] ASE SP04 PL06 - SAPJIRA (tools.sap) | Z80: [WEBSERVSAPPRODUCT-3674] ASE SP04 PL06 - SAPJIRA (tools.sap) | AB80: 500000 | AC80: Open | AD80: No | AE80: Yes | AF80: I541859 | AG80: 13.12076 | AH80: 1.509434 | AI80: 406.03802 | AJ80: 8.1207603 | AK80: 13.12076 | AL80: 45321 | AN80: N | AO80: 4
A81: Irfan Khan | B81: SAP HANA Database & Analytics | C81: Sharma, Anuj <anuj.sharma01@sap.com> | D81: Outbound OEM | E81: On-Premise | F81: P1 | G81: S4 | H81: Y | I81: Incremental ONLY | J81: SDK 16.0 SP04 PL06 | L81: 45362 | M81: 45345 | N81: 45411 | O81: GTLC Germany | P81: Wilko | Q81: Done | R81: Y | S81: 45370 | T81: 45383 | W81: https://jira.tools.sap/browse/CTPSAPPRODUCT-4727 | Z81: https://jira.tools.sap/browse/WEBSERVSAPPRODUCT-3678 | AB81: 500000 | AC81: Open | AD81: No | AE81: Yes | AF81: I541859 | AG81: 13.150949 | AH81: 1.509434 | AI81: 407.54745 | AJ81: 8.150949 | AK81: 13.150949 | AL81: 45329 | AN81: N | AO81: 28
A82: Irfan Khan | B82: SAP HANA Database & Analytics | C82: Sharma, Anuj <anuj.sharma01@sap.com> | D82: Outbound OEM | E82: On-Premise | F82: P1 | G82: S4 | H82: Y | I82: Incremental ONLY | J82: OS 16.0 SP04 PL06 | L82: 45362 | M82: 45348 | N82: 45411 | O82: GTLC Germany | P82: Wilko | Q82: Done | R82: Y | S82: 45370 | T82: 45383 | W82: https://jira.tools.sap/browse/CTPSAPPRODUCT-4726 | Z82: https://jira.tools.sap/browse/WEBSERVSAPPRODUCT-3677 | AA82: Requested to configure Blackduck | AB82: 500000 | AC82: Open | AD82: No | AE82: Yes | AF82: I541859 | AG82: 13.181138 | AH82: 1.509434 | AI82: 409.05688 | AJ82: 8.1811377 | AK82: 13.181138 | AL82: 45329 | AN82: N | AO82: 28
A83: Irfan Khan | B83: SAP HANA Database & Analytics | C83: Zhong, Gary <gary.zhong@sap.com> | D83: Outbound OEM | E83: On-Premise | F83: P1 | G83: S4 | H83: Y | I83: Incremental ONLY | J83: SRS SP04 PL06 | L83: 45376 | M83: 45345 | N83: 45411 | O83: GTLC Germany | P83: Wilko | Q83: Done | R83: Y | S83: 45370 | T83: 45399 | W83: [CTPSAPPRODUCT-4730] SRS 16.0 SP04 PL06 - SAPJIRA (tools.sap) | Z83: [WEBSERVSAPPRODUCT-3681] SRS 16.0 SP04 PL06 - SAPJIRA (tools.sap) | AA83: Requested to configure Blackduck | AB83: 500000 | AC83: Open | AD83: No | AE83: Yes | AF83: I541859 | AG83: 13.211326 | AH83: 1.509434 | AI83: 410.56632 | AJ83: 8.2113264 | AK83: 13.211326 | AL83: 45327 | AN83: N | AO83: 12
A84: Ritu Bhargava | B84: CX Management America | C84: Ranadive, Saurabh <saurabh.ranadive@sap.com>; Alvarado Jimenez, Gilberto <gilberto.alvarado.jimenez@sap.com> | D84: Source Code | E84: On-Premise | F84: P1 | G84: S4 | H84: Y | I84: Incremental ONLY | J84: Composable Storefront -MDG (2310-2403) 2405 | L84: 45413 | M84: 45315 | N84: 45426 | O84: GTLC Germany | P84: Wilko | Q84: Done | R84: Y | S84: 45404 | T84: 45414 | AB84: 500000 | AC84: Open | AD84: No | AE84: Yes | AF84: I541859 | AG84: 13.241515 | AH84: 1.509434 | AI84: 412.07575 | AJ84: 8.241515 | AK84: 13.241515 | AL84: 45311 | AM84: Y | AN84: Y | AO84: 12
A85: Michael Paul Weingartner | B85: SAP BTP Core | C85: Muessig, Peter <peter.muessig@sap.com>; Koehl, Felix <felix.koehl@sap.com> | D85: On-Premise | E85: On-Premise | F85: P1 | G85: S4 | H85: Y | I85: Incremental ONLY | J85: SAPUI5 1.124 | K85: 45385 | L85: 45412 | N85: 45428 | O85: GTLC Germany | P85: Ilona | Q85: Done | R85: Y | S85: 45404 | T85: 45420 | AB85: 500000 | AC85: Open | AD85: No | AE85: Yes | AF85: D042776 | AG85: 13.271704 | AH85: 1.509434 | AI85: 413.58519 | AJ85: 8.2717037 | AK85: 13.271704 | AL85: 45309 | AM85: Y | AN85: N | AO85: 8
A86: Jan Gilg | B86: SAP S/4 HANA | C86: Huang, Allen <allen.huang@sap.com>; Yu, Terry <terry.yu@sap.com> | D86: Outbound OEM | E86: On-Premise | F86: P1 | G86: S4 | H86: Y | I86: Incremental ONLY | J86: B1 10.0 FP 2405 | K86: 45187 | L86: 45366 | M86: 45356 | N86: 45429 | O86: GTLC China | P86: Yi Zhang | Q86: Done | S86: 45362 | T86: 45397 | AA86: Need to discuss with team on Blackduck Configuration | CTP and WS tickets yet to be created | AB86: 500000 | AC86: Open | AD86: No | AE86: Yes | AF86: I559269 | AG86: 13.301892 | AH86: 1.509434 | AI86: 415.09462 | AJ86: 8.3018924 | AK86: 13.301892 | AL86: 45341 | AN86: N | AO86: 32
A87: Ritu Bhargava | B87: CX Management America | C87: Ranadive, Saurabh <saurabh.ranadive@sap.com>; Alvarado Jimenez, Gilberto <gilberto.alvarado.jimenez@sap.com> | D87: Source Code | E87: On-Premise | F87: P1 | G87: S4 | H87: Y | I87: Incremental ONLY | J87: MCS (Modern Commerce Solution) Pilot 2405 | L87: 45427 | M87: 45357 | N87: 45442 | O87: GTLC Germany | P87: Giang | Q87: Done | R87: Y | S87: 45447 | T87: 45449 | AB87: 500000 | AC87: Open | AD87: No | AE87: Yes | AF87: I540507 | AG87: 13.332081 | AH87: 1.509434 | AI87: 416.60405 | AJ87: 8.3320811 | AK87: 13.332081 | AL87: 45400 | AM87: Y | AN87: Y | AO87: -7
A88: Ritu Bhargava | B88: CX Management America | C88: Ranadive, Saurabh <saurabh.ranadive@sap.com>; Alvarado Jimenez, Gilberto <gilberto.alvarado.jimenez@sap.com> | D88: Source Code | E88: On-Premise | F88: P1 | G88: S4 | H88: Y | I88: Incremental ONLY | J88: Composable Storefront -MDG (2310-2403) 2406 | L88: 45441 | M88: 45357 | N88: 45454 | O88: GTLC Canada | P88: Chaitanya | Q88: Done | R88: Y | S88: 45463 | T88: 45526 | AB88: 500000 | AC88: Open | AD88: No | AE88: Yes | AF88: I532200 | AG88: 13.36227 | AH88: 1.509434 | AI88: 418.11349 | AJ88: 8.3622698 | AK88: 13.36227 | AL88: 45311 | AM88: Y | AN88: Y | AO88: -72
A89: Michael Paul Weingartner | B89: SAP BTP Core | C89: Muessig, Peter <peter.muessig@sap.com>; Koehl, Felix <felix.koehl@sap.com> | D89: On-Premise | E89: On-Premise | F89: P1 | G89: S4 | H89: Y | I89: Incremental ONLY | J89: SAPUI5 1.125 | K89: 45412 | L89: 45441 | M89: 45348 | N89: 45456 | O89: GTLC Germany | P89: Ilona | Q89: Done | R89: Y | S89: 45436 | T89: 45450 | AA89: Jira yet to be created | AB89: 500000 | AC89: Open | AD89: No | AE89: Yes | AF89: D042776 | AG89: 13.392458 | AH89: 1.509434 | AI89: 419.62292 | AJ89: 8.3924584 | AK89: 13.392458 | AL89: 45309 | AM89: Y | AN89: N | AO89: 6
A90: Ritu Bhargava | B90: CX Management America | C90: Ranadive, Saurabh <saurabh.ranadive@sap.com>; Alvarado Jimenez, Gilberto <gilberto.alvarado.jimenez@sap.com> | D90: Source Code | E90: On-Premise | F90: P1 | G90: S4 | H90: Y | I90: Incremental ONLY | J90: MCS (Modern Commerce Solution) Pilot 2406 | L90: 45455 | N90: 45470 | O90: GTLC Canada | P90: Chaitanya | Q90: Done | R90: Y | S90: 45461 | T90: 45477 | AB90: 500000 | AC90: Open | AD90: No | AE90: Yes | AF90: I532200 | AG90: 13.422647 | AH90: 1.509434 | AI90: 421.13236 | AJ90: 8.4226471 | AK90: 13.422647 | AL90: 45405 | AM90: Y | AN90: Y | AO90: -7
A91: Philipp Herzig | B91: Product Engineering Intelligent Enterprise and Cross Architecture | C91: Mueller, Christian Mathias <christ.mueller@sap.com> | D91: Source Code | E91: On-Premise | F91: P1 | G91: S4 | H91: Y | I91: Incremental ONLY | J91: AI libraries and SDKs MDG 2406b | L91: 45470 | M91: 45359 | N91: 45477 | O91: GTLC China | P91: Yi Zhang | Q91: Done | R91: Y | S91: 45475 | T91: 45478 | AB91: 500000 | AC91: Open | AD91: No | AE91: Yes | AF91: I559269 | AG91: 13.452836 | AH91: 1.509434 | AI91: 422.64179 | AJ91: 8.4528358 | AK91: 13.452836 | AL91: 45369 | AM91: Y | AN91: N | AO91: -1
A92: Ritu Bhargava | B92: CX Management America | C92: Ranadive, Saurabh <saurabh.ranadive@sap.com>; Alvarado Jimenez, Gilberto <gilberto.alvarado.jimenez@sap.com> | D92: Source Code | E92: On-Premise | F92: P1 | G92: S4 | H92: Y | I92: Incremental ONLY | J92: Composable Storefront -MDG (2310-2403) 2407 | L92: 45469 | M92: 45359 | N92: 45482 | O92: GTLC Canada | P92: Chaitanya | Q92: Done | R92: Y | S92: 45475 | T92: 45566 | AB92: 500000 | AC92: Open | AD92: No | AE92: Yes | AF92: I532200 | AG92: 13.483024 | AH92: 1.509434 | AI92: 424.15122 | AJ92: 8.4830245 | AK92: 13.483024 | AL92: 45438 | AM92: Y | AN92: Y | AO92: -84
A93: Michael Paul Weingartner | B93: SAP BTP Core | C93: Muessig, Peter <peter.muessig@sap.com>; Koehl, Felix <felix.koehl@sap.com> | D93: On-Premise | E93: On-Premise | F93: P1 | G93: S4 | H93: Y | I93: Incremental ONLY | J93: SAPUI5 1.126 | K93: 45441 | L93: 45469 | M93: 45357 | N93: 45484 | O93: GTLC China | P93: Yi Zhang | Q93: Done | R93: Y | S93: 45476 | T93: 45482 | AA93: Reassigned from Ilona (13/6/24) | AB93: 500000 | AC93: Open | AD93: No | AE93: Yes | AF93: I559269 | AG93: 13.513213 | AH93: 1.509434 | AI93: 425.66066 | AJ93: 8.5132132 | AK93: 13.513213 | AL93: 45309 | AM93: Y | AN93: N | AO93: 2
A94: Irfan Khan | B94: SAP HANA Database & Analytics | C94: Yadav, Bharati <bharati.yadav@sap.com> | D94: Outbound OEM | E94: On-Premise | F94: P1 | G94: S4 | H94: Y | I94: Incremental ONLY | J94: SDK 16.0 SP03 PL15 | L94: 45449 | M94: 45371 | N94: 45495 | O94: GTLC China | P94: Yi Zhang | Q94: Done | R94: Y | S94: 45442 | T94: 45469 | W94: [CTPSAPPRODUCT-4734] SDK 16.0 SP03 PL15 - SAPJIRA (tools.sap) | AB94: 500000 | AC94: Open | AD94: No | AE94: Yes | AF94: I559269 | AG94: 13.543402 | AH94: 1.509434 | AI94: 427.17009 | AJ94: 8.5434018 | AK94: 13.543402 | AL94: 45442 | AM94: N | AN94: N | AO94: 26
A95: Irfan Khan | B95: SAP HANA Database & Analytics | C95: Yadav, Bharati <bharati.yadav@sap.com> | D95: Outbound OEM | E95: On-Premise | F95: P1 | G95: S4 | H95: Y | I95: Incremental ONLY | J95: OS 16.0 SP04 PL06 | L95: 45449 | N95: 45495 | O95: GTLC China | P95: Yi Zhang | Q95: Done | R95: Y | S95: 45442 | T95: 45469 | W95: [CTPSAPPRODUCT-4735] OS 16.0 SP04 PL06 - SAPJIRA (tools.sap) | AB95: 500000 | AC95: Open | AD95: No | AE95: Yes | AF95: I559269 | AG95: 13.573591 | AH95: 1.509434 | AI95: 428.67953 | AJ95: 8.5735905 | AK95: 13.573591 | AL95: 45442 | AM95: N | AN95: N | AO95: 26
A96: Irfan Khan | B96: SAP HANA Database & Analytics | C96: Dong, Zhi-peng <zhi-peng.dong@sap.com> | D96: Outbound OEM | E96: On-Premise | F96: P1 | G96: S4 | H96: Y | I96: Incremental ONLY | J96: ASE 16.0 SP03 PL15 | L96: 45464 | M96: 45338 | N96: 45495 | O96: GTLC China | P96: Yi Zhang | Q96: Done | R96: Y | S96: 45442 | T96: 45460 | W96: [CTPSAPPRODUCT-4736] ASE 16.0 SP03 PL15 - SAPJIRA (tools.sap) | AB96: 500000 | AC96: Open | AD96: No | AE96: Yes | AF96: I559269 | AG96: 13.603779 | AH96: 1.509434 | AI96: 430.18896 | AJ96: 8.6037792 | AK96: 13.603779 | AL96: 45442 | AM96: N | AN96: N | AO96: 35
A97: Philipp Herzig | B97: Product Engineering Intelligent Enterprise and Cross Architecture | C97: Mueller, Christian Mathias <christ.mueller@sap.com> | D97: Source Code | E97: On-Premise | F97: P1 | G97: S4 | H97: Y | I97: Incremental ONLY | J97: AI libraries and SDKs MDG 2407b | L97: 45498 | M97: 45373 | N97: 45505 | O97: GTLC Canada | P97: Deb | Q97: Done | R97: Y | S97: 45503 | T97: 45552 | AA97: Consultant assignment | AB97: 500000 | AC97: Open | AD97: No | AE97: Yes | AF97: I077275 | AG97: 13.633968 | AH97: 1.509434 | AI97: 431.69839 | AJ97: 8.6339679 | AK97: 13.633968 | AL97: 45369 | AM97: Y | AN97: N | AO97: -47
A98: Michael Paul Weingartner | B98: SAP BTP Core | C98: Muessig, Peter <peter.muessig@sap.com>; Koehl, Felix <felix.koehl@sap.com> | D98: On-Premise | E98: On-Premise | F98: P1 | G98: S4 | H98: Y | I98: Incremental ONLY | J98: SAPUI5 1.127 | K98: 45469 | L98: 45497 | M98: 45373 | N98: 45512 | O98: GTLC China | P98: Yi Zhang | Q98: Done | R98: Y | S98: 45484 | T98: 45503 | AA98: Jira yet to be created | AB98: 500000 | AC98: Open | AD98: No | AE98: Yes | AF98: I559269 | AG98: 13.664157 | AH98: 1.509434 | AI98: 433.20783 | AJ98: 8.6641566 | AK98: 13.664157 | AL98: 45309 | AM98: Y | AN98: N | AO98: 9
A99: Ritu Bhargava | B99: CX Management America | C99: Ranadive, Saurabh <saurabh.ranadive@sap.com>; Alvarado Jimenez, Gilberto <gilberto.alvarado.jimenez@sap.com> | D99: Source Code | E99: On-Premise | F99: P1 | G99: S4 | H99: Y | I99: Incremental ONLY | J99: Composable Storefront -MDG (2310-2403) 2408 | L99: 45504 | M99: 45376 | N99: 45517 | O99: GTLC Canada | P99: Chaitanya | Q99: Done | R99: Y | S99: 45506 | T99: 45519 | AB99: 500000 | AC99: Open | AD99: No | AE99: Yes | AF99: I532200 | AG99: 13.694345 | AH99: 1.509434 | AI99: 434.71726 | AJ99: 8.6943452 | AK99: 13.694345 | AL99: 45438 | AM99: Y | AN99: Y | AO99: -2
A100: Philipp Herzig | B100: Product Engineering Intelligent Enterprise and Cross Architecture | C100: Mueller, Christian Mathias <christ.mueller@sap.com> | D100: Source Code | E100: On-Premise | F100: P1 | G100: S4 | H100: Y | I100: Incremental ONLY | J100: AI libraries and SDKs MDG 2408b | L100: 45526 | M100: 45373 | N100: 45533 | O100: GTLC Canada | P100: Deb | Q100: Done | R100: Y | S100: 45517 | T100: 45552 | AA100: Consultant assignment | AB100: 500000 | AC100: Open | AD100: No | AE100: Yes | AF100: I077275 | AG100: 13.724534 | AH100: 1.509434 | AI100: 436.2267 | AJ100: 8.7245339 | AK100: 13.724534 | AL100: 45369 | AM100: Y | AN100: N | AO100: -19
...

Sheet 2025 Done
A1: L1 Manager | B1: L1 Development Unit | C1: Dev Contact | D1: Program Category | E1: Delivery Mode | F1: Priority | G1: Severity | H1: Previously Scanned | I1: Scan Category | J1: Program (Delivery) | K1: Start of Development | L1: End of Development | M1: RTC | N1: Location | O1: FOSS Analyst | P1: FOSS Scan State | Q1: Black Duck Scan | R1: FOSS Scan Assigned | S1: FOSS Scan Closed | T1: Commercial Scan Status | U1: Comm Analyst | V1: CTP Scan Ticket JIRA link | W1: Web Service Scan Status | X1: Web Service Analyst | Y1: WS Scan Ticket JIRA link | Z1: Comments | AA1: SLOC Count | AB1: Tracking System Ticket Status | AC1: RTC Passed | AD1: Recommended to Request Exemption | AE1: Owner # | AF1: Estimated Calendar Week (CW) for the scan to be "In Progress" | AG1: Estimated # of days to complete the first round of scan | AH1: Cumulative Days | AI1: CW to be added to the current CW | AJ1: Estimated CW for scan to be in progress | AK1: Scan Submission Date | AL1: Continuous scan | AM1: Crown Jewel | AN1: Closed within SLA | AO1: Unreviewed components | AP1: Unmatched | AQ1: Snippets | AS1: RDM
A2: Manoj Swaminathan | B2: ISBN CloudOps Cross COPS | C2: Schneider, Markus<ma.schneider@sap.com> | D2: On-Mobile Device | E2: On-Mobile Device | F2: P1 | G2: S1 | H2: Y | I2: Incremental ONLY | J2: SAP Concur Mobile iOS 10.19 (Feb 2025) | L2: 45698 | M2: 45712 | N2: GTLC Vietnam | O2: Thao | P2: Done | Q2: Y | R2: 45705 | S2: 45706 | AA2: 500000 | AB2: Open | AC2: No | AD2: Yes | AE2: I758015 | AF2: 6.7169811 | AG2: 1.509434 | AH2: 135.84906 | AI2: 2.7169811 | AJ2: 6.7169811 | AK2: 45710 | AL2: Y | AM2: Y | AN2: -298 | AS2: 45408
A3: Uma Rani T M | B3: Strategy & Transformation, Customer Success | C3: BAR, Pascal<pascal.bar@sap.com> | D3: Outbound OEM | E3: On-Premise | F3: P1 | G3: S1 | H3: Y | I3: Incremental ONLY | J3: SAP Convergent Charging 2023_FPS3 | K3: 45551 | L3: 45667 | M3: 45714 | N3: GTLC Germany | O3: Giang | P3: Done | Q3: Y | R3: 45698 | S3: 45716 | AA3: 500000 | AB3: Open | AC3: No | AD3: Yes | AE3: I540507 | AF3: 7.4716981 | AG3: 1.509434 | AH3: 173.58491 | AI3: 3.4716981 | AJ3: 7.4716981 | AK3: 45694 | AL3: N | AM3: N | AN3: -49 | AS3: 45667
A4: Michael Ameling | B4: Cross Architecture | C4: Ivanov, Ivan<ivan.ivanov05@sap.com> | D4: Outbound OEM | E4: On-Premise | F4: P1 | G4: S1 | H4: N | I4: Incremental ONLY | J4: FS on K8s Delivery 2511a | L4: 45961 | M4: 45974 | N4: GTLC Vietnam | O4: Khoi | P4: Done | Q4: Y | R4: 45967 | S4: 45973 | AA4: 500000 | AB4: Open | AC4: No | AD4: Yes | AE4: I758929 | AF4: 7.0490566 | AG4: 15.09434 | AH4: 152.45283 | AI4: 3.0490566 | AJ4: 7.0490566 | AK4: 45964 | AL4: N | AM4: N | AN4: 0 | AS4: 45973
A5: Michael Ameling | B5: Cross Architecture | C5: Dong, Zhi-peng <zhi-peng.dong@sap.com> | D5: Outbound OEM | E5: On-Premise | F5: P1 | G5: S1 | H5: Y | I5: Incremental ONLY | J5: ASE 16.0 SP04 PL08 | L5: 45918 | M5: 46001 | N5: GTLC Vietnam | O5: Hoan | P5: Done | Q5: Y | R5: 45944 | S5: 45954 | AA5: 500000 | AB5: Open | AC5: No | AD5: Yes | AE5: I758150 | AF5: 7.1396226 | AG5: 1.509434 | AH5: 156.98113 | AI5: 3.1396226 | AJ5: 7.1396226 | AK5: 45925 | AL5: N | AM5: N | AN5: 40 | AO5: 17 | AP5: 0 | AQ5: 385 | AS5: 45994
A6: Rachel Laventure | B6: People Growth Management Office UK | C6: Gopinath, Vivek <vivek.gopinath@sap.com> | D6: Source Code | E6: On-Premise | F6: P1 | G6: S2 | H6: Y | I6: Incremental ONLY | J6: Financial Services Accelerator Spa 2502 | K6: 45642 | L6: 45672 | M6: 45700 | N6: GTLC Canada | O6: Chaitanya | P6: Done | Q6: Y | R6: 45674 | S6: 45720 | AA6: 500000 | AB6: Open | AC6: No | AD6: Yes | AE6: I532200 | AF6: 7.109434 | AG6: 1.509434 | AH6: 155.4717 | AI6: 3.109434 | AJ6: 7.109434 | AK6: 45643 | AL6: N | AM6: N | AN6: -28 | AS6: 45692
A7: Michael Ameling | B7: Cross Architecture | C7: Bharati Yadav (bharati.yadav@sap.com) | D7: Outbound OEM | E7: On-Premise | F7: P1 | G7: S2 | H7: Y | I7: Incremental ONLY | J7: OS 16.1 SP00 PL00 | K7: 45413 | L7: 45541 | M7: 45706 | N7: GTLC Canada | O7: Kanika | P7: Done | Q7: Y | R7: 45673 | S7: 45699 | AA7: 500000 | AB7: Open | AC7: No | AD7: Yes | AE7: C5380106 | AF7: 7.2 | AG7: 1.509434 | AH7: 160 | AI7: 3.2 | AJ7: 7.2 | AK7: 45608 | AM7: N | AN7: 0 | AS7: 45699
A8: Manoj Swaminathan | B8: ISBN CloudOps Cross COPS | C8: Arora, Aditya <aditya.arora@sap.com> | D8: Source Code | E8: On-Mobile Device | F8: P1 | G8: S2 | H8: Y | I8: Incremental ONLY | J8: SAP Mobile Start App 2.2 Android - SRC | L8: 45693 | M8: 45714 | N8: GTLC Germany | O8: Rajat | P8: Done | Q8: Y | R8: 45699 | S8: 45705 | AA8: 500000 | AB8: Open | AC8: No | AD8: Yes | AE8: I501689 | AF8: 7.6226415 | AG8: 1.509434 | AH8: 181.13208 | AI8: 3.6226415 | AJ8: 7.6226415 | AK8: 45694 | AL8: N | AM8: N | AN8: 8 | AS8: 45713
A9: Michael Ameling | B9: Cross Architecture | C9: Zhong, Gary <gary.zhong@sap.com> | D9: Outbound OEM | E9: On-Premise | F9: P1 | G9: S2 | H9: Y | I9: Incremental ONLY | J9: SRS 16.0 SP04 PL07 | L9: 45709 | M9: 45791 | N9: GTLC Germany | O9: Kanika | P9: Done | Q9: Y | R9: 45742 | S9: 45765 | AA9: 500000 | AB9: Open | AC9: No | AD9: Yes | AE9: C5380106 | AF9: 7.2603774 | AG9: 1.509434 | AH9: 163.01887 | AI9: 3.2603774 | AJ9: 7.2603774 | AK9: 45714 | AL9: N | AM9: N | AN9: 19 | AS9: 45784
A10: Irfan Khan | B10: SAP HANA Database & Analytics | C10: Limberg, Angie <angie.limberg@sap.com> | D10: Outbound OEM | E10: On-Premise | F10: P1 | G10: S2 | H10: Y | I10: Incremental ONLY | J10: SAP HANA Cloud Integration,DS 2506 (1.0.11.57) | K10: 45744 | L10: 45798 | M10: 45835 | N10: GTLC Canada | O10: Mengjie | P10: Done | Q10: Y | R10: 45820 | S10: 45834 | AA10: 500000 | AB10: Open | AC10: No | AD10: Yes | AE10: C5390744 | AF10: 7.6528302 | AG10: 1.509434 | AH10: 182.64151 | AI10: 3.6528302 | AJ10: 7.6528302 | AK10: 45796 | AL10: N | AM10: N | AN10: 0 | AO10: 3 | AP10: 0 | AQ10: 7 | AS10: 45834
A11: Irfan Khan | B11: SAP HANA Database & Analytics | C11: Simonson, Randy<randy.simonson@sap.com> | D11: Outbound OEM | E11: On-Premise | F11: P1 | G11: S2 | H11: Y | I11: Incremental ONLY | J11: SAP Data Quality Management SDK 2025 | K11: 45512 | L11: 45793 | M11: 45835 | N11: GTLC Canada | O11: Kanika | P11: Done | Q11: Y | R11: 45819 | S11: 45835 | AA11: 500000 | AB11: Open | AC11: No | AD11: Yes | AE11: C5380106 | AF11: 7.9849057 | AG11: 1.509434 | AH11: 199.24528 | AI11: 3.9849057 | AJ11: 7.9849057 | AK11: 45811 | AL11: N | AM11: N | AN11: -14 | AO11: 17 | AP11: 0 | AQ11: 391 | AS11: 45821
A12: Manoj Swaminathan | B12: ISBN CloudOps Cross COPS | C12: Huang, Allen <allen.huang@sap.com> | D12: Outbound OEM | E12: On-Premise | F12: P1 | G12: S2 | H12: Y | I12: Incremental ONLY | J12: B1 10.0 FP 2508 | L12: 45800 | M12: 45842 | N12: GTLC Germany | O12: Duane | P12: Done | Q12: Y | R12: 45819 | S12: 45881 | AA12: 500000 | AB12: Open | AC12: No | AD12: Yes | AE12: C5380108 | AF12: 8.0150943 | AG12: 1.509434 | AH12: 200.75472 | AI12: 4.0150943 | AJ12: 8.0150943 | AK12: 45811 | AL12: N | AM12: N | AN12: -41 | AO12: 2498 | AP12: 721 | AQ12: 26704 | AS12: 45840
A13: Irfan Khan | B13: SAP HANA Database & Analytics | C13: Limberg, Angie <angie.limberg@sap.com> | D13: Outbound OEM | E13: On-Premise | F13: P1 | G13: S2 | H13: Y | I13: Incremental ONLY | J13: SAP HANA Cloud Integration,DS 2509 (1.0.11.58) | K13: 45838 | L13: 45866 | M13: 45905 | N13: GTLC Vietnam | O13: Dong | P13: Done | Q13: Y | R13: 45881 | S13: 45888 | AA13: 500000 | AB13: Open | AC13: No | AD13: Yes | AE13: I758010 | AF13: 7.3207547 | AG13: 1.509434 | AH13: 166.03774 | AI13: 3.3207547 | AJ13: 7.3207547 | AK13: 45869 | AL13: N | AM13: N | AN13: 16 | AO13: 5 | AP13: 0 | AQ13: 0 | AS13: 45904
A14: Michael Ameling | B14: Cross Architecture | C14: Zhong, Gary <gary.zhong@sap.com> | D14: Outbound OEM | E14: On-Premise | F14: P1 | G14: S2 | H14: Y | I14: Incremental ONLY | J14: SRS 16.1 SP00 PL01 | L14: 45834 | M14: 45910 | N14: GTLC Vietnam | O14: Luyen | P14: Done | Q14: Y | R14: 45870 | S14: 45875 | AA14: 500000 | AB14: Open | AC14: No | AD14: Yes | AE14: I516362 | AF14: 7.4113208 | AG14: 1.509434 | AH14: 170.56604 | AI14: 3.4113208 | AJ14: 7.4113208 | AK14: 45470 | AL14: N | AM14: N | AN14: 27 | AO14: 12 | AP14: 3 | AQ14: 1 | AS14: 45902
A15: Michael Ameling | B15: Cross Architecture | C15: Dong, Zhi-peng <zhi-peng.dong@sap.com> | D15: Outbound OEM | E15: On-Premise | F15: P1 | G15: S2 | H15: Y | I15: Incremental ONLY | J15: ASE 16.1 SP00 PL01 | L15: 45835 | M15: 45910 | N15: GTLC Vietnam | O15: Khoa | P15: Done | Q15: Y | R15: 45870 | S15: 45887 | AA15: 500000 | AB15: Open | AC15: No | AD15: Yes | AE15: I758929 | AF15: 7.4415094 | AG15: 1.509434 | AH15: 172.07547 | AI15: 3.4415094 | AJ15: 7.4415094 | AK15: 45476 | AL15: N | AM15: N | AN15: 15 | AO15: 804 | AP15: 5 | AQ15: 714 | AS15: 45902
A16: Balaji Balasubramanian | B16: BTP HANA Mgmt Office | C16: Malten, Claus<claus.malten@sap.com> | D16: Source Code | E16: On-Premise | F16: P1 | G16: S2 | H16: Y | I16: Incremental ONLY | J16: Telco and Utilities Accelerator 2025-Q3-JDK21 | L16: 45919 | M16: 45930 | N16: GTLC Vietnam | O16: Khoa | P16: Done | Q16: Y | R16: 45924 | S16: 45929 | AA16: 500000 | AB16: Open | AC16: No | AD16: Yes | AE16: I758929 | AF16: 7.4113208 | AG16: 1.509434 | AH16: 170.56604 | AI16: 3.4113208 | AJ16: 7.4113208 | AK16: 45923 | AL16: N | AM16: N | AN16: -3 | AO16: 65 | AP16: 1 | AQ16: 233 | AS16: 45926
A17: Uma Rani T M | B17: Strategy & Transformation, Customer Success | C17: BAR, Pascal<pascal.bar@sap.com> | D17: Outbound OEM | E17: On-Premise | F17: P1 | G17: S2 | H17: Y | I17: Incremental ONLY | J17: SAP Convergent Charging 2025_FPS0 | K17: 45695 | L17: 45863 | M17: 45938 | N17: GTLC Vietnam | O17: Khoa | P17: Done | Q17: Y | R17: 45929 | S17: 45939 | AA17: 500000 | AB17: Open | AC17: No | AD17: Yes | AE17: I758929 | AF17: 7.5018868 | AG17: 1.509434 | AH17: 175.09434 | AI17: 3.5018868 | AJ17: 7.5018868 | AK17: 45926 | AL17: N | AM17: N | AN17: -6 | AO17: 449 | AP17: 174 | AQ17: 192 | AS17: 45933
A18: Uma Rani T M | B18: Strategy & Transformation, Customer Success | C18: MEGEVAND,Emmanuel<emmanuel.megevand@sap.com> | D18: Outbound OEM | E18: On-Premise | F18: P1 | G18: S2 | H18: Y | I18: Incremental ONLY | J18: SAP Information Steward 2025 | L18: 45939 | M18: 45975 | N18: GTLC China | O18: Nguyen | P18: Done | Q18: Y | R18: 45966 | S18: 45971 | AA18: 500000 | AB18: Open | AC18: No | AD18: Yes | AE18: I762314 | AF18: 8.1962264 | AG18: 1.509434 | AH18: 209.81132 | AI18: 4.1962264 | AJ18: 8.1962264 | AK18: 45939 | AL18: N | AM18: N | AN18: 0 | AO18: 187 | AP18: 0 | AQ18: 2500 | AS18: 45971
A19: Uma Rani T M | B19: Strategy & Transformation, Customer Success | C19: Gopal, Manjunath<manjunath.gopal@sap.com> | D19: On-Premise | E19: On-Premise | F19: P1 | G19: S2 | H19: Y | I19: Incremental ONLY | J19: SAP PQM OP 2025 | K19: 45848 | L19: 45888 | M19: 45987 | N19: GTLC Vietnam | O19: Hoan | P19: Done | Q19: Y | R19: 45936 | S19: 45974 | AA19: 500000 | AB19: Open | AC19: No | AD19: Yes | AE19: I758150 | AF19: 7.5018868 | AG19: 1.509434 | AH19: 175.09434 | AI19: 3.5018868 | AJ19: 7.5018868 | AK19: 45926 | AL19: N | AM19: N | AN19: 11 | AO19: 641 | AP19: 0 | AQ19: 0 | AS19: 45985
A20: Uma Rani T M | B20: Strategy & Transformation, Customer Success | C20: Ramprasad, Shobana<shobana.ramprasad@sap.com> | D20: Source Code | E20: On-Premise | F20: P1 | G20: S2 | H20: Y | I20: Incremental ONLY | J20: S/4HANA Payment Engine 1.0 | K20: 45702 | L20: 45947 | M20: 45989 | N20: GTLC Vietnam | O20: Dong | P20: Done | Q20: Y | R20: 45987 | S20: 45994 | AA20: 500000 | AB20: Open | AC20: No | AD20: Yes | AE20: I758010 | AF20: 7.5320755 | AG20: 1.509434 | AH20: 176.60377 | AI20: 3.5320755 | AJ20: 7.5320755 | AK20: 45986 | AL20: N | AM20: N | AN20: -7 | AO20: 0 | AP20: 0 | AQ20: 0 | AS20: 45987
A21: Michael Ameling | B21: Cross Architecture | C21: Samdekar, Sharwari<sharwari.manoj.samdekar@sap.com> | D21: Outbound OEM | E21: On-Premise | F21: P1 | G21: S2 | H21: Y | I21: Incremental ONLY | J21: OS 16.0 SP04 PL08 | K21: 45863 | L21: 45902 | M21: 46001 | N21: GTLC China | O21: Liye | P21: Done | Q21: Y | R21: 45944 | S21: 45964 | AA21: 500000 | AB21: Open | AC21: No | AD21: Yes | AE21: I853975 | AF21: 7.5622642 | AG21: 1.509434 | AH21: 178.11321 | AI21: 3.5622642 | AJ21: 7.5622642 | AK21: 45926 | AL21: N | AM21: N | AN21: 44 | AO21: 0 | AP21: 0 | AQ21: 129 | AS21: 45994
A22: Michael Ameling | B22: Cross Architecture | C22: Samdekar, Sharwari<sharwari.manoj.samdekar@sap.com> | D22: Outbound OEM | E22: On-Premise | F22: P1 | G22: S2 | H22: Y | I22: Incremental ONLY | J22: SDK 16.0 SP04 PL08 | K22: 45863 | L22: 45902 | M22: 46001 | N22: GTLC Vietnam | O22: Nguyen | P22: Done | Q22: Y | R22: 45944 | S22: 45950 | AA22: 500000 | AB22: Open | AC22: No | AD22: Yes | AE22: I762314 | AF22: 7.5924528 | AG22: 1.509434 | AH22: 179.62264 | AI22: 3.5924528 | AJ22: 7.5924528 | AK22: 45926 | AL22: N | AM22: N | AN22: 44 | AO22: 7 | AP22: 0 | AQ22: 278 | AS22: 45994
A23: Michael Ameling | B23: Cross Architecture | C23: Zhong, Gary <gary.zhong@sap.com> | D23: Outbound OEM | E23: On-Premise | F23: P1 | G23: S2 | H23: Y | I23: Incremental ONLY | J23: SRS 16.0 SP04 PL08 | L23: 45918 | M23: 46001 | N23: GTLC Vietnam | O23: Thao | P23: Done | Q23: Y | R23: 45944 | S23: 45957 | AA23: 500000 | AB23: Open | AC23: No | AD23: Yes | AE23: I758015 | AF23: 7.6830189 | AG23: 1.509434 | AH23: 184.15094 | AI23: 3.6830189 | AJ23: 7.6830189 | AK23: 45926 | AL23: N | AM23: N | AN23: 37 | AO23: 3 | AP23: 1 | AQ23: 3 | AS23: 45994
A24: Uma Rani T M | B24: Strategy & Transformation, Customer Success | C24: MRAK, Ivan<ivan.mrak@sap.com> | D24: On-Premise | E24: On-Premise | F24: P1 | G24: S2 | H24: Y | I24: Incremental ONLY | J24: SAP LUMIRA DESIGNER 2025 | L24: 45968 | M24: 46052 | N24: GTLC Vietnam | O24: Khoa | P24: Done | Q24: Y | R24: 45995 | S24: 46002 | AA24: 500000 | AB24: Open | AC24: No | AD24: Yes | AE24: I758929 | AF24: 7.6528302 | AG24: 1.509434 | AH24: 182.64151 | AI24: 3.6528302 | AJ24: 7.6528302 | AK24: 45938 | AL24: N | AM24: N | AN24: 42 | AS24: 46044
A25: Michael Ameling | B25: Cross Architecture | C25: Dong, Zhi-peng <zhi-peng.dong@sap.com> | D25: Outbound OEM | E25: On-Premise | F25: P1 | G25: S3 | H25: N | I25: Incremental ONLY | J25: ASE 16.1 SP00 PL00 | L25: 45617 | M25: 45706 | N25: GTLC Canada | O25: Devanshi | P25: Done | Q25: Y | R25: 45602 | S25: 45699 | Z25: Consultant assignment | AA25: 500000 | AB25: Open | AC25: No | AD25: Yes | AE25: C5380104 | AF25: 7.954717 | AG25: 15.09434 | AH25: 197.73585 | AI25: 3.954717 | AJ25: 7.954717 | AK25: 45582 | AL25: N | AM25: N | AN25: 0 | AS25: 45699
A26: Michael Ameling | B26: Cross Architecture | C26: Zhong, Gary <gary.zhong@sap.com> | D26: Outbound OEM | E26: On-Premise | F26: P1 | G26: S4 | H26: Y | I26: Incremental ONLY | J26: SRS 16.1 SP00 PL00 | L26: 45617 | M26: 45706 | N26: GTLC Canada | O26: Kanika | P26: Done | Q26: Y | R26: 45602 | S26: 45674 | Z26: Consultant assignment | AA26: 500000 | AB26: Open | AC26: No | AD26: Yes | AE26: C5380106 | AF26: 7.9849057 | AG26: 1.509434 | AH26: 199.24528 | AI26: 3.9849057 | AJ26: 7.9849057 | AK26: 45582 | AL26: N | AM26: N | AN26: 25 | AS26: 45699
A27: Manoj Swaminathan | B27: ISBN CloudOps Cross COPS | C27: Huang, Allen <allen.huang@sap.com> | D27: Outbound OEM | E27: On-Premise | F27: P1 | G27: S4 | H27: Y | I27: Incremental ONLY | J27: B1 10.0 FP 2502 | K27: 45537 | L27: 45618 | M27: 45716 | N27: GTLC China | O27: Yi Zhang | P27: Done | Q27: Y | R27: 45643 | S27: 45666 | AA27: 500000 | AB27: Open | AC27: No | AD27: Yes | AE27: I559269 | AF27: 8.0150943 | AG27: 1.509434 | AH27: 200.75472 | AI27: 4.0150943 | AJ27: 8.0150943 | AK27: 45614 | AL27: N | AM27: N | AN27: 50 | AS27: 45716
A28: Irfan Khan | B28: SAP HANA Database & Analytics | C28: Limberg, Angie <angie.limberg@sap.com> | D28: Outbound OEM | E28: On-Premise | F28: P1 | G28: S4 | H28: Y | I28: Incremental ONLY | J28: SAP HANA Cloud Integration,DS 2503 (1.0.11.56) | K28: 45596 | L28: 45722 | M28: 45750 | N28: GTLC Vietnam | O28: Dong | P28: Done | Q28: Y | R28: 45356 | S28: 45727 | AA28: 500000 | AB28: Open | AC28: No | AD28: Yes | AE28: I758010 | AF28: 8.045283 | AG28: 1.509434 | AH28: 202.26415 | AI28: 4.045283 | AJ28: 8.045283 | AK28: 45635 | AL28: N | AM28: N | AN28: -242 | AS28: 45485
A29: Michael Ameling | B29: Cross Architecture | C29: Wang, Haiqiang <haiqiang.wang01@sap.com> | D29: Outbound OEM | E29: On-Premise | F29: P1 | G29: S4 | H29: Y | I29: Incremental ONLY | J29: ASE 16.0 SP04 PL07 | L29: 45756 | M29: 45791 | N29: GTLC Vietnam | O29: Luyen | P29: Done | Q29: Y | R29: 45758 | S29: 45775 | AA29: 500000 | AB29: Open | AC29: No | AD29: Yes | AE29: I516362 | AF29: 8.1358491 | AG29: 1.509434 | AH29: 206.79245 | AI29: 4.1358491 | AJ29: 8.1358491 | AK29: 45727 | AL29: N | AM29: N | AN29: -27 | AS29: 45748
A30: Michael Ameling | B30: Cross Architecture | C30: Liu, Feng <feng.liu01@sap.com> | D30: Outbound OEM | E30: On-Premise | F30: P1 | G30: S4 | H30: Y | I30: Incremental ONLY | J30: SDK 16.0 SP04 PL07 | K30: 45616 | L30: 45737 | M30: 45791 | N30: GTLC Germany | O30: Devanshi | P30: Done | Q30: Y | R30: 45742 | S30: 45765 | AA30: 500000 | AB30: Open | AC30: No | AD30: Yes | AE30: C5380104 | AF30: 8.1056604 | AG30: 1.509434 | AH30: 205.28302 | AI30: 4.1056604 | AJ30: 8.1056604 | AK30: 45714 | AL30: N | AM30: N | AN30: 19 | AS30: 45784
A31: Michael Ameling | B31: Cross Architecture | C31: Liu, Feng <feng.liu01@sap.com> | D31: Outbound OEM | E31: On-Premise | F31: P1 | G31: S4 | H31: Y | I31: Incremental ONLY | J31: OS 16.0 SP04 PL07 | K31: 45616 | L31: 45737 | M31: 45791 | N31: GTLC Germany | O31: Duane | P31: Done | Q31: Y | R31: 45742 | S31: 45750 | AA31: 500000 | AB31: Open | AC31: No | AD31: Yes | AE31: C5380108 | AF31: 8.1358491 | AG31: 1.509434 | AH31: 206.79245 | AI31: 4.1358491 | AJ31: 8.1358491 | AK31: 45714 | AL31: N | AM31: N | AN31: 34 | AS31: 45784
A32: Manoj Swaminathan | B32: ISBN CloudOps Cross COPS | C32: Schmitt, Frank <frank.schmitt@sap.com> | D32: Source Code | E32: On-Mobile Device | F32: P1 | G32: S4 | H32: Y | I32: Incremental ONLY | J32: SAP Mobile Start App 2.3 iOS - SRC | L32: 45784 | M32: 45805 | N32: GTLC Vietnam | O32: Ngoc | P32: Done | Q32: Y | R32: 45782 | S32: 45790 | AA32: 500000 | AB32: Open | AC32: No | AD32: Yes | AE32: I758014 | AF32: 8.2264151 | AG32: 1.509434 | AH32: 211.32075 | AI32: 4.2264151 | AJ32: 8.2264151 | AK32: 45706 | AL32: N | AM32: N | AN32: 13 | AS32: 45803
A33: Uma Rani T M | B33: Strategy & Transformation, Customer Success | C33: Gelle, Sreenivasulu <sreenivasulu.gelle@sap.com> | D33: Outbound OEM | E33: On-Premise | F33: P1 | G33: S4 | H33: Y | I33: Incremental ONLY | J33: SAP Data Services 2025 | K33: 45516 | L33: 45807 | M33: 45835 | N33: GTLC Canada | O33: Devanshi | P33: Done | Q33: Y | R33: 45819 | S33: 45835 | AA33: 500000 | AB33: Open | AC33: No | AD33: Yes | AE33: C5380104 | AF33: 9.7358491 | AG33: 1.509434 | AH33: 286.79245 | AI33: 5.7358491 | AJ33: 9.7358491 | AK33: 45810 | AL33: N | AM33: N | AN33: -7 | AO33: 179 | AP33: 0 | AQ33: 2659 | AS33: 45828
A34: Michael Ameling | B34: Cross Architecture | C34: Schmitt, Frank <frank.schmitt@sap.com> | D34: Source Code | E34: On-Mobile Device | F34: P1 | G34: S4 | H34: Y | I34: Incremental ONLY | J34: SAP Mobile Start App 2.4 iOS - SRC | L34: 45854 | M34: 45875 | N34: GTLC Vietnam | O34: Luyen | P34: Done | Q34: Y | R34: 45861 | S34: 45863 | AA34: 500000 | AB34: Open | AC34: No | AD34: Yes | AE34: I516362 | AF34: 10.037736 | AG34: 1.509434 | AH34: 301.88679 | AI34: 6.0377358 | AJ34: 10.037736 | AK34: 45792 | AL34: N | AM34: N | AN34: 10 | AO34: 11 | AP34: 6 | AQ34: 45 | AS34: 45873
A35: Michael Ameling | B35: Cross Architecture | C35: Arora, Aditya <aditya.arora@sap.com> | D35: Source Code | E35: On-Mobile Device | F35: P1 | G35: S4 | H35: Y | I35: Incremental ONLY | J35: SAP Mobile Start App 2.4 Android - SRC | L35: 45854 | M35: 45875 | N35: GTLC Vietnam | O35: Huu | P35: Done | Q35: Y | R35: 45862 | S35: 45867 | AA35: 500000 | AB35: Open | AC35: No | AD35: Yes | AE35: I758016 | AF35: 9.7358491 | AG35: 1.509434 | AH35: 286.79245 | AI35: 5.7358491 | AJ35: 9.7358491 | AK35: 45792 | AL35: N | AM35: N | AN35: 6 | AO35: 116 | AP35: 207 | AQ35: 277 | AR35: -81 | AS35: 45873
A36: Michael Ameling | B36: Cross Architecture | C36: Liu, Feng<feng.liu01@sap.com> | D36: Outbound OEM | E36: On-Premise | F36: P1 | G36: S4 | H36: Y | I36: Incremental ONLY | J36: SDK 16.1 SP00 PL01 | K36: 45737 | L36: 45863 | M36: 45910 | N36: GTLC Vietnam | O36: Khoi | P36: Done | Q36: Y | R36: 45870 | S36: 45875 | AA36: 500000 | AB36: Open | AC36: No | AD36: Yes | AE36: I758929 | AF36: 8.2867925 | AG36: 1.509434 | AH36: 214.33962 | AI36: 4.2867925 | AJ36: 8.2867925 | AK36: 45737 | AL36: N | AM36: N | AN36: 27 | AO36: 45 | AP36: 0 | AQ36: 664 | AS36: 45902
A37: Michael Ameling | B37: Cross Architecture | C37: Liu, Feng<feng.liu01@sap.com> | D37: Outbound OEM | E37: On-Premise | F37: P1 | G37: S4 | H37: Y | I37: Incremental ONLY | J37: OS 16.1 SP00 PL01 | K37: 45737 | L37: 45863 | M37: 45910 | N37: GTLC Vietnam | O37: Nguyen | P37: Done | Q37: Y | R37: 45870 | S37: 45888 | AA37: 500000 | AB37: Open | AC37: No | AD37: Yes | AE37: I762314 | AF37: 8.3169811 | AG37: 1.509434 | AH37: 215.84906 | AI37: 4.3169811 | AJ37: 8.3169811 | AK37: 45737 | AL37: N | AM37: N | AN37: 14 | AS37: 45902
A38: Irfan Khan | B38: SAP HANA Database & Analytics | C38: Limberg, Angie <angie.limberg@sap.com> | D38: Outbound OEM | E38: On-Premise | F38: P1 | G38: S4 | H38: Y | I38: Incremental ONLY | J38: SAP HANA Cloud Integration,DS 2509 2511 (1.0.11.59) | K38: 45929 | L38: 45944 | M38: 45968 | N38: GTLC Vietnam | O38: Khoa | P38: Done | Q38: Y | R38: 45944 | S38: 45954 | AA38: 500000 | AB38: Open | AC38: No | AD38: Yes | AE38: I758929 | AF38: 8.3471698 | AG38: 1.509434 | AH38: 217.35849 | AI38: 4.3471698 | AJ38: 8.3471698 | AK38: 45939 | AL38: N | AM38: N | AN38: 12 | AS38: 45966
A39: Augusta SPINELLI | B39: Services Head, Southern Europe,MEA | C39: Kumar, Vivek<vivek.kumar11@sap.com> | D39: Source Code | E39: On-Premise | F39: P2 | G39: S1 | H39: N | I39: Incremental ONLY | J39: 305592123_CSD_Business_Partner_Hilti_AG | K39: 45677 | L39: 45695 | M39: 45698 | N39: GTLC India | O39: Apoorva | P39: Done | Q39: Y | R39: 45698 | S39: 45698 | AA39: 500000 | AB39: Open | AC39: No | AD39: Yes | AE39: C5367590 | AF39: 8.6490566 | AG39: 15.09434 | AH39: 232.45283 | AI39: 4.6490566 | AJ39: 8.6490566 | AK39: 45686 | AL39: N | AM39: N | AN39: -3 | AS39: 45695
A40: Stefan Steinle | B40: Customer Solution Support and Innovation | C40: Kabadzhova, Kremena <kremena.kabadzhova@sap.com> | D40: Source Code | E40: On-Premise | F40: P2 | G40: S1 | H40: Y | I40: Incremental ONLY | J40: SAP Cloud Appliance Library 4.41 | L40: 45694 | M40: 45713 | N40: GTLC India | O40: Gaurisha | P40: Done | Q40: Y | R40: 45698 | S40: 45701 | AA40: 500000 | AB40: Open | AC40: No | AD40: Yes | AE40: I748895 | AF40: 8.6792453 | AG40: 1.509434 | AH40: 233.96226 | AI40: 4.6792453 | AJ40: 8.6792453 | AK40: 45664 | AL40: Y | AM40: N | AN40: 7 | AS40: 45708
A41: Michael Ameling | B41: Cross Architecture | C41: Dubbrow, Patrick <patrick.dubbrow@sap.com> | D41: On-Premise | E41: On-Premise | F41: P2 | G41: S1 | H41: N | I41: Incremental ONLY | J41: ABAP Platform 2023 SP03 (indirect) | K41: 45509 | L41: 45579 | M41: 45714 | N41: GTLC Germany | O41: Rajat | P41: Done | Q41: Y | R41: 45645 | S41: 45674 | AA41: 500000 | AB41: Open | AC41: No | AD41: Yes | AE41: I501689 | AF41: 9.3132075 | AG41: 15.09434 | AH41: 265.66038 | AI41: 5.3132075 | AJ41: 9.3132075 | AK41: 45643 | AL41: N | AM41: N | AN41: -326 | AS41: 45348
A42: Augusta SPINELLI | B42: Services Head, Southern Europe,MEA | C42: Kumar, Vivek <vivek.kumar11@sap.com> | D42: Source Code | E42: On-Premise | F42: P2 | G42: S1 | H42: N | I42: Incremental ONLY | J42: 305302302_CSD_CHARTER_CLIENT_TAX_WIENIT_GMBH | K42: 45656 | L42: 45709 | M42: 45719 | N42: GTLC Germany | O42: Frazia | P42: Done | Q42: Y | R42: 45686 | S42: 45694 | AA42: 500000 | AB42: Open | AC42: No | AD42: Yes | AE42: I588032 | AF42: 9.2830189 | AG42: 15.09434 | AH42: 264.15094 | AI42: 5.2830189 | AJ42: 9.2830189 | AK42: 45672 | AL42: N | AM42: N | AN42: -14 | AS42: 45680
A43: Stefan Steinle | B43: Customer Solution Support and Innovation | C43: Kabadzhova, Kremena <kremena.kabadzhova@sap.com> | D43: Source Code | E43: On-Premise | F43: P2 | G43: S1 | H43: Y | I43: Incremental ONLY | J43: SAP Cloud Appliance Library 4.42 | L43: 45694 | M43: 45736 | N43: GTLC Vietnam | O43: Huu | P43: Done | Q43: Y | R43: 45723 | S43: 45729 | AA43: 500000 | AB43: Open | AC43: No | AD43: Yes | AE43: I758016 | AF43: 6.0226415 | AG43: 1.509434 | AH43: 101.13208 | AI43: 2.0226415 | AJ43: 6.0226415 | AK43: 45664 | AL43: Y | AM43: N | AN43: -21 | AS43: 45708
A44: Stefan Steinle | B44: Customer Solution Support and Innovation | C44: Kabadzhova, Kremena <kremena.kabadzhova@sap.com> | D44: Source Code | E44: On-Premise | F44: P2 | G44: S1 | H44: Y | I44: Incremental ONLY | J44: SAP Cloud Appliance Library 4.43 | L44: 45694 | M44: 45764 | N44: GTLC Vietnam | O44: Huu | P44: Done | Q44: Y | R44: 45758 | S44: 45762 | AA44: 500000 | AB44: Open | AC44: No | AD44: Yes | AE44: I758016 | AF44: 9.3433962 | AG44: 1.509434 | AH44: 267.16981 | AI44: 5.3433962 | AJ44: 9.3433962 | AK44: 45664 | AL44: Y | AM44: N | AN44: -54 | AS44: 45708
A45: Stefan Steinle | B45: Customer Solution Support and Innovation | C45: Kabadzhova, Kremena <kremena.kabadzhova@sap.com> | D45: Source Code | E45: On-Premise | F45: P2 | G45: S1 | H45: Y | I45: Incremental ONLY | J45: SAP Cloud Appliance Library 4.44 | L45: 45694 | M45: 45792 | N45: GTLC Vietnam | O45: Huu | P45: Done | Q45: Y | R45: 45785 | S45: 45786 | AA45: 500000 | AB45: Open | AC45: No | AD45: Yes | AE45: I758016 | AF45: 9.3735849 | AG45: 1.509434 | AH45: 268.67925 | AI45: 5.3735849 | AJ45: 9.3735849 | AK45: 45664 | AL45: Y | AM45: N | AN45: -78 | AS45: 45708
A46: Dominik Metzger | B46: People Growth Management Office UK | C46: Woessner, Philipp <philipp.woessner@sap.com> | D46: On-Mobile Device | E46: On-Mobile Device | F46: P2 | G46: S1 | H46: Y | I46: Incremental ONLY | J46: SAP Logistics Management Mobile 1.0-Beta | L46: 45784 | M46: 45796 | N46: GTLC India | O46: Apoorva | P46: Done | Q46: Y | R46: 45796 | S46: 45800 | AA46: 500000 | AB46: Open | AC46: No | AD46: Yes | AE46: C5367590 | AF46: 9.4037736 | AG46: 1.509434 | AH46: 270.18868 | AI46: 5.4037736 | AJ46: 9.4037736 | AK46: 45784 | AL46: N | AM46: N | AN46: -7 | AS46: 45793
A47: Dominik Metzger | B47: People Growth Management Office UK | C47: Woessner, Philipp <philipp.woessner@sap.com> | D47: On-Mobile Device | E47: On-Mobile Device | F47: P2 | G47: S1 | H47: Y | I47: Incremental ONLY | J47: SAP Build Apps App Runtime 2504 | L47: 45799 | M47: 45803 | N47: GTLC Canada | O47: Devanshi | P47: Done | Q47: Y | R47: 45800 | S47: 45834 | AA47: 500000 | AB47: Open | AC47: No | AD47: Yes | AE47: C5380104 | AF47: 12.845283 | AG47: 1.509434 | AH47: 442.26415 | AI47: 8.845283 | AJ47: 12.845283 | AK47: 45799 | AL47: N | AM47: N | AN47: -31 | AS47: 45803
A48: Jan Gilg | B48: SAP S/4 HANA | C48: Beck, Cornelius <cornelius.beck@sap.com> | D48: On-Premise | E48: On-Premise | F48: P2 | G48: S1 | H48: N | I48: Incremental ONLY | J48: SAP Customer Checkout point-of-sale 3.0 | K48: 45580 | L48: 45782 | M48: 45813 | N48: GTLC China | O48: Yi Zhang | P48: Done | Q48: Y | R48: 45797 | S48: 45803 | AA48: 500000 | AB48: Open | AC48: No | AD48: Yes | AE48: I559269 | AF48: 9.7358491 | AG48: 15.09434 | AH48: 286.79245 | AI48: 5.7358491 | AJ48: 9.7358491 | AK48: 45777 | AL48: N | AM48: N | AN48: 14 | AS48: 45817
A49: Sindhu Gangadharan | B49: SAP User Enabl Mgmt SE | C49: Riegel,Lukas <lukas.riegel@sap.com> | D49: Source Code | E49: On-Premise | F49: P2 | G49: S1 | H49: N | I49: Incremental ONLY | J49: 305504569_CSD_OMV_AI_use_cases_OMV_AG | L49: 45803 | M49: 45814 | N49: GTLC Canada | O49: Kanika | P49: Done | Q49: Y | R49: 45828 | S49: 45828 | AA49: 500000 | AB49: Open | AC49: No | AD49: Yes | AE49: C5380106 | AF49: 12.90566 | AG49: 15.09434 | AH49: 445.28302 | AI49: 8.9056604 | AJ49: 12.90566 | AK49: 45803 | AL49: N | AM49: N | AN49: -25 | AS49: 45803
A50: Sindhu Gangadharan | B50: SAP User Enabl Mgmt SE | C50: Riegel,Lukas <lukas.riegel@sap.com> | D50: Source Code | E50: On-Premise | F50: P2 | G50: S1 | H50: N | I50: Incremental ONLY | J50: 305504569_CSD_OMV_AI_use_cases_OMV_AG (SEV) | L50: 45803 | M50: 45814 | N50: GTLC Canada | O50: Kanika | P50: Done | Q50: Y | R50: 45753 | S50: 45812 | AA50: 500000 | AB50: Open | AC50: No | AD50: Yes | AE50: C5380106 | AF50: 13.207547 | AG50: 15.09434 | AH50: 460.37736 | AI50: 9.2075472 | AJ50: 13.207547 | AK50: 45803 | AL50: N | AM50: N | AN50: -9 | AS50: 45803
